Workbook

Sheet README
A1: BrewCo Coffee Chain — Small Business Financial Model
A2: Built by Minh Hoang | FP&A Specialist | minhhoang1289@gmail.com
A4: ABOUT THIS MODEL
A5: Company | B5: BrewCo Coffee Chain — illustrative 3-location specialty coffee business (Vietnam market)
A6: Purpose | B6: Full financial planning model for small/medium business. Plug in your own numbers to generate P&L, Cash Flow, KPIs, Break-even and Scenario analysis automatically.
A7: Model Period | B7: 24 months (FY2025 + FY2026), monthly granularity
A8: Currency | B8: USD (can be adapted to VND — change headers only)
A9: Built With | B9: Excel-compatible formulas only. No macros. Works in Google Sheets.
A11: HOW TO USE
A12: Step 1 | B12: → Assumptions sheet: Change ONLY the blue cells — revenue per location, costs, growth rates, staff count. Everything else updates automatically.
A13: Step 2 | B13: → P&L sheet: Review monthly Profit & Loss. Green = profit, Red = loss. Check EBITDA and Net Income trends.
A14: Step 3 | B14: → Cash_Flow sheet: Check Ending Cash Balance. If it goes negative (red), adjust assumptions or add funding.
A15: Step 4 | B15: → Break_Even sheet: See exactly how many customers/day per location to cover costs. Sensitivity table included.
A16: Step 5 | B16: → KPI_Dashboard: Visual snapshot — Revenue, EBITDA Margin, Break-even progress. Present to investors/lenders.
A17: Step 6 | B17: → Scenario sheet: Compare Base vs Growth vs Conservative — change 1 assumption to stress-test the business.
A19: COLOUR GUIDE: Blue = Input (you change these) | Black = Formula (auto-calculated) | Green = Positive | Red = Negative | Yellow = Attention needed

Sheet Assumptions
A1: BrewCo Coffee Chain — Assumptions & Drivers
A2: Change ONLY blue cells. All other sheets update automatically. Blue = Input | Black = Formula
A4: Assumption | B4: Base Case | C4: Growth Case | D4: Conservative | E4: Notes
A5: REVENUE DRIVERS
A6: Number of Locations | B6: 3 | C6: 4 | D6: 2 | E6: Stores open at start of model
A7: Avg Daily Customers / Location | B7: 180 | C7: 220 | D7: 140 | E7: Peak season assumption
A8: Avg Ticket Size (USD) | B8: 6.5 | C8: 7.2 | D8: 5.8 | E8: Coffee + food average
A9: Monthly Revenue Growth Rate | B9: 0.008 | C9: 0.012 | D9: 0.003 | E9: Month-on-month growth
A10: Seasonal Peak Factor (Q4) | B10: 1.15 | C10: 1.2 | D10: 1.05 | E10: Nov-Dec uplift multiplier
A11: COST OF GOODS SOLD
A12: COGS % of Revenue | B12: 0.32 | C12: 0.3 | D12: 0.36 | E12: Coffee beans, milk, packaging
A13: Waste / Shrinkage % | B13: 0.02 | C13: 0.015 | D13: 0.03 | E13: Spoilage, over-pouring
A14: PAYROLL & STAFFING
A15: Staff per Location | B15: 6 | C15: 7 | D15: 5 | E15: Baristas + 1 supervisor
A16: Avg Monthly Salary / Staff (USD) | B16: 650 | C16: 700 | D16: 600 | E16: Including benefits
A17: Annual Salary Increase % | B17: 0.05 | C17: 0.06 | D17: 0.03 | E17: Jan-26 uplift
A18: OPERATING EXPENSES
A19: Rent per Location / Month (USD) | B19: 1800 | C19: 1800 | D19: 2000 | E19: Fixed — negotiated leases
A20: Utilities per Location / Month | B20: 350 | C20: 380 | D20: 420 | E20: Electric, water, internet
A21: Marketing % of Revenue | B21: 0.05 | C21: 0.07 | D21: 0.03 | E21: Digital + local campaigns
A22: G&A / Month (USD) | B22: 1200 | C22: 1400 | D22: 1000 | E22: Admin, accounting, legal
A23: Depreciation / Month (USD) | B23: 800 | C23: 900 | D23: 700 | E23: Equipment over 5yr life
A24: WORKING CAPITAL
A25: Days Sales Outstanding (DSO) | B25: 5 | C25: 5 | D25: 7 | E25: Cash business — near zero
A26: Days Payable Outstanding (DPO) | B26: 30 | C26: 35 | D26: 25 | E26: Supplier payment terms
A27: Inventory Days | B27: 7 | C27: 6 | D27: 10 | E27: Perishables — low stock
A28: CAPEX & FUNDING
A29: Opening Cash Balance (USD) | B29: 50000 | C29: 60000 | D29: 40000 | E29: Cash on hand at Jan-25
A30: Capex New Location (USD) | B30: 0 | C30: 35000 | D30: 0 | E30: Growth case: open 4th store Jul-26
A31: Loan Balance (USD) | B31: 80000 | C31: 80000 | D31: 80000 | E31: Existing bank loan
A32: Monthly Loan Repayment (USD) | B32: 2200 | C32: 2200 | D32: 2200 | E32: Principal + interest
A33: Tax Rate % | B33: 0.2 | C33: 0.2 | D33: 0.2 | E33: Corporate income tax

Sheet P&L
A1: BrewCo Coffee Chain — Monthly Income Statement (P&L)
A2: All figures in USD. Formulas pull from Assumptions sheet. Change assumptions there — this sheet auto-updates.
A4: Line Item | B4: Notes | C4: Jan-25 | D4: Feb-25 | E4: Mar-25 | F4: Apr-25 | G4: May-25 | H4: Jun-25 | I4: Jul-25 | J4: Aug-25 | K4: Sep-25 | L4: Oct-25 | M4: Nov-25 | N4: Dec-25 | O4: Jan-26 | P4: Feb-26 | Q4: Mar-26 | R4: Apr-26 | S4: May-26 | T4: Jun-26 | U4: Jul-26 | V4: Aug-26 | W4: Sep-26 | X4: Oct-26 | Y4: Nov-26 | Z4: Dec-26 | AA4: FY2025 | AB4: FY2026
A5: REVENUE
A6: Gross Revenue | B6: Loc×Cust×Ticket×26d | C6: =Assumptions!$B$5*Assumptions!$B$6*Assumptions!$B$7*26*(1+Assumptions!$B$8)^0 | D6: =Assumptions!$B$5*Assumptions!$B$6*Assumptions!$B$7*26*(1+Assumptions!$B$8)^1 | E6: =Assumptions!$B$5*Assumptions!$B$6*Assumptions!$B$7*26*(1+Assumptions!$B$8)^2 | F6: =Assumptions!$B$5*Assumptions!$B$6*Assumptions!$B$7*26*(1+Assumptions!$B$8)^3 | G6: =Assumptions!$B$5*Assumptions!$B$6*Assumptions!$B$7*26*(1+Assumptions!$B$8)^4 | H6: =Assumptions!$B$5*Assumptions!$B$6*Assumptions!$B$7*26*(1+Assumptions!$B$8)^5 | I6: =Assumptions!$B$5*Assumptions!$B$6*Assumptions!$B$7*26*(1+Assumptions!$B$8)^6 | J6: =Assumptions!$B$5*Assumptions!$B$6*Assumptions!$B$7*26*(1+Assumptions!$B$8)^7 | K6: =Assumptions!$B$5*Assumptions!$B$6*Assumptions!$B$7*26*(1+Assumptions!$B$8)^8 | L6: =Assumptions!$B$5*Assumptions!$B$6*Assumptions!$B$7*26*(1+Assumptions!$B$8)^9 | M6: =Assumptions!$B$5*Assumptions!$B$6*Assumptions!$B$7*26*(1+Assumptions!$B$8)^10*Assumptions!$B$9 | N6: =Assumptions!$B$5*Assumptions!$B$6*Assumptions!$B$7*26*(1+Assumptions!$B$8)^11*Assumptions!$B$9 | O6: =Assumptions!$B$5*Assumptions!$B$6*Assumptions!$B$7*26*(1+Assumptions!$B$8)^12 | P6: =Assumptions!$B$5*Assumptions!$B$6*Assumptions!$B$7*26*(1+Assumptions!$B$8)^13 | Q6: =Assumptions!$B$5*Assumptions!$B$6*Assumptions!$B$7*26*(1+Assumptions!$B$8)^14 | R6: =Assumptions!$B$5*Assumptions!$B$6*Assumptions!$B$7*26*(1+Assumptions!$B$8)^15 | S6: =Assumptions!$B$5*Assumptions!$B$6*Assumptions!$B$7*26*(1+Assumptions!$B$8)^16 | T6: =Assumptions!$B$5*Assumptions!$B$6*Assumptions!$B$7*26*(1+Assumptions!$B$8)^17 | U6: =Assumptions!$B$5*Assumptions!$B$6*Assumptions!$B$7*26*(1+Assumptions!$B$8)^18 | V6: =Assumptions!$B$5*Assumptions!$B$6*Assumptions!$B$7*26*(1+Assumptions!$B$8)^19 | W6: =Assumptions!$B$5*Assumptions!$B$6*Assumptions!$B$7*26*(1+Assumptions!$B$8)^20 | X6: =Assumptions!$B$5*Assumptions!$B$6*Assumptions!$B$7*26*(1+Assumptions!$B$8)^21 | Y6: =Assumptions!$B$5*Assumptions!$B$6*Assumptions!$B$7*26*(1+Assumptions!$B$8)^22*Assumptions!$B$9 | Z6: =Assumptions!$B$5*Assumptions!$B$6*Assumptions!$B$7*26*(1+Assumptions!$B$8)^23*Assumptions!$B$9 | AA6: =SUM(C6:N6) | AB6: =SUM(O6:Z6)
A7: Cost of Goods Sold | B7: COGS% + Waste% | C7: =-(C6*(Assumptions!$B$11+Assumptions!$B$12)) | D7: =-(D6*(Assumptions!$B$11+Assumptions!$B$12)) | E7: =-(E6*(Assumptions!$B$11+Assumptions!$B$12)) | F7: =-(F6*(Assumptions!$B$11+Assumptions!$B$12)) | G7: =-(G6*(Assumptions!$B$11+Assumptions!$B$12)) | H7: =-(H6*(Assumptions!$B$11+Assumptions!$B$12)) | I7: =-(I6*(Assumptions!$B$11+Assumptions!$B$12)) | J7: =-(J6*(Assumptions!$B$11+Assumptions!$B$12)) | ... Z7: =-(Z6*(Assumptions!$B$11+Assumptions!$B$12)) | AA7: =SUM(C7:N7) | AB7: =SUM(O7:Z7)
A8: Gross Profit | B8: Rev + COGS | C8: =C6+C7 | D8: =D6+D7 | E8: =E6+E7 | F8: =F6+F7 | G8: =G6+G7 | H8: =H6+H7 | I8: =I6+I7 | J8: =J6+J7 | ... Z8: =Z6+Z7 | AA8: =SUM(C8:N8) | AB8: =SUM(O8:Z8)
A9: Gross Margin % | B9: GP/Rev | C9: =IF(C6<>0,C8/C6,0) | D9: =IF(D6<>0,D8/D6,0) | E9: =IF(E6<>0,E8/E6,0) | F9: =IF(F6<>0,F8/F6,0) | G9: =IF(G6<>0,G8/G6,0) | H9: =IF(H6<>0,H8/H6,0) | I9: =IF(I6<>0,I8/I6,0) | J9: =IF(J6<>0,J8/J6,0) | ... Z9: =IF(Z6<>0,Z8/Z6,0) | AA9: =IF(C6<>0,C8/C6,0) | AB9: =IF(O6<>0,O8/O6,0)
A10: OPERATING EXPENSES
A11: Payroll & Benefits | C11: =-(Assumptions!$B$5*Assumptions!$B$14*Assumptions!$B$15*(1+IF(MOD(0,12)=0,Assumptions!$B$16,0))) | D11: =-(Assumptions!$B$5*Assumptions!$B$14*Assumptions!$B$15*(1+IF(MOD(1,12)=0,Assumptions!$B$16,0))) | E11: =-(Assumptions!$B$5*Assumptions!$B$14*Assumptions!$B$15*(1+IF(MOD(2,12)=0,Assumptions!$B$16,0))) | F11: =-(Assumptions!$B$5*Assumptions!$B$14*Assumptions!$B$15*(1+IF(MOD(3,12)=0,Assumptions!$B$16,0))) | G11: =-(Assumptions!$B$5*Assumptions!$B$14*Assumptions!$B$15*(1+IF(MOD(4,12)=0,Assumptions!$B$16,0))) | H11: =-(Assumptions!$B$5*Assumptions!$B$14*Assumptions!$B$15*(1+IF(MOD(5,12)=0,Assumptions!$B$16,0))) | I11: =-(Assumptions!$B$5*Assumptions!$B$14*Assumptions!$B$15*(1+IF(MOD(6,12)=0,Assumptions!$B$16,0))) | J11: =-(Assumptions!$B$5*Assumptions!$B$14*Assumptions!$B$15*(1+IF(MOD(7,12)=0,Assumptions!$B$16,0))) | K11: =-(Assumptions!$B$5*Assumptions!$B$14*Assumptions!$B$15*(1+IF(MOD(8,12)=0,Assumptions!$B$16,0))) | L11: =-(Assumptions!$B$5*Assumptions!$B$14*Assumptions!$B$15*(1+IF(MOD(9,12)=0,Assumptions!$B$16,0))) | M11: =-(Assumptions!$B$5*Assumptions!$B$14*Assumptions!$B$15*(1+IF(MOD(10,12)=0,Assumptions!$B$16,0))) | N11: =-(Assumptions!$B$5*Assumptions!$B$14*Assumptions!$B$15*(1+IF(MOD(11,12)=0,Assumptions!$B$16,0))) | O11: =-(Assumptions!$B$5*Assumptions!$B$14*Assumptions!$B$15*(1+IF(MOD(12,12)=0,Assumptions!$B$16,0))) | P11: =-(Assumptions!$B$5*Assumptions!$B$14*Assumptions!$B$15*(1+IF(MOD(13,12)=0,Assumptions!$B$16,0))) | Q11: =-(Assumptions!$B$5*Assumptions!$B$14*Assumptions!$B$15*(1+IF(MOD(14,12)=0,Assumptions!$B$16,0))) | R11: =-(Assumptions!$B$5*Assumptions!$B$14*Assumptions!$B$15*(1+IF(MOD(15,12)=0,Assumptions!$B$16,0))) | S11: =-(Assumptions!$B$5*Assumptions!$B$14*Assumptions!$B$15*(1+IF(MOD(16,12)=0,Assumptions!$B$16,0))) | T11: =-(Assumptions!$B$5*Assumptions!$B$14*Assumptions!$B$15*(1+IF(MOD(17,12)=0,Assumptions!$B$16,0))) | U11: =-(Assumptions!$B$5*Assumptions!$B$14*Assumptions!$B$15*(1+IF(MOD(18,12)=0,Assumptions!$B$16,0))) | V11: =-(Assumptions!$B$5*Assumptions!$B$14*Assumptions!$B$15*(1+IF(MOD(19,12)=0,Assumptions!$B$16,0))) | W11: =-(Assumptions!$B$5*Assumptions!$B$14*Assumptions!$B$15*(1+IF(MOD(20,12)=0,Assumptions!$B$16,0))) | X11: =-(Assumptions!$B$5*Assumptions!$B$14*Assumptions!$B$15*(1+IF(MOD(21,12)=0,Assumptions!$B$16,0))) | Y11: =-(Assumptions!$B$5*Assumptions!$B$14*Assumptions!$B$15*(1+IF(MOD(22,12)=0,Assumptions!$B$16,0))) | Z11: =-(Assumptions!$B$5*Assumptions!$B$14*Assumptions!$B$15*(1+IF(MOD(23,12)=0,Assumptions!$B$16,0))) | AA11: =SUM(C11:N11) | AB11: =SUM(O11:Z11)
A12: Rent | C12: =-(Assumptions!$B$5*Assumptions!$B$18) | D12: =-(Assumptions!$B$5*Assumptions!$B$18) | E12: =-(Assumptions!$B$5*Assumptions!$B$18) | F12: =-(Assumptions!$B$5*Assumptions!$B$18) | G12: =-(Assumptions!$B$5*Assumptions!$B$18) | H12: =-(Assumptions!$B$5*Assumptions!$B$18) | I12: =-(Assumptions!$B$5*Assumptions!$B$18) | J12: =-(Assumptions!$B$5*Assumptions!$B$18) | ... Z12: =-(Assumptions!$B$5*Assumptions!$B$18) | AA12: =SUM(C12:N12) | AB12: =SUM(O12:Z12)
A13: Utilities | C13: =-(Assumptions!$B$5*Assumptions!$B$19) | D13: =-(Assumptions!$B$5*Assumptions!$B$19) | E13: =-(Assumptions!$B$5*Assumptions!$B$19) | F13: =-(Assumptions!$B$5*Assumptions!$B$19) | G13: =-(Assumptions!$B$5*Assumptions!$B$19) | H13: =-(Assumptions!$B$5*Assumptions!$B$19) | I13: =-(Assumptions!$B$5*Assumptions!$B$19) | J13: =-(Assumptions!$B$5*Assumptions!$B$19) | ... Z13: =-(Assumptions!$B$5*Assumptions!$B$19) | AA13: =SUM(C13:N13) | AB13: =SUM(O13:Z13)
A14: Marketing | C14: =-(C6*Assumptions!$B$20) | D14: =-(D6*Assumptions!$B$20) | E14: =-(E6*Assumptions!$B$20) | F14: =-(F6*Assumptions!$B$20) | G14: =-(G6*Assumptions!$B$20) | H14: =-(H6*Assumptions!$B$20) | I14: =-(I6*Assumptions!$B$20) | J14: =-(J6*Assumptions!$B$20) | ... Z14: =-(Z6*Assumptions!$B$20) | AA14: =SUM(C14:N14) | AB14: =SUM(O14:Z14)
A15: G&A | C15: =-Assumptions!$B$21 | D15: =-Assumptions!$B$21 | E15: =-Assumptions!$B$21 | F15: =-Assumptions!$B$21 | G15: =-Assumptions!$B$21 | H15: =-Assumptions!$B$21 | I15: =-Assumptions!$B$21 | J15: =-Assumptions!$B$21 | ... Z15: =-Assumptions!$B$21 | AA15: =SUM(C15:N15) | AB15: =SUM(O15:Z15)
A16: Depreciation | C16: =-Assumptions!$B$22 | D16: =-Assumptions!$B$22 | E16: =-Assumptions!$B$22 | F16: =-Assumptions!$B$22 | G16: =-Assumptions!$B$22 | H16: =-Assumptions!$B$22 | I16: =-Assumptions!$B$22 | J16: =-Assumptions!$B$22 | ... Z16: =-Assumptions!$B$22 | AA16: =SUM(C16:N16) | AB16: =SUM(O16:Z16)
A17: Total Operating Expenses | C17: =SUM(C11:C16) | D17: =SUM(D11:D16) | E17: =SUM(E11:E16) | F17: =SUM(F11:F16) | G17: =SUM(G11:G16) | H17: =SUM(H11:H16) | I17: =SUM(I11:I16) | J17: =SUM(J11:J16) | ... Z17: =SUM(Z11:Z16) | AA17: =SUM(C17:N17) | AB17: =SUM(O17:Z17)
A18: EBITDA | B18: GP+Opex | C18: =C8+SUM(C11:C15) | D18: =D8+SUM(D11:D15) | E18: =E8+SUM(E11:E15) | F18: =F8+SUM(F11:F15) | G18: =G8+SUM(G11:G15) | H18: =H8+SUM(H11:H15) | I18: =I8+SUM(I11:I15) | J18: =J8+SUM(J11:J15) | ... Z18: =Z8+SUM(Z11:Z15) | AA18: =SUM(C18:N18) | AB18: =SUM(O18:Z18)
A19: EBITDA Margin % | C19: =IF(C6<>0,C18/C6,0) | D19: =IF(D6<>0,D18/D6,0) | E19: =IF(E6<>0,E18/E6,0) | F19: =IF(F6<>0,F18/F6,0) | G19: =IF(G6<>0,G18/G6,0) | H19: =IF(H6<>0,H18/H6,0) | I19: =IF(I6<>0,I18/I6,0) | J19: =IF(J6<>0,J18/J6,0) | ... Z19: =IF(Z6<>0,Z18/Z6,0) | AA19: =IF(C6<>0,C18/C6,0) | AB19: =IF(O6<>0,O18/O6,0)
A20: BELOW THE LINE
A21: EBIT (after Depreciation) | C21: =C18+C16 | D21: =D18+D16 | E21: =E18+E16 | F21: =F18+F16 | G21: =G18+G16 | H21: =H18+H16 | I21: =I18+I16 | J21: =J18+J16 | ... Z21: =Z18+Z16 | AA21: =SUM(C21:N21) | AB21: =SUM(O21:Z21)
A22: Income Tax | C22: =IF(C21>0,-C21*Assumptions!$B$32,0) | D22: =IF(D21>0,-D21*Assumptions!$B$32,0) | E22: =IF(E21>0,-E21*Assumptions!$B$32,0) | F22: =IF(F21>0,-F21*Assumptions!$B$32,0) | G22: =IF(G21>0,-G21*Assumptions!$B$32,0) | H22: =IF(H21>0,-H21*Assumptions!$B$32,0) | I22: =IF(I21>0,-I21*Assumptions!$B$32,0) | J22: =IF(J21>0,-J21*Assumptions!$B$32,0) | ... Z22: =IF(Z21>0,-Z21*Assumptions!$B$32,0) | AA22: =SUM(C22:N22) | AB22: =SUM(O22:Z22)
A23: NET INCOME | C23: =C21+C22 | D23: =D21+D22 | E23: =E21+E22 | F23: =F21+F22 | G23: =G21+G22 | H23: =H21+H22 | I23: =I21+I22 | J23: =J21+J22 | ... Z23: =Z21+Z22 | AA23: =SUM(C23:N23) | AB23: =SUM(O23:Z23)

Sheet Cash_Flow
A1: BrewCo Coffee Chain — Monthly Cash Flow Statement
A2: Linked from P&L. Ending Cash = Opening + Net Cash Movement. Red = cash shortfall — review Assumptions.
A4: Line Item | C4: Jan-25 | D4: Feb-25 | E4: Mar-25 | F4: Apr-25 | G4: May-25 | H4: Jun-25 | I4: Jul-25 | J4: Aug-25 | K4: Sep-25 | L4: Oct-25 | M4: Nov-25 | N4: Dec-25 | O4: Jan-26 | P4: Feb-26 | Q4: Mar-26 | R4: Apr-26 | S4: May-26 | T4: Jun-26 | U4: Jul-26 | V4: Aug-26 | W4: Sep-26 | X4: Oct-26 | Y4: Nov-26 | Z4: Dec-26 | AA4: FY2025 | AB4: FY2026
A5: Opening Cash Balance | C5: =Assumptions!$B$28 | D5: =C17 | E5: =C17 | F5: =D17 | G5: =E17 | H5: =F17 | I5: =G17 | J5: =H17 | K5: =I17 | L5: =J17 | ... AA5: =Y17
A6: OPERATING CASH FLOW
A7: Net Income | C7: ='P&L'!C23 | D7: ='P&L'!D23 | E7: ='P&L'!E23 | F7: ='P&L'!F23 | G7: ='P&L'!G23 | H7: ='P&L'!H23 | I7: ='P&L'!I23 | J7: ='P&L'!J23 | ... Z7: ='P&L'!Z23 | AA7: =SUM(C7:N7) | AB7: =SUM(O7:Z7)
A8: Add Back: Depreciation | C8: =-'P&L'!C16 | D8: =-'P&L'!D16 | E8: =-'P&L'!E16 | F8: =-'P&L'!F16 | G8: =-'P&L'!G16 | H8: =-'P&L'!H16 | I8: =-'P&L'!I16 | J8: =-'P&L'!J16 | ... Z8: =-'P&L'!Z16 | AA8: =SUM(C8:N8) | AB8: =SUM(O8:Z8)
A9: Change in Receivables | C9: =-'P&L'!C6*Assumptions!$B$24/30*IF(0>0,1,0) | D9: =-'P&L'!D6*Assumptions!$B$24/30*IF(1>0,1,0) | E9: =-'P&L'!E6*Assumptions!$B$24/30*IF(2>0,1,0) | F9: =-'P&L'!F6*Assumptions!$B$24/30*IF(3>0,1,0) | G9: =-'P&L'!G6*Assumptions!$B$24/30*IF(4>0,1,0) | H9: =-'P&L'!H6*Assumptions!$B$24/30*IF(5>0,1,0) | I9: =-'P&L'!I6*Assumptions!$B$24/30*IF(6>0,1,0) | J9: =-'P&L'!J6*Assumptions!$B$24/30*IF(7>0,1,0) | K9: =-'P&L'!K6*Assumptions!$B$24/30*IF(8>0,1,0) | L9: =-'P&L'!L6*Assumptions!$B$24/30*IF(9>0,1,0) | M9: =-'P&L'!M6*Assumptions!$B$24/30*IF(10>0,1,0) | N9: =-'P&L'!N6*Assumptions!$B$24/30*IF(11>0,1,0) | O9: =-'P&L'!O6*Assumptions!$B$24/30*IF(12>0,1,0) | P9: =-'P&L'!P6*Assumptions!$B$24/30*IF(13>0,1,0) | Q9: =-'P&L'!Q6*Assumptions!$B$24/30*IF(14>0,1,0) | R9: =-'P&L'!R6*Assumptions!$B$24/30*IF(15>0,1,0) | S9: =-'P&L'!S6*Assumptions!$B$24/30*IF(16>0,1,0) | T9: =-'P&L'!T6*Assumptions!$B$24/30*IF(17>0,1,0) | U9: =-'P&L'!U6*Assumptions!$B$24/30*IF(18>0,1,0) | V9: =-'P&L'!V6*Assumptions!$B$24/30*IF(19>0,1,0) | W9: =-'P&L'!W6*Assumptions!$B$24/30*IF(20>0,1,0) | X9: =-'P&L'!X6*Assumptions!$B$24/30*IF(21>0,1,0) | Y9: =-'P&L'!Y6*Assumptions!$B$24/30*IF(22>0,1,0) | Z9: =-'P&L'!Z6*Assumptions!$B$24/30*IF(23>0,1,0) | AA9: =SUM(C9:N9) | AB9: =SUM(O9:Z9)
A10: Change in Payables | C10: ='P&L'!C6*(Assumptions!$B$12+Assumptions!$B$11)*Assumptions!$B$25/30*IF(0>0,1,0) | D10: ='P&L'!D6*(Assumptions!$B$12+Assumptions!$B$11)*Assumptions!$B$25/30*IF(1>0,1,0) | E10: ='P&L'!E6*(Assumptions!$B$12+Assumptions!$B$11)*Assumptions!$B$25/30*IF(2>0,1,0) | F10: ='P&L'!F6*(Assumptions!$B$12+Assumptions!$B$11)*Assumptions!$B$25/30*IF(3>0,1,0) | G10: ='P&L'!G6*(Assumptions!$B$12+Assumptions!$B$11)*Assumptions!$B$25/30*IF(4>0,1,0) | H10: ='P&L'!H6*(Assumptions!$B$12+Assumptions!$B$11)*Assumptions!$B$25/30*IF(5>0,1,0) | I10: ='P&L'!I6*(Assumptions!$B$12+Assumptions!$B$11)*Assumptions!$B$25/30*IF(6>0,1,0) | J10: ='P&L'!J6*(Assumptions!$B$12+Assumptions!$B$11)*Assumptions!$B$25/30*IF(7>0,1,0) | K10: ='P&L'!K6*(Assumptions!$B$12+Assumptions!$B$11)*Assumptions!$B$25/30*IF(8>0,1,0) | L10: ='P&L'!L6*(Assumptions!$B$12+Assumptions!$B$11)*Assumptions!$B$25/30*IF(9>0,1,0) | M10: ='P&L'!M6*(Assumptions!$B$12+Assumptions!$B$11)*Assumptions!$B$25/30*IF(10>0,1,0) | N10: ='P&L'!N6*(Assumptions!$B$12+Assumptions!$B$11)*Assumptions!$B$25/30*IF(11>0,1,0) | O10: ='P&L'!O6*(Assumptions!$B$12+Assumptions!$B$11)*Assumptions!$B$25/30*IF(12>0,1,0) | P10: ='P&L'!P6*(Assumptions!$B$12+Assumptions!$B$11)*Assumptions!$B$25/30*IF(13>0,1,0) | Q10: ='P&L'!Q6*(Assumptions!$B$12+Assumptions!$B$11)*Assumptions!$B$25/30*IF(14>0,1,0) | R10: ='P&L'!R6*(Assumptions!$B$12+Assumptions!$B$11)*Assumptions!$B$25/30*IF(15>0,1,0) | S10: ='P&L'!S6*(Assumptions!$B$12+Assumptions!$B$11)*Assumptions!$B$25/30*IF(16>0,1,0) | T10: ='P&L'!T6*(Assumptions!$B$12+Assumptions!$B$11)*Assumptions!$B$25/30*IF(17>0,1,0) | U10: ='P&L'!U6*(Assumptions!$B$12+Assumptions!$B$11)*Assumptions!$B$25/30*IF(18>0,1,0) | V10: ='P&L'!V6*(Assumptions!$B$12+Assumptions!$B$11)*Assumptions!$B$25/30*IF(19>0,1,0) | W10: ='P&L'!W6*(Assumptions!$B$12+Assumptions!$B$11)*Assumptions!$B$25/30*IF(20>0,1,0) | X10: ='P&L'!X6*(Assumptions!$B$12+Assumptions!$B$11)*Assumptions!$B$25/30*IF(21>0,1,0) | Y10: ='P&L'!Y6*(Assumptions!$B$12+Assumptions!$B$11)*Assumptions!$B$25/30*IF(22>0,1,0) | Z10: ='P&L'!Z6*(Assumptions!$B$12+Assumptions!$B$11)*Assumptions!$B$25/30*IF(23>0,1,0) | AA10: =SUM(C10:N10) | AB10: =SUM(O10:Z10)
A11: Total Operating CF | C11: =SUM(C7:C10) | D11: =SUM(D7:D10) | E11: =SUM(E7:E10) | F11: =SUM(F7:F10) | G11: =SUM(G7:G10) | H11: =SUM(H7:H10) | I11: =SUM(I7:I10) | J11: =SUM(J7:J10) | ... Z11: =SUM(Z7:Z10) | AA11: =SUM(C11:N11) | AB11: =SUM(O11:Z11)
A12: FINANCING CASH FLOW
A13: Loan Repayment | C13: =-Assumptions!$B$31 | D13: =-Assumptions!$B$31 | E13: =-Assumptions!$B$31 | F13: =-Assumptions!$B$31 | G13: =-Assumptions!$B$31 | H13: =-Assumptions!$B$31 | I13: =-Assumptions!$B$31 | J13: =-Assumptions!$B$31 | ... Z13: =-Assumptions!$B$31 | AA13: =SUM(C13:N13) | AB13: =SUM(O13:Z13)
A14: Capex (New Location) | C14: =0 | D14: =0 | E14: =0 | F14: =0 | G14: =0 | H14: =0 | I14: =0 | J14: =0 | ... Z14: =0 | AA14: =SUM(C14:N14) | AB14: =SUM(O14:Z14)
A15: Total Financing CF | C15: =C13+C14 | D15: =D13+D14 | E15: =E13+E14 | F15: =F13+F14 | G15: =G13+G14 | H15: =H13+H14 | I15: =I13+I14 | J15: =J13+J14 | ... Z15: =Z13+Z14 | AA15: =SUM(C15:N15) | AB15: =SUM(O15:Z15)
A16: Net Cash Movement | C16: =C11+C15 | D16: =D11+D15 | E16: =E11+E15 | F16: =F11+F15 | G16: =G11+G15 | H16: =H11+H15 | I16: =I11+I15 | J16: =J11+J15 | ... Z16: =Z11+Z15 | AA16: =SUM(C16:N16) | AB16: =SUM(O16:Z16)
A17: ENDING CASH BALANCE | C17: =C5+C16 | D17: =D5+D16 | E17: =E5+E16 | F17: =F5+F16 | G17: =G5+G16 | H17: =H5+H16 | I17: =I5+I16 | J17: =J5+J16 | ... Z17: =Z5+Z16 | AA17: =N17 | AB17: =Z17

Sheet Break_Even
A1: BrewCo Coffee Chain — Break-Even Analysis
A2: How many customers per day per location are needed to cover all fixed costs? Sensitivity table shows impact of ticket size changes.
A4: SECTION 1 — BREAK-EVEN CALCULATION
A5: Average Ticket Size (USD) | B5: =Assumptions!$B$7
A6: COGS % per Cup (incl. waste) | B6: =Assumptions!$B$11+Assumptions!$B$12
A7: Contribution per Cup (USD) | B7: =B6*(1-B7)
A8: Monthly Fixed Costs per Location (USD) | B8: =Assumptions!$B$15*Assumptions!$B$14+Assumptions!$B$18+Assumptions!$B$19+Assumptions!$B$21+Assumptions!$B$22
A9: Working Days per Month | B9: =26
A10: Break-Even Customers / Month | B10: =IF(B8<>0,B9/B8,0)
A11: Break-Even Customers / Day | B11: =IF(B11<>0,B12/B11,0) | C11: ← Target to hit daily
A12: Current Avg Daily Customers (Base) | B12: =Assumptions!$B$6 | C12: ← From Assumptions
A13: Safety Margin (Customers above BE) | B13: =B14-B13
A14: Safety Margin % | B14: =IF(B14<>0,B15/B14,0) | C14: ← >20% = healthy buffer
A16: SECTION 2 — SENSITIVITY: BREAK-EVEN CUSTOMERS/DAY vs TICKET SIZE & COGS%
A17: Ticket Size → | B17: $5.00 | C17: $5.50 | D17: $6.00 | E17: $6.50 | F17: $7.00 | G17: $7.50 | H17: $8.00 | I17: ↓ COGS%
A18: COGS 28% | B18: 215.3 | C18: 195.7 | D18: 179.4 | E18: 165.6 | F18: 153.8 | G18: 143.5 | H18: 134.5 | I18: Customers/day/location
A19: COGS 30% | B19: 221.4 | C19: 201.3 | D19: 184.5 | E19: 170.3 | F19: 158.2 | G19: 147.6 | H19: 138.4 | I19: Customers/day/location
A20: COGS 32% | B20: 227.9 | C20: 207.2 | D20: 190 | E20: 175.3 | F20: 162.8 | G20: 152 | H20: 142.5 | I20: Customers/day/location
A21: COGS 34% | B21: 234.8 | C21: 213.5 | D21: 195.7 | E21: 180.7 | F21: 167.7 | G21: 156.6 | H21: 146.8 | I21: Customers/day/location
A22: COGS 36% | B22: 242.2 | C22: 220.2 | D22: 201.8 | E22: 186.3 | F22: 173 | G22: 161.5 | H22: 151.4 | I22: Customers/day/location
A23: COGS 38% | B23: 250 | C23: 227.3 | D23: 208.3 | E23: 192.3 | F23: 178.6 | G23: 166.7 | H23: 156.2 | I23: Customers/day/location
A25: ≤150 | B25: Achievable — healthy
A26: 151–200 | B26: Stretch target
A27: >200 | B27: Very difficult — review cost structure

Sheet KPI_Dashboard
A1: BrewCo Coffee Chain — KPI Dashboard | FY2025–FY2026
A2: All KPIs auto-update when Assumptions change. Green = on track | Red = attention needed.
A4: KEY PERFORMANCE INDICATORS — MONTHLY TREND
A5: KPI | B5: Jan-25 | C5: Feb-25 | D5: Mar-25 | E5: Apr-25 | F5: May-25 | G5: Jun-25 | H5: Jul-25 | I5: Aug-25 | J5: Sep-25 | K5: Oct-25 | L5: Nov-25 | M5: Dec-25 | N5: FY2025
A6: Monthly Revenue ($) | B6: ='P&L'!C6 | C6: ='P&L'!D6 | D6: ='P&L'!E6 | E6: ='P&L'!F6 | F6: ='P&L'!G6 | G6: ='P&L'!H6 | H6: ='P&L'!I6 | I6: ='P&L'!J6 | ... M6: ='P&L'!N6 | N6: ='P&L'!AA6
A7: Gross Profit ($) | B7: ='P&L'!C8 | C7: ='P&L'!D8 | D7: ='P&L'!E8 | E7: ='P&L'!F8 | F7: ='P&L'!G8 | G7: ='P&L'!H8 | H7: ='P&L'!I8 | I7: ='P&L'!J8 | ... M7: ='P&L'!N8 | N7: ='P&L'!AA8
A8: EBITDA ($) | B8: ='P&L'!C18 | C8: ='P&L'!D18 | D8: ='P&L'!E18 | E8: ='P&L'!F18 | F8: ='P&L'!G18 | G8: ='P&L'!H18 | H8: ='P&L'!I18 | I8: ='P&L'!J18 | ... M8: ='P&L'!N18 | N8: ='P&L'!AA18
A9: Net Income ($) | B9: ='P&L'!C23 | C9: ='P&L'!D23 | D9: ='P&L'!E23 | E9: ='P&L'!F23 | F9: ='P&L'!G23 | G9: ='P&L'!H23 | H9: ='P&L'!I23 | I9: ='P&L'!J23 | ... M9: ='P&L'!N23 | N9: ='P&L'!AA23
A10: Ending Cash ($) | B10: ='Cash_Flow'!C17 | C10: ='Cash_Flow'!D17 | D10: ='Cash_Flow'!E17 | E10: ='Cash_Flow'!F17 | F10: ='Cash_Flow'!G17 | G10: ='Cash_Flow'!H17 | H10: ='Cash_Flow'!I17 | I10: ='Cash_Flow'!J17 | ... M10: ='Cash_Flow'!N17 | N10: ='Cash_Flow'!AA17
A11: Gross Margin % | B11: =IF('P&L'!C6<>0,'P&L'!C8/'P&L'!C6,0) | C11: =IF('P&L'!D6<>0,'P&L'!D8/'P&L'!D6,0) | D11: =IF('P&L'!E6<>0,'P&L'!E8/'P&L'!E6,0) | E11: =IF('P&L'!F6<>0,'P&L'!F8/'P&L'!F6,0) | F11: =IF('P&L'!G6<>0,'P&L'!G8/'P&L'!G6,0) | G11: =IF('P&L'!H6<>0,'P&L'!H8/'P&L'!H6,0) | H11: =IF('P&L'!I6<>0,'P&L'!I8/'P&L'!I6,0) | I11: =IF('P&L'!J6<>0,'P&L'!J8/'P&L'!J6,0) | ... M11: =IF('P&L'!N6<>0,'P&L'!N8/'P&L'!N6,0) | N11: =IF('P&L'!AA6<>0,'P&L'!AA8/'P&L'!AA6,0)
A12: EBITDA Margin % | B12: =IF('P&L'!C6<>0,'P&L'!C18/'P&L'!C6,0) | C12: =IF('P&L'!D6<>0,'P&L'!D18/'P&L'!D6,0) | D12: =IF('P&L'!E6<>0,'P&L'!E18/'P&L'!E6,0) | E12: =IF('P&L'!F6<>0,'P&L'!F18/'P&L'!F6,0) | F12: =IF('P&L'!G6<>0,'P&L'!G18/'P&L'!G6,0) | G12: =IF('P&L'!H6<>0,'P&L'!H18/'P&L'!H6,0) | H12: =IF('P&L'!I6<>0,'P&L'!I18/'P&L'!I6,0) | I12: =IF('P&L'!J6<>0,'P&L'!J18/'P&L'!J6,0) | ... M12: =IF('P&L'!N6<>0,'P&L'!N18/'P&L'!N6,0) | N12: =IF('P&L'!AA6<>0,'P&L'!AA18/'P&L'!AA6,0)
A13: Net Margin % | B13: =IF('P&L'!C6<>0,'P&L'!C23/'P&L'!C6,0) | C13: =IF('P&L'!D6<>0,'P&L'!D23/'P&L'!D6,0) | D13: =IF('P&L'!E6<>0,'P&L'!E23/'P&L'!E6,0) | E13: =IF('P&L'!F6<>0,'P&L'!F23/'P&L'!F6,0) | F13: =IF('P&L'!G6<>0,'P&L'!G23/'P&L'!G6,0) | G13: =IF('P&L'!H6<>0,'P&L'!H23/'P&L'!H6,0) | H13: =IF('P&L'!I6<>0,'P&L'!I23/'P&L'!I6,0) | I13: =IF('P&L'!J6<>0,'P&L'!J23/'P&L'!J6,0) | ... M13: =IF('P&L'!N6<>0,'P&L'!N23/'P&L'!N6,0) | N13: =IF('P&L'!AA6<>0,'P&L'!AA23/'P&L'!AA6,0)

Sheet Scenario
A1: BrewCo Coffee Chain — Scenario Analysis | Base vs Growth vs Conservative
A2: Results calculated from Assumptions sheet (columns B/C/D). Switch scenarios by updating Assumptions sheet.
A4: Metric | B4: Unit | C4: Base Case | D4: Growth Case | E4: Conservative | F4: Growth vs Base | G4: Cons vs Base
A5: SECTION 1 — KEY ASSUMPTION COMPARISON
A6: Daily Customers / Location | B6: # | C6: =Assumptions!$B$6 | D6: =Assumptions!$C$6 | E6: =Assumptions!$D$6 | F6: =IF(Assumptions!$B$6<>0,(Assumptions!$C$6-Assumptions!$B$6)/Assumptions!$B$6,0) | G6: =IF(Assumptions!$B$6<>0,(Assumptions!$D$6-Assumptions!$B$6)/Assumptions!$B$6,0)
A7: Avg Ticket Size (USD) | B7: $ | C7: =Assumptions!$B$7 | D7: =Assumptions!$C$7 | E7: =Assumptions!$D$7 | F7: =IF(Assumptions!$B$7<>0,(Assumptions!$C$7-Assumptions!$B$7)/Assumptions!$B$7,0) | G7: =IF(Assumptions!$B$7<>0,(Assumptions!$D$7-Assumptions!$B$7)/Assumptions!$B$7,0)
A8: Monthly Growth Rate | B8: % | C8: =Assumptions!$B$8 | D8: =Assumptions!$C$8 | E8: =Assumptions!$D$8 | F8: =IF(Assumptions!$B$8<>0,(Assumptions!$C$8-Assumptions!$B$8)/Assumptions!$B$8,0) | G8: =IF(Assumptions!$B$8<>0,(Assumptions!$D$8-Assumptions!$B$8)/Assumptions!$B$8,0)
A9: COGS % Revenue | B9: % | C9: =Assumptions!$B$11 | D9: =Assumptions!$C$11 | E9: =Assumptions!$D$11 | F9: =IF(Assumptions!$B$11<>0,(Assumptions!$C$11-Assumptions!$B$11)/Assumptions!$B$11,0) | G9: =IF(Assumptions!$B$11<>0,(Assumptions!$D$11-Assumptions!$B$11)/Assumptions!$B$11,0)
A10: Staff / Location | B10: # | C10: =Assumptions!$B$14 | D10: =Assumptions!$C$14 | E10: =Assumptions!$D$14 | F10: =IF(Assumptions!$B$14<>0,(Assumptions!$C$14-Assumptions!$B$14)/Assumptions!$B$14,0) | G10: =IF(Assumptions!$B$14<>0,(Assumptions!$D$14-Assumptions!$B$14)/Assumptions!$B$14,0)
A11: Monthly Salary / Staff | B11: $ | C11: =Assumptions!$B$15 | D11: =Assumptions!$C$15 | E11: =Assumptions!$D$15 | F11: =IF(Assumptions!$B$15<>0,(Assumptions!$C$15-Assumptions!$B$15)/Assumptions!$B$15,0) | G11: =IF(Assumptions!$B$15<>0,(Assumptions!$D$15-Assumptions!$B$15)/Assumptions!$B$15,0)
A12: Rent / Location / Month | B12: $ | C12: =Assumptions!$B$18 | D12: =Assumptions!$C$18 | E12: =Assumptions!$D$18 | F12: =IF(Assumptions!$B$18<>0,(Assumptions!$C$18-Assumptions!$B$18)/Assumptions!$B$18,0) | G12: =IF(Assumptions!$B$18<>0,(Assumptions!$D$18-Assumptions!$B$18)/Assumptions!$B$18,0)
A13: Marketing % Revenue | B13: % | C13: =Assumptions!$B$20 | D13: =Assumptions!$C$20 | E13: =Assumptions!$D$20 | F13: =IF(Assumptions!$B$20<>0,(Assumptions!$C$20-Assumptions!$B$20)/Assumptions!$B$20,0) | G13: =IF(Assumptions!$B$20<>0,(Assumptions!$D$20-Assumptions!$B$20)/Assumptions!$B$20,0)
A15: SECTION 2 — FINANCIAL OUTPUT (FY2025, Base = current Assumptions)
A16: Note: Base = current P&L output. Growth & Conservative are illustrative estimates based on assumption delta. To model each scenario precisely: copy Assumptions col C or D over col B, then re-run P&L. This section shows the directional impact.
A17: FY2025 Revenue | B17: $ | C17: ='P&L'!AA6 | D17: =C17*1.1 | E17: =C17*0.85 | F17: =IF(C17<>0,(D17-C17)/ABS(C17),0) | G17: =IF(C17<>0,(E17-C17)/ABS(C17),0)
A18: FY2025 Gross Profit | B18: $ | C18: ='P&L'!AA8 | D18: =C18*1.12 | E18: =C18*0.8 | F18: =IF(C18<>0,(D18-C18)/ABS(C18),0) | G18: =IF(C18<>0,(E18-C18)/ABS(C18),0)
A19: FY2025 Gross Margin % | B19: % | C19: =IF('P&L'!AA6<>0,'P&L'!AA8/'P&L'!AA6,0) | D19: — | E19: — | F19: — | G19: —
A20: FY2025 EBITDA | B20: $ | C20: ='P&L'!AA18 | D20: =C20*1.18 | E20: =C20*0.7 | F20: =IF(C20<>0,(D20-C20)/ABS(C20),0) | G20: =IF(C20<>0,(E20-C20)/ABS(C20),0)
A21: FY2025 EBITDA Margin % | B21: % | C21: =IF('P&L'!AA6<>0,'P&L'!AA8/'P&L'!AA6,0) | D21: — | E21: — | F21: — | G21: —
A22: FY2025 Net Income | B22: $ | C22: ='P&L'!AA23 | D22: =C22*1.2 | E22: =C22*0.65 | F22: =IF(C22<>0,(D22-C22)/ABS(C22),0) | G22: =IF(C22<>0,(E22-C22)/ABS(C22),0)
A23: FY2026 Revenue | B23: $ | C23: ='P&L'!AB6 | D23: =C23*1.15 | E23: =C23*0.82 | F23: =IF(C23<>0,(D23-C23)/ABS(C23),0) | G23: =IF(C23<>0,(E23-C23)/ABS(C23),0)
A24: FY2026 Net Income | B24: $ | C24: ='P&L'!AB23 | D24: =C24*1.25 | E24: =C24*0.6 | F24: =IF(C24<>0,(D24-C24)/ABS(C24),0) | G24: =IF(C24<>0,(E24-C24)/ABS(C24),0)
A25: Year-End Cash | B25: $ | C25: ='Cash_Flow'!Z17 | D25: =C25*1.15 | E25: =C25*0.75 | F25: =IF(C25<>0,(D25-C25)/ABS(C25),0) | G25: =IF(C25<>0,(E25-C25)/ABS(C25),0)
