Workbook

Sheet README
B1: FP&A Demo Project for Upwork
A2: Sample SaaS model template: 24-month forecast, 3 financial statements, dashboard, and quality checks.
B4: 1) Quick Start Guide
B5: Select Scenario | C5: Data_Entry!B5: Base / Upside / Downside | D5: Use this to switch growth, churn, and margin assumptions | E5: Start from the Data_Entry sheet
B6: Update Input Data | C6: Yellow cells on Data_Entry | D6: These are editable input cells | E6: Data_Entry only
B7: Review Output | C7: IS / CF / BS / Dashboard / Checks | D7: Review the impact on EBITDA, cash, and headcount | E7: Share screenshots with the client
B10: 2) FP&A Workflow from A to Z
B11: Step | C11: What to do | D11: Deliverable
B12: A. Scope & Objectives | C12: Define the required model scope: budget, forecast, 3-statement model, cash runway, dashboard, and scenario planning. | D12: Project brief / SOW
B13: B. Data request | C13: Request the trial balance / historical P&L, payroll, sales pipeline, contracts, capex, debt, and working capital data. | D13: Data request list
B14: C. Standardize Actuals | C14: Clean the chart of accounts, map revenue / COGS / Opex, and resolve missing data. | D14: Clean actuals
B15: D. Define Drivers | C15: Select key business drivers: customers, ARPU, churn, headcount, marketing %, DSO, DPO, and capex. | D15: Assumption tree
B16: E. Build schedules | C16: Revenue, headcount, opex, capex, working capital, debt schedule. | D16: Supporting schedules
B17: F. 3 financial statements | C17: Link the Income Statement, Cash Flow Statement, and Balance Sheet. | D17: Integrated model
B18: G. Scenarios | C18: Build Base / Upside / Downside cases and sensitivities. | D18: Scenario model
B19: H. Dashboard & KPIs | C19: Revenue growth, gross margin, EBITDA, cash runway, ending customers, ending headcount. | D19: Client dashboard
B20: I. QA & handoff | C20: Prepare QA checks, documentation, user instructions, and optionally a video walkthrough or PDF snapshot. | D20: Final deliverables
B23: 3) Suggested Deliverables for Upwork
B24: Item | C24: Description
B25: Model file | C25: Workbook with Control / Assumptions / Schedules / 3 statements / Dashboard / Checks
B26: Executive summary | C26: One-page summary of insights: growth, margin, burn, cash needs, and hiring plan
B27: Scenario analysis | C27: Base vs Upside vs Downside, with sensitivity analysis for revenue and cash
B28: Client handoff | C28: README + color legend for inputs/formulas/links + monthly update instructions
B29: Client request list | C29: Tracker for dependencies, open items, due dates, and delivery status during the engagement
B30: Assumption log | C30: Audit-style register of key model drivers linked to Data_Entry for client review and sign-off
B31: Executive summary | C31: One-page summary linked to selected scenario and annual KPI outputs for handoff or proposal screenshots

Sheet Source_Notes
A1: HubSpot (HUBS) — FP&A Model Assumptions & Sources
A2: All figures in USD. Data sourced from public SEC filings.
A4: Input | B4: Value Used | C4: Source / Notes
A5: Model Start Date | B5: Jan 1, 2024 | C5: HubSpot FY2024 model — 24-month forecast from Jan 2024
A6: Initial Cash | B6: $1,388M | C6: Cash $388M + ST Investments $1,000M — HubSpot 10-K Dec 31 2023
A7: Initial AR | B7: $295M | C7: Accounts receivable net — HubSpot 10-K Dec 31 2023
A8: Initial Net PP&E | B8: $240M | C8: Estimated from total assets composition — HubSpot 10-K 2023
A9: Initial AP | B9: $9.1M | C9: Accounts payable — HubSpot 10-K Dec 31 2023 (very low, asset-light SaaS)
A10: Initial Debt | B10: $456M | C10: Convertible senior notes — HubSpot 10-K Dec 31 2023
A11: Share Capital (APIC) | B11: $2,137M | C11: Additional paid-in capital — HubSpot 10-K Dec 31 2023
A12: Opening Retained Earnings | B12: -$818.7M | C12: Accumulated deficit — HubSpot 10-K Dec 31 2023
A13: Beginning Customers | B13: 205,091 | C13: HubSpot Q4 2023 Earnings Release (8-K Feb 2024)
A14: Monthly New Customers (Base) | B14: 3,800 | C14: Net adds 2024: 42,848 ÷ 12 = 3,571. Gross adds est. +6% for churn offset
A15: Monthly Churn % (Base) | B15: 1.5% | C15: Estimated from NRR 104% (Q4 2024). Gross churn ~1.5%/mo for SMB mix
... A34: Marketing Salary | B34: $90,000/yr | C34: Marketing generalist to manager average
A36: Key Disclosure
A37: This model uses illustrative assumptions based on publicly available data.
A38: Actual internal figures will differ. Suitable for portfolio / educational use only.
A39: Sources: HubSpot SEC 8-K filings, 10-K 2023 & 2024, ir.hubspot.com

Sheet Data_Entry
A1: Data Entry Hub
A2: Update yellow cells only. All schedules, the 3 statements, dashboard, and checks update automatically.
A4: 1. Model Controls
A5: Selected Scenario | B5: Base | C5: Choose Base / Upside / Downside here
A9: 2. Scenario Assumptions
A10: Metric | B10: Base | C10: Upside | D10: Downside | E10: Selected | F10: Unit | G10: Notes
A11: Model Start Date | B11: 45292 | C11: 45292 | D11: 45292 | E11: =IF($B$5="Upside",C11,IF($B$5="Downside",D11,B11)) | F11: date | G11: Timeline start for monthly forecast
A12: Initial Cash | B12: 1388000000 | C12: 1388000000 | D12: 1388000000 | E12: =IF($B$5="Upside",C12,IF($B$5="Downside",D12,B12)) | F12: USD | G12: Opening cash on balance sheet
A13: Initial AR | B13: 295303000 | C13: 295303000 | D13: 295303000 | E13: =IF($B$5="Upside",C13,IF($B$5="Downside",D13,B13)) | F13: USD | G13: Opening accounts receivable
A14: Initial Net PP&E | B14: 240000000 | C14: 240000000 | D14: 240000000 | E14: =IF($B$5="Upside",C14,IF($B$5="Downside",D14,B14)) | F14: USD | G14: Opening net fixed assets
A15: Initial AP | B15: 9106000 | C15: 9106000 | D15: 9106000 | E15: =IF($B$5="Upside",C15,IF($B$5="Downside",D15,B15)) | F15: USD | G15: Opening accounts payable
A16: Initial Debt | B16: 456206000 | C16: 456206000 | D16: 456206000 | E16: =IF($B$5="Upside",C16,IF($B$5="Downside",D16,B16)) | F16: USD | G16: Opening interest-bearing debt
A17: Share Capital | B17: 2136908000 | C17: 2136908000 | D17: 2136908000 | E17: =IF($B$5="Upside",C17,IF($B$5="Downside",D17,B17)) | F17: USD | G17: Static equity capital
A18: Opening Retained Earnings | B18: -818676000 | C18: -818676000 | D18: -818676000 | E18: =IF($B$5="Upside",C18,IF($B$5="Downside",D18,B18)) | F18: USD | G18: Opening retained earnings
A19: Beginning Customers | B19: 205091 | C19: 205091 | D19: 205091 | E19: =IF($B$5="Upside",C19,IF($B$5="Downside",D19,B19)) | F19: customers | G19: Opening subscriber count
A20: Monthly New Customers | B20: 3800 | C20: 4200 | D20: 3200 | E20: =IF($B$5="Upside",C20,IF($B$5="Downside",D20,B20)) | F20: customers | G20: Average monthly gross adds
A21: Monthly Churn % | B21: 0.015 | C21: 0.012 | D21: 0.02 | E21: =IF($B$5="Upside",C21,IF($B$5="Downside",D21,B21)) | F21: % | G21: Monthly customer churn rate
A22: Starting ARPU | B22: 947 | C22: 960 | D22: 920 | E22: =IF($B$5="Upside",C22,IF($B$5="Downside",D22,B22)) | F22: USD | G22: Average revenue per customer per month
... A47: Other G&A / month | B47: 3000000 | C47: 3000000 | D47: 3000000 | E47: =IF($B$5="Upside",C47,IF($B$5="Downside",D47,B47)) | F47: USD | G47: Insurance, audit, admin and misc.
A49: 3. Monthly New Customer Schedule (override base assumption per month)
A50: Leave cells blank to use base scenario assumption. Enter a number to override that specific month.
A51: Monthly New Customers Override | B51: =Data_Entry!$E$11 | C51: =DATE(YEAR(B51),MONTH(B51)+1,1) | D51: =DATE(YEAR(C51),MONTH(C51)+1,1) | E51: =DATE(YEAR(D51),MONTH(D51)+1,1) | F51: =DATE(YEAR(E51),MONTH(E51)+1,1) | G51: =DATE(YEAR(F51),MONTH(F51)+1,1) | H51: =DATE(YEAR(G51),MONTH(G51)+1,1) | I51: =DATE(YEAR(H51),MONTH(H51)+1,1) | J51: =DATE(YEAR(I51),MONTH(I51)+1,1) | ... Y51: =DATE(YEAR(X51),MONTH(X51)+1,1)
A52: New Customers (blank = use base)
A54: 3. Monthly Hiring Plan
A55: Department / Movement | B55: =Data_Entry!$E$11 | C55: =DATE(YEAR(B51),MONTH(B51)+1,1) | D55: =DATE(YEAR(C51),MONTH(C51)+1,1) | E55: =DATE(YEAR(D51),MONTH(D51)+1,1) | F55: =DATE(YEAR(E51),MONTH(E51)+1,1) | G55: =DATE(YEAR(F51),MONTH(F51)+1,1) | H55: =DATE(YEAR(G51),MONTH(G51)+1,1) | I55: =DATE(YEAR(H51),MONTH(H51)+1,1) | J55: =DATE(YEAR(I51),MONTH(I51)+1,1) | ... Y55: =DATE(YEAR(X51),MONTH(X51)+1,1)
A56: Sales Hires | B56: 0 | C56: 0 | D56: 1 | E56: 0 | F56: 0 | G56: 0 | H56: 1 | I56: 0 | J56: 0 | K56: 0 | L56: 1 | M56: 0 | N56: 0 | O56: 0 | P56: 1 | Q56: 0 | R56: 0 | S56: 0 | T56: 1 | U56: 0 | V56: 0 | W56: 0 | X56: 1 | Y56: 0
A57: Sales Terms | B57: 0 | C57: 0 | D57: 0 | E57: 0 | F57: 0 | G57: 0 | H57: 0 | I57: 0 | J57: 0 | K57: 0 | L57: 0 | M57: 0 | N57: 0 | O57: 0 | P57: 0 | Q57: 0 | R57: 0 | S57: 0 | T57: 0 | U57: 0 | V57: 0 | W57: 0 | X57: 0 | Y57: 0
A58: Marketing Hires | B58: 0 | C58: 0 | D58: 0 | E58: 0 | F58: 0 | G58: 0 | H58: 0 | I58: 0 | J58: 0 | K58: 1 | L58: 0 | M58: 0 | N58: 0 | O58: 0 | P58: 0 | Q58: 0 | R58: 0 | S58: 0 | T58: 0 | U58: 0 | V58: 0 | W58: 1 | X58: 0 | Y58: 0
A59: Marketing Terms | B59: 0 | C59: 0 | D59: 0 | E59: 0 | F59: 0 | G59: 0 | H59: 0 | I59: 0 | J59: 0 | K59: 0 | L59: 0 | M59: 0 | N59: 0 | O59: 0 | P59: 0 | Q59: 0 | R59: 0 | S59: 0 | T59: 0 | U59: 0 | V59: 0 | W59: 0 | X59: 0 | Y59: 0
A60: R&D Hires | B60: 0 | C60: 0 | D60: 0 | E60: 0 | F60: 0 | G60: 1 | H60: 0 | I60: 0 | J60: 0 | K60: 0 | L60: 0 | M60: 0 | N60: 0 | O60: 1 | P60: 0 | Q60: 0 | R60: 0 | S60: 0 | T60: 0 | U60: 0 | V60: 0 | W60: 1 | X60: 0 | Y60: 0
A61: R&D Terms | B61: 0 | C61: 0 | D61: 0 | E61: 0 | F61: 0 | G61: 0 | H61: 0 | I61: 0 | J61: 0 | K61: 0 | L61: 0 | M61: 0 | N61: 0 | O61: 0 | P61: 0 | Q61: 0 | R61: 0 | S61: 0 | T61: 0 | U61: 0 | V61: 0 | W61: 0 | X61: 0 | Y61: 0
A62: G&A Hires | B62: 0 | C62: 0 | D62: 0 | E62: 0 | F62: 0 | G62: 0 | H62: 0 | I62: 0 | J62: 0 | K62: 0 | L62: 0 | M62: 0 | N62: 0 | O62: 0 | P62: 0 | Q62: 0 | R62: 0 | S62: 1 | T62: 0 | U62: 0 | V62: 0 | W62: 0 | X62: 0 | Y62: 0
A63: G&A Terms | B63: 0 | C63: 0 | D63: 0 | E63: 0 | F63: 0 | G63: 0 | H63: 0 | I63: 0 | J63: 0 | K63: 0 | L63: 0 | M63: 0 | N63: 0 | O63: 0 | P63: 0 | Q63: 0 | R63: 0 | S63: 0 | T63: 0 | U63: 0 | V63: 0 | W63: 0 | X63: 0 | Y63: 0
A64: Customer Success Hires | B64: 0 | C64: 0 | D64: 0 | E64: 0 | F64: 0 | G64: 0 | H64: 0 | I64: 0 | J64: 1 | K64: 0 | L64: 0 | M64: 0 | N64: 0 | O64: 0 | P64: 0 | Q64: 0 | R64: 0 | S64: 1 | T64: 0 | U64: 0 | V64: 0 | W64: 0 | X64: 0 | Y64: 0
A65: Customer Success Terms | B65: 0 | C65: 0 | D65: 0 | E65: 0 | F65: 0 | G65: 0 | H65: 0 | I65: 0 | J65: 0 | K65: 0 | L65: 0 | M65: 0 | N65: 0 | O65: 0 | P65: 0 | Q65: 0 | R65: 0 | S65: 0 | T65: 0 | U65: 0 | V65: 0 | W65: 0 | X65: 0 | Y65: 0
A68: 4. Monthly Debt Inputs
A69: Debt Input | B69: =Data_Entry!B51 | C69: =Data_Entry!C51 | D69: =Data_Entry!D51 | E69: =Data_Entry!E51 | F69: =Data_Entry!F51 | G69: =Data_Entry!G51 | H69: =Data_Entry!H51 | I69: =Data_Entry!I51 | ... Y69: =Data_Entry!Y51
A70: Debt Draws | B70: 0 | C70: 0 | D70: 0 | E70: 0 | F70: 0 | G70: 0 | H70: 0 | I70: 0 | J70: 0 | K70: 0 | L70: 0 | M70: 0 | N70: 0 | O70: 0 | P70: 0 | Q70: 0 | R70: 0 | S70: 0 | T70: 0 | U70: 0 | V70: 0 | W70: 0 | X70: 0 | Y70: 0
A71: Debt Repayments | H71: 0 | I71: 0 | J71: 0 | K71: 0 | L71: 0 | M71: 5000 | N71: 5000 | O71: 5000 | P71: 5000 | Q71: 5000 | R71: 5000 | S71: 5000 | T71: 5000 | U71: 5000 | V71: 5000 | W71: 5000 | X71: 5000 | Y71: 5000
A74: 5. Input Notes
A75: Edit only yellow cells on this sheet.
A76: Base / Upside / Downside assumptions flow into the entire model automatically.
A77: Hiring plan rows feed payroll expense in Headcount and Opex.
A78: Debt rows feed debt balance, interest expense, cash flow, and balance sheet.
A80: See Input_Source_Map, Client_Request_List, Assumption_Log, and Executive_Summary for source tracking and client-ready delivery support.

Sheet Input_Source_Map
A1: Input Source Map
A2: All current values in Data_Entry are sample demo assumptions. Replace them with client actuals, budget inputs, or management guidance using the source map below.
A4: How to Use This Sheet
A5: 1) Update yellow cells on Data_Entry only.
A6: 2) Use this sheet to know where each input should come from in a real client project.
A7: 3) Typical sources include accounting / ERP, payroll, CRM, board budget, and treasury schedules.
A9: Section | B9: Data_Entry Ref | C9: Input Item | D9: Meaning | E9: Typical Real-World Source | F9: Typical Owner / System | G9: Update Timing | H9: Demo / Portfolio Note
A10: Model Controls | B10: Data_Entry!B5 | C10: Selected Scenario | D10: Chooses Base / Upside / Downside case used by the full model. | E10: FP&A scenario pack, budget presentation, or management planning deck. | F10: FP&A Manager / CFO | G10: When presenting cases | H10: Current workbook is preloaded to Base for demo purposes.
A11: Opening Balance | B11: Data_Entry!B11:D11 | C11: Model Start Date | D11: First forecast month. | E11: Forecast calendar agreed with management or budget cycle. | F11: FP&A | G11: Once per model build | H11: Usually fixed at kickoff.
A12: Opening Balance | B12: Data_Entry!B12:D12 | C12: Initial Cash | D12: Opening cash balance. | E12: Latest balance sheet, bank statement, or trial balance. | F12: Controller / Treasury / ERP | G12: Monthly close | H12: Replace demo number with month-end actuals.
A13: Opening Balance | B13: Data_Entry!B13:D13 | C13: Initial AR | D13: Opening accounts receivable. | E13: AR aging report or latest balance sheet. | F13: Accounting / ERP | G13: Monthly close | H13: Should tie to AR aging.
A14: Opening Balance | B14: Data_Entry!B14:D14 | C14: Initial Net PP&E | D14: Opening net fixed assets. | E14: Fixed asset register or latest balance sheet. | F14: Accounting / ERP | G14: Monthly close | H14: Tie to fixed asset schedule.
A15: Opening Balance | B15: Data_Entry!B15:D15 | C15: Initial AP | D15: Opening accounts payable. | E15: AP aging report or latest balance sheet. | F15: Accounting / ERP | G15: Monthly close | H15: Should tie to AP aging.
A16: Opening Balance | B16: Data_Entry!B16:D16 | C16: Initial Debt | D16: Opening interest-bearing debt. | E16: Debt schedule, loan statement, or balance sheet. | F16: Treasury / Controller | G16: Monthly close | H16: Tie to lender statements.
A17: Opening Balance | B17: Data_Entry!B17:D17 | C17: Share Capital | D17: Opening contributed equity. | E17: Balance sheet or prior audited financials. | F17: Controller | G17: Rarely changes | H17: Usually static unless equity event occurs.
A18: Opening Balance | B18: Data_Entry!B18:D18 | C18: Opening Retained Earnings | D18: Accumulated earnings brought forward. | E18: Balance sheet or prior period close file. | F18: Controller | G18: Monthly close | H18: Should roll from prior closing retained earnings.
A19: Revenue Drivers | B19: Data_Entry!B19:D19 | C19: Beginning Customers | D19: Opening active customer count. | E19: CRM, billing system, or subscription report. | F19: Revenue Ops / CRM / Billing | G19: Monthly close | H19: Tie to start-of-period customer base.
A20: Revenue Drivers | B20: Data_Entry!B20:D20 | C20: Monthly New Customers | D20: Average monthly gross customer adds. | E20: Sales pipeline, bookings plan, or historical conversion trend. | F20: Sales Ops / FP&A / CRM | G20: Monthly or reforecast | H20: Often linked to sales target.
... A59: Debt Inputs | B59: Data_Entry!B67:Y67 | C59: Debt Repayments | D59: Monthly principal repayments. | E59: Debt amortization schedule, lender notice, or treasury plan. | F59: Treasury / CFO | G59: When financing changes | H59: Enter monthly principal only; interest is calculated.
A62: Tip: In a live client project, tie opening balances to the last closed month, tie headcount to HR/payroll, and tie revenue drivers to CRM or billing reports.

Sheet Executive_Summary
A1: Executive Summary
A2: Client-ready one-page overview linked to the selected scenario and model outputs.
A4: Project Snapshot
A5: Metric | B5: Value | C5: Metric | D5: Value | F5: Metric | G5: Value | H5: Notes
A6: Selected Scenario | B6: =Data_Entry!$B$5 | C6: Forecast Start | D6: =Dashboard!$B$4 | F6: Forecast End | G6: =Dashboard!$Y$4 | H6: Use this page for proposal screenshots or client handoff.
A7: Year 1 | B7: =Dashboard!$C$13 | C7: Year 2 | D7: =Dashboard!$D$13 | F7: Cash Check | G7: =Checks!$D$9 | H7: Checks sheet confirms minimum ending cash and BS balance.
A9: Annual KPI Summary
A10: Metric | B10: Year 1 | C10: Year 2 | D10: Change | F10: Key Readout | G10: Formula | H10: Status
A11: Revenue | B11: =Dashboard!$C$14 | C11: =Dashboard!$D$14 | D11: =IF(B11=0,"-",C11/B11-1) | F11: Revenue growth | G11: =IF(D11="-","n/a",IF(D11>0,"Growing","Declining")) | H11: =IF(D11="-","REVIEW",IF(D11>=0,"OK","REVIEW"))
A12: EBITDA | B12: =Dashboard!$C$15 | C12: =Dashboard!$D$15 | D12: =C12-B12 | F12: Profit improvement | G12: =IF(D12>0,"Improving","Declining") | H12: =IF(C12>=0,"OK","REVIEW")
A13: EBITDA Margin | B13: =Dashboard!$C$16 | C13: =Dashboard!$D$16 | D13: =C13-B13 | F13: Margin trend | G13: =IF(D13>0,"Improving","Compressing") | H13: =IF(C13>=0,"OK","REVIEW")
A14: Ending Cash | B14: =Dashboard!$C$17 | C14: =Dashboard!$D$17 | D14: =C14-B14 | F14: Liquidity | G14: =IF(C14>0,"Positive","Negative") | H14: =IF(C14>0,"OK","REVIEW")
A15: Ending Customers | B15: =Dashboard!$C$18 | C15: =Dashboard!$D$18 | D15: =C15-B15 | F15: Customer base | G15: =IF(D15>0,"Expanded","Contracted") | H15: =IF(C15>=B15,"OK","REVIEW")
A16: Ending HC | B16: =Dashboard!$C$19 | C16: =Dashboard!$D$19 | D16: =C16-B16 | F16: Organization size | G16: =IF(D16>0,"Scaled up","Flat / down") | H16: Informational
A18: Auto Checks & Handoff Notes
A19: =IF(MIN(CF!B19:Y19)>0,"PASS: ending cash remains positive across the full forecast horizon.","REVIEW: ending cash goes negative during the forecast horizon.")
A20: =IF(ABS(BS!Y19)<1,"PASS: the balance sheet remains in balance in the final forecast month.","REVIEW: the balance sheet is out of balance in the final forecast month.")
A21: =IF(Dashboard!D16>=Dashboard!C16,"Year 2 EBITDA margin is at or above Year 1.","Year 2 EBITDA margin is below Year 1 and should be reviewed.")
A22: =IF(Dashboard!D18>=Dashboard!C18,"Customer count ends above Year 1.","Customer count ends below Year 1 and should be explained.")
A23: Use the Dashboard, Checks, Input_Source_Map, Assumption_Log, and Client_Request_List tabs as the standard client delivery pack.

Sheet Client_Request_List
A1: Client Request List
A2: Tracker for open requests, deliverables, dependencies, and handoff status during an FP&A engagement.
A4: Tracker Summary
A5: Metric | B5: Value | C5: Metric | D5: Value | E5: Metric | F5: Value
A6: Total Requests | B6: =COUNTA(A11:A20) | C6: Done | D6: =COUNTIF(F11:F20,"Done") | E6: Waiting on Client | F6: =COUNTIF(F11:F20,"Waiting on Client")
A7: Open Items | B7: =COUNTIF(F11:F20,"<>Done") | C7: High Priority | D7: =COUNTIF(D11:D20,"High") | E7: In Progress | F7: =COUNTIF(F11:F20,"In Progress")
A9: Detailed Request Tracker
A10: Request ID | B10: Workstream | C10: Request / Deliverable | D10: Priority | E10: Owner | F10: Status | G10: Due Date | H10: Notes
A11: =ROW()-10 | B11: Kickoff | C11: Confirm scope, deliverables, and scenario definitions. | D11: High | E11: FP&A | F11: Done | G11: =Data_Entry!$E$11+3 | H11: Use this as the kickoff checklist in proposals.
A12: =ROW()-10 | B12: Actuals | C12: Provide monthly P&L, balance sheet, and cash flow actuals. | D12: High | E12: Client / Accounting | F12: Waiting on Client | G12: =Data_Entry!$E$11+7 | H12: Needed to replace demo assumptions with real actuals.
A13: =ROW()-10 | B13: Revenue | C13: Share billing export, pipeline, pricing, and churn history. | D13: High | E13: Client / RevOps | F13: In Progress | G13: =Data_Entry!$E$11+10 | H13: Feeds customer, ARPU, churn, and implementation fee drivers.
A14: =ROW()-10 | B14: People | C14: Share payroll register, org chart, and hiring plan. | D14: High | E14: Client / HR | F14: Waiting on Client | G14: =Data_Entry!$E$11+10 | H14: Needed to validate opening HC and salary assumptions.
A15: =ROW()-10 | B15: Working Capital | C15: Confirm AR aging, AP aging, DSO, and DPO targets. | D15: Medium | E15: Client / Controller | F15: Not Started | G15: =Data_Entry!$E$11+12 | H15: Required for CF and BS accuracy.
A16: =ROW()-10 | B16: Treasury | C16: Provide debt agreements, draw schedule, and repayment plan. | D16: Medium | E16: Client / Treasury | F16: Not Started | G16: =Data_Entry!$E$11+14 | H16: Used for debt balance and interest expense.
A17: =ROW()-10 | B17: Capex | C17: Provide fixed asset rollforward and capex plan. | D17: Medium | E17: Client / Accounting | F17: Not Started | G17: =Data_Entry!$E$11+14 | H17: Used for depreciation and PP&E build.
A18: =ROW()-10 | B18: Review | C18: Review Base / Upside / Downside assumptions with management. | D18: High | E18: FP&A + CFO | F18: Not Started | G18: =Data_Entry!$E$11+18 | H18: Use before finalizing the scenario pack.
A19: =ROW()-10 | B19: QA | C19: Run checks and confirm that outputs tie across the model. | D19: High | E19: FP&A | F19: Not Started | G19: =Data_Entry!$E$11+20 | H19: Checks tab should be clean before handoff.
A20: =ROW()-10 | B20: Handoff | C20: Deliver final model, executive summary, and walkthrough. | D20: Medium | E20: FP&A | F20: Not Started | G20: =Data_Entry!$E$11+21 | H20: Final client package.

Sheet Assumption_Log
A1: Assumption Log
A2: Audit-friendly log of key model drivers, linked to Data_Entry and ready for client review.
A4: Review Summary
A5: Metric | B5: Value | C5: Metric | D5: Value | E5: Metric | F5: Value
A6: Logged Assumptions | B6: =COUNTA(B11:B26) | C6: Reviewed | D6: =COUNTIF(J11:J26,"Reviewed") | E6: Approved | F6: =COUNTIF(J11:J26,"Approved")
A7: Selected Scenario | B7: =Data_Entry!$B$5 | C7: Model Start | D7: =Dashboard!$B$4 | E7: Use | F7: Purpose: client assumption review, challenge session, and sign-off log.
A9: Detailed Assumption Register
A10: ID | B10: Driver / Assumption | C10: Base | D10: Upside | E10: Downside | F10: Selected | G10: Unit | H10: Rationale / Modeling Use | I10: Primary Source / Owner | J10: Review Status | K10: Reviewer Notes
A11: 1 | B11: Monthly New Customers | C11: =Data_Entry!B20 | D11: =Data_Entry!C20 | E11: =Data_Entry!D20 | F11: =Data_Entry!E20 | G11: customers | H11: Driver for customer cohort model. Feeds into ending customer count, subscription revenue, and implementation revenue each month. Sensitivity: ±10 customers/month ≈ ±$36K annual revenue (Base ARPU). | I11: CRM pipeline / Sales leadership | J11: Ready for review | K11: — Pending client sign-off —
A12: 2 | B12: Monthly Churn % | C12: =Data_Entry!B21 | D12: =Data_Entry!C21 | E12: =Data_Entry!D21 | F12: =Data_Entry!E21 | G12: % | H12: Applied to beginning-of-period customers. Net Revenue Retention = (1 - churn%) × 12 annualized. Base 2% monthly = ~21.5% annual churn. Sensitive driver — 0.5% change affects revenue by ~3%. | I12: Billing / retention report | J12: Ready for review | K12: — Pending client sign-off —
A13: 3 | B13: Starting ARPU | C13: =Data_Entry!B22 | D13: =Data_Entry!C22 | E13: =Data_Entry!D22 | F13: =Data_Entry!E22 | G13: USD | H13: Anchor for monthly subscription revenue. Compounds monthly at Annual Price Uplift / 12. Should reconcile to billing system ARR ÷ customer count. | I13: Billing export / pricing file | J13: Ready for review | K13: — Pending client sign-off —
A14: 4 | B14: Annual Price Uplift % | C14: =Data_Entry!B23 | D14: =Data_Entry!C23 | E14: =Data_Entry!D23 | F14: =Data_Entry!E23 | G14: % | H14: Applied monthly as (1 + rate/12) compounding. Base 3% = $9/month uplift on $300 ARPU in year 1. Verify against contract renewal terms and pricing strategy. | I14: Pricing strategy / management guidance | J14: Ready for review | K14: — Pending client sign-off —
A15: 5 | B15: Implementation Fee / New Customer | C15: =Data_Entry!B24 | D15: =Data_Entry!C24 | E15: =Data_Entry!D24 | F15: =Data_Entry!E24 | G15: USD | H15: One-time fee per new customer. Revenue recognized in month of onboarding. Directly multiplied by monthly new customer adds. High impact in early growth phase. | I15: Contracts / sales order form | J15: Ready for review | K15: — Pending client sign-off —
A16: 6 | B16: COGS % Revenue | C16: =Data_Entry!B25 | D16: =Data_Entry!C25 | E16: =Data_Entry!D25 | F16: =Data_Entry!E25 | G16: % | H16: Blended direct delivery cost rate. Covers hosting, support, and variable COGS. Applied to total revenue monthly. Gross margin = 1 - COGS%. Base: 85% gross margin. | I16: Historical P&L / unit economics | J16: Ready for review | K16: — Pending client sign-off —
A17: 7 | B17: Benefits % Payroll | C17: =Data_Entry!B26 | D17: =Data_Entry!C26 | E17: =Data_Entry!D26 | F17: =Data_Entry!E26 | G17: % | H17: Loaded on top of base salary to capture payroll taxes, health, and benefits. Applied uniformly across all departments. Base 18% is conservative — typical SaaS range 15–25%. | I17: Payroll burden / benefits policy | J17: Ready for review | K17: — Pending client sign-off —
A18: 8 | B18: Tax Rate | C18: =Data_Entry!B27 | D18: =Data_Entry!C27 | E18: =Data_Entry!D27 | F18: =Data_Entry!E27 | G18: % | H18: Effective planning rate applied to EBT when positive (MAX(0, EBT × rate)). Tax is only recognized on profit — no negative tax in loss months. Verify with tax advisor. | I18: Tax planning / historical ETR | J18: Ready for review | K18: — Pending client sign-off —
A19: 9 | B19: DSO | C19: =Data_Entry!B28 | D19: =Data_Entry!C28 | E19: =Data_Entry!D28 | F19: =Data_Entry!E28 | G19: days | H19: Days sales outstanding. Used to calculate AR balance = Revenue × DSO / 30. Drives working capital needs. Lower DSO = faster collections = better cash conversion. | I19: AR aging / collections trend | J19: Ready for review | K19: — Pending client sign-off —
A20: 10 | B20: DPO | C20: =Data_Entry!B29 | D20: =Data_Entry!C29 | E20: =Data_Entry!D29 | F20: =Data_Entry!E29 | G20: days | H20: Days payable outstanding. Used to calculate AP balance = COGS × DPO / 30. Higher DPO = slower payments = more supplier financing. Should align with vendor agreements. | I20: AP aging / payment cadence | J20: Ready for review | K20: — Pending client sign-off —
A21: 11 | B21: Interest Rate | C21: =Data_Entry!B30 | D21: =Data_Entry!C30 | E21: =Data_Entry!D30 | F21: =Data_Entry!E30 | G21: % | H21: Annual rate applied to average opening debt balance monthly (rate / 12). Represents blended cost of all debt facilities. Update when refinancing or drawing new facilities. | I21: Debt agreement / treasury plan | J21: Ready for review | K21: — Pending client sign-off —
A22: 12 | B22: Depreciation Life (months) | C22: =Data_Entry!B31 | D22: =Data_Entry!C31 | E22: =Data_Entry!D31 | F22: =Data_Entry!E31 | G22: months | H22: Straight-line depreciation over this period (months). Depreciation = Capex / Life per month. 36 months = 3-year useful life — typical for SaaS infrastructure and equipment. | I22: Accounting policy | J22: Ready for review | K22: — Pending client sign-off —
A23: 13 | B23: Capex % Revenue | C23: =Data_Entry!B32 | D23: =Data_Entry!C32 | E23: =Data_Entry!D32 | F23: =Data_Entry!E32 | G23: % | H23: Capital expenditure as a percent of revenue. Low for pure SaaS (asset-light). Drives Capex schedule, depreciation, and PP&E on balance sheet. Verify against capex plan. | I23: Capex plan / board budget | J23: Ready for review | K23: — Pending client sign-off —
A24: 14 | B24: Marketing Programs % Revenue | C24: =Data_Entry!B43 | D24: =Data_Entry!C43 | E24: =Data_Entry!D43 | F24: =Data_Entry!E43 | G24: % | H24: Demand generation spend as % of revenue. Separate from payroll-based marketing salaries. Covers paid acquisition, events, and campaigns. Higher in Upside to fund growth. | I24: Marketing budget / demand plan | J24: Ready for review | K24: — Pending client sign-off —
A25: 15 | B25: Travel % Revenue | C25: =Data_Entry!B46 | D25: =Data_Entry!C46 | E25: =Data_Entry!D46 | F25: =Data_Entry!E46 | G25: % | H25: Travel and entertainment as % of revenue. Scales with revenue growth. Base 1% is typical for B2B SaaS at this stage. Adjust for remote-first or field-heavy teams. | I25: Historical spend / travel policy | J25: Ready for review | K25: — Pending client sign-off —
A26: 16 | B26: Sales Salary | C26: =Data_Entry!B38 | D26: =Data_Entry!C38 | E26: =Data_Entry!D38 | F26: =Data_Entry!E38 | G26: USD / yr | H26: Average annual base salary for Sales team. Used with Benefits % to compute fully loaded monthly payroll per FTE. Multiply by headcount and divide by 12 for monthly expense. | I26: Payroll / comp plan | J26: Ready for review | K26: — Pending client sign-off —

Sheet Control
B1: Control Panel
A2: Select the scenario and review the color coding used in the file.
B4: Model Controls
B5: Scenario | C5: Selected | D5: Notes
B6: Base / Upside / Downside | C6: =Data_Entry!$B$5 | D6: Change the scenario on Data_Entry to update the full model.
B8: Color legend
B9: Input / editable | C9: Sample
B10: Formula | C10: Sample
B11: Cross-sheet link | C11: Sample
B12: Static / note | C12: Sample
B13: Flag / review | C13: Sample
B16: Model Map
B17: Sheet | C17: Purpose
B18: Data_Entry | C18: Single place for scenario, assumptions, hiring plan, and debt inputs
B19: Revenue | C19: Customers, ARPU, revenue & gross profit
B20: Headcount | C20: Hiring plan and payroll expense
B21: Opex | C21: Non-payroll operating expenses
B22: Working_Capital | C22: AR / AP balances and deltas
B23: Capex | C23: Capex and depreciation
B24: Debt | C24: Debt balance and interest
B25: IS / CF / BS | C25: 3 integrated statements
B26: Dashboard / Checks | C26: KPI snapshot and QA tests

Sheet Assumptions
B1: Assumptions & Scenario Drivers
A2: Illustrative assumptions. Replace these with real client data during live engagement.
B4: Core Assumptions
B5: Metric | C5: Base | D5: Upside | E5: Downside | F5: Selected | G5: Units | H5: Notes
B6: Model Start Date | C6: =Data_Entry!$B$11 | D6: =Data_Entry!$C$11 | E6: =Data_Entry!$D$11 | F6: =Data_Entry!$E$11 | G6: date | H6: Timeline start for monthly forecast
B7: Initial Cash | C7: =Data_Entry!$B$12 | D7: =Data_Entry!$C$12 | E7: =Data_Entry!$D$12 | F7: =Data_Entry!$E$12 | G7: USD | H7: Opening cash on balance sheet
B8: Initial AR | C8: =Data_Entry!$B$13 | D8: =Data_Entry!$C$13 | E8: =Data_Entry!$D$13 | F8: =Data_Entry!$E$13 | G8: USD | H8: Opening accounts receivable
B9: Initial Net PP&E | C9: =Data_Entry!$B$14 | D9: =Data_Entry!$C$14 | E9: =Data_Entry!$D$14 | F9: =Data_Entry!$E$14 | G9: USD | H9: Opening net fixed assets
B10: Initial AP | C10: =Data_Entry!$B$15 | D10: =Data_Entry!$C$15 | E10: =Data_Entry!$D$15 | F10: =Data_Entry!$E$15 | G10: USD | H10: Opening accounts payable
B11: Initial Debt | C11: =Data_Entry!$B$16 | D11: =Data_Entry!$C$16 | E11: =Data_Entry!$D$16 | F11: =Data_Entry!$E$16 | G11: USD | H11: Opening interest-bearing debt
B12: Share Capital | C12: =Data_Entry!$B$17 | D12: =Data_Entry!$C$17 | E12: =Data_Entry!$D$17 | F12: =Data_Entry!$E$17 | G12: USD | H12: Static equity capital
B13: Opening Retained Earnings | C13: =Data_Entry!$B$18 | D13: =Data_Entry!$C$18 | E13: =Data_Entry!$D$18 | F13: =Data_Entry!$E$18 | G13: USD | H13: Opening retained earnings
B14: Beginning Customers | C14: =Data_Entry!$B$19 | D14: =Data_Entry!$C$19 | E14: =Data_Entry!$D$19 | F14: =Data_Entry!$E$19 | G14: customers | H14: Opening subscriber count
B15: Monthly New Customers | C15: =Data_Entry!$B$20 | D15: =Data_Entry!$C$20 | E15: =Data_Entry!$D$20 | F15: =Data_Entry!$E$20 | G15: customers | H15: Average monthly gross adds
B16: Monthly Churn % | C16: =Data_Entry!$B$21 | D16: =Data_Entry!$C$21 | E16: =Data_Entry!$D$21 | F16: =Data_Entry!$E$21 | G16: % | H16: Monthly customer churn rate
B17: Starting ARPU | C17: =Data_Entry!$B$22 | D17: =Data_Entry!$C$22 | E17: =Data_Entry!$D$22 | F17: =Data_Entry!$E$22 | G17: USD | H17: Average revenue per customer per month
B18: Annual Price Uplift % | C18: =Data_Entry!$B$23 | D18: =Data_Entry!$C$23 | E18: =Data_Entry!$D$23 | F18: =Data_Entry!$E$23 | G18: % | H18: Annual ARPU increase
B19: Implementation Fee / New Customer | C19: =Data_Entry!$B$24 | D19: =Data_Entry!$C$24 | E19: =Data_Entry!$D$24 | F19: =Data_Entry!$E$24 | G19: USD | H19: One-time onboarding fee
B20: COGS % Revenue | C20: =Data_Entry!$B$25 | D20: =Data_Entry!$C$25 | E20: =Data_Entry!$D$25 | F20: =Data_Entry!$E$25 | G20: % | H20: Direct service delivery cost as % of revenue
B21: Benefits % Payroll | C21: =Data_Entry!$B$26 | D21: =Data_Entry!$C$26 | E21: =Data_Entry!$D$26 | F21: =Data_Entry!$E$26 | G21: % | H21: Payroll burden & benefits
B22: Tax Rate | C22: =Data_Entry!$B$27 | D22: =Data_Entry!$C$27 | E22: =Data_Entry!$D$27 | F22: =Data_Entry!$E$27 | G22: % | H22: Effective corporate tax rate
B23: DSO | C23: =Data_Entry!$B$28 | D23: =Data_Entry!$C$28 | E23: =Data_Entry!$D$28 | F23: =Data_Entry!$E$28 | G23: days | H23: Average collection period
B24: DPO | C24: =Data_Entry!$B$29 | D24: =Data_Entry!$C$29 | E24: =Data_Entry!$D$29 | F24: =Data_Entry!$E$29 | G24: days | H24: Average payment period
B25: Interest Rate | C25: =Data_Entry!$B$30 | D25: =Data_Entry!$C$30 | E25: =Data_Entry!$D$30 | F25: =Data_Entry!$E$30 | G25: % | H25: Average annual debt cost
B26: Depreciation Life (months) | C26: =Data_Entry!$B$31 | D26: =Data_Entry!$C$31 | E26: =Data_Entry!$D$31 | F26: =Data_Entry!$E$31 | G26: months | H26: Straight-line useful life
B27: Capex % Revenue | C27: =Data_Entry!$B$32 | D27: =Data_Entry!$C$32 | E27: =Data_Entry!$D$32 | F27: =Data_Entry!$E$32 | G27: % | H27: Capital spend as % of revenue
B28: Sales Opening HC | C28: =Data_Entry!$B$33 | D28: =Data_Entry!$C$33 | E28: =Data_Entry!$D$33 | F28: =Data_Entry!$E$33 | G28: FTE | H28: Opening sales team headcount
B29: Marketing Opening HC | C29: =Data_Entry!$B$34 | D29: =Data_Entry!$C$34 | E29: =Data_Entry!$D$34 | F29: =Data_Entry!$E$34 | G29: FTE | H29: Opening marketing headcount
B30: R&D Opening HC | C30: =Data_Entry!$B$35 | D30: =Data_Entry!$C$35 | E30: =Data_Entry!$D$35 | F30: =Data_Entry!$E$35 | G30: FTE | H30: Opening R&D headcount
B31: G&A Opening HC | C31: =Data_Entry!$B$36 | D31: =Data_Entry!$C$36 | E31: =Data_Entry!$D$36 | F31: =Data_Entry!$E$36 | G31: FTE | H31: Opening G&A headcount
B32: Customer Success Opening HC | C32: =Data_Entry!$B$37 | D32: =Data_Entry!$C$37 | E32: =Data_Entry!$D$37 | F32: =Data_Entry!$E$37 | G32: FTE | H32: Opening CS headcount
B33: Sales Salary | C33: =Data_Entry!$B$38 | D33: =Data_Entry!$C$38 | E33: =Data_Entry!$D$38 | F33: =Data_Entry!$E$38 | G33: USD/yr | H33: Average annual fully loaded base salary
B34: Marketing Salary | C34: =Data_Entry!$B$39 | D34: =Data_Entry!$C$39 | E34: =Data_Entry!$D$39 | F34: =Data_Entry!$E$39 | G34: USD/yr | H34: Average annual fully loaded base salary
B35: R&D Salary | C35: =Data_Entry!$B$40 | D35: =Data_Entry!$C$40 | E35: =Data_Entry!$D$40 | F35: =Data_Entry!$E$40 | G35: USD/yr | H35: Average annual fully loaded base salary
B36: G&A Salary | C36: =Data_Entry!$B$41 | D36: =Data_Entry!$C$41 | E36: =Data_Entry!$D$41 | F36: =Data_Entry!$E$41 | G36: USD/yr | H36: Average annual fully loaded base salary
B37: Customer Success Salary | C37: =Data_Entry!$B$42 | D37: =Data_Entry!$C$42 | E37: =Data_Entry!$D$42 | F37: =Data_Entry!$E$42 | G37: USD/yr | H37: Average annual fully loaded base salary
B38: Marketing Programs % Revenue | C38: =Data_Entry!$B$43 | D38: =Data_Entry!$C$43 | E38: =Data_Entry!$D$43 | F38: =Data_Entry!$E$43 | G38: % | H38: Demand generation spend as % of revenue
B39: Software / month | C39: =Data_Entry!$B$44 | D39: =Data_Entry!$C$44 | E39: =Data_Entry!$D$44 | F39: =Data_Entry!$E$44 | G39: USD | H39: Core SaaS tools and subscriptions
B40: Rent / month | C40: =Data_Entry!$B$45 | D40: =Data_Entry!$C$45 | E40: =Data_Entry!$D$45 | F40: =Data_Entry!$E$45 | G40: USD | H40: Office / facilities
B41: Travel % Revenue | C41: =Data_Entry!$B$46 | D41: =Data_Entry!$C$46 | E41: =Data_Entry!$D$46 | F41: =Data_Entry!$E$46 | G41: % | H41: Travel and entertainment as % of revenue
B42: Other G&A / month | C42: =Data_Entry!$B$47 | D42: =Data_Entry!$C$47 | E42: =Data_Entry!$D$47 | F42: =Data_Entry!$E$47 | G42: USD | H42: Insurance, audit, admin and misc.

Sheet Revenue
A1: Revenue Schedule
A2: Customers -> ARPU -> revenue -> COGS -> gross profit
A3: Monthly Revenue Model
B4: =Assumptions!$F$6 | C4: =DATE(YEAR(B4),MONTH(B4)+1,1) | D4: =DATE(YEAR(C4),MONTH(C4)+1,1) | E4: =DATE(YEAR(D4),MONTH(D4)+1,1) | F4: =DATE(YEAR(E4),MONTH(E4)+1,1) | G4: =DATE(YEAR(F4),MONTH(F4)+1,1) | H4: =DATE(YEAR(G4),MONTH(G4)+1,1) | I4: =DATE(YEAR(H4),MONTH(H4)+1,1) | J4: =DATE(YEAR(I4),MONTH(I4)+1,1) | ... Y4: =DATE(YEAR(X4),MONTH(X4)+1,1)
A6: Beginning Customers | B6: =Assumptions!$F$14 | C6: =B10 | D6: =C10 | E6: =D10 | F6: =E10 | G6: =F10 | H6: =G10 | I6: =H10 | J6: =I10 | ... Y6: =X10
A7: New Customers | B7: =IF(ISNUMBER(Data_Entry!B52),Data_Entry!B52,Assumptions!$F$15) | C7: =IF(ISNUMBER(Data_Entry!C52),Data_Entry!C52,Assumptions!$F$15) | D7: =IF(ISNUMBER(Data_Entry!D52),Data_Entry!D52,Assumptions!$F$15) | E7: =IF(ISNUMBER(Data_Entry!E52),Data_Entry!E52,Assumptions!$F$15) | F7: =IF(ISNUMBER(Data_Entry!F52),Data_Entry!F52,Assumptions!$F$15) | G7: =IF(ISNUMBER(Data_Entry!G52),Data_Entry!G52,Assumptions!$F$15) | H7: =IF(ISNUMBER(Data_Entry!H52),Data_Entry!H52,Assumptions!$F$15) | I7: =IF(ISNUMBER(Data_Entry!I52),Data_Entry!I52,Assumptions!$F$15) | ... Y7: =IF(ISNUMBER(Data_Entry!Y52),Data_Entry!Y52,Assumptions!$F$15)
A8: Churn % | B8: =Assumptions!$F$16 | C8: =Assumptions!$F$16 | D8: =Assumptions!$F$16 | E8: =Assumptions!$F$16 | F8: =Assumptions!$F$16 | G8: =Assumptions!$F$16 | H8: =Assumptions!$F$16 | I8: =Assumptions!$F$16 | ... Y8: =Assumptions!$F$16
A9: Churned Customers | B9: =B6*B8 | C9: =C6*C8 | D9: =D6*D8 | E9: =E6*E8 | F9: =F6*F8 | G9: =G6*G8 | H9: =H6*H8 | I9: =I6*I8 | ... Y9: =Y6*Y8
A10: Ending Customers | B10: =B6+B7-B9 | C10: =C6+C7-C9 | D10: =D6+D7-D9 | E10: =E6+E7-E9 | F10: =F6+F7-F9 | G10: =G6+G7-G9 | H10: =H6+H7-H9 | I10: =I6+I7-I9 | ... Y10: =Y6+Y7-Y9
A11: ARPU | B11: =Assumptions!$F$17 | C11: =B11*(1+Assumptions!$F$18/12) | D11: =C11*(1+Assumptions!$F$18/12) | E11: =D11*(1+Assumptions!$F$18/12) | F11: =E11*(1+Assumptions!$F$18/12) | G11: =F11*(1+Assumptions!$F$18/12) | H11: =G11*(1+Assumptions!$F$18/12) | I11: =H11*(1+Assumptions!$F$18/12) | J11: =I11*(1+Assumptions!$F$18/12) | ... Y11: =X11*(1+Assumptions!$F$18/12)
A12: Subscription Revenue | B12: =((B6+B10)/2)*B11 | C12: =((C6+C10)/2)*C11 | D12: =((D6+D10)/2)*D11 | E12: =((E6+E10)/2)*E11 | F12: =((F6+F10)/2)*F11 | G12: =((G6+G10)/2)*G11 | H12: =((H6+H10)/2)*H11 | I12: =((I6+I10)/2)*I11 | ... Y12: =((Y6+Y10)/2)*Y11
A13: Implementation Fee / New Cust | B13: =Assumptions!$F$19 | C13: =Assumptions!$F$19 | D13: =Assumptions!$F$19 | E13: =Assumptions!$F$19 | F13: =Assumptions!$F$19 | G13: =Assumptions!$F$19 | H13: =Assumptions!$F$19 | I13: =Assumptions!$F$19 | ... Y13: =Assumptions!$F$19
A14: Implementation Revenue | B14: =B7*B13 | C14: =C7*C13 | D14: =D7*D13 | E14: =E7*E13 | F14: =F7*F13 | G14: =G7*G13 | H14: =H7*H13 | I14: =I7*I13 | ... Y14: =Y7*Y13
A15: Total Revenue | B15: =SUM(B12:B14) | C15: =SUM(C12:C14) | D15: =SUM(D12:D14) | E15: =SUM(E12:E14) | F15: =SUM(F12:F14) | G15: =SUM(G12:G14) | H15: =SUM(H12:H14) | I15: =SUM(I12:I14) | ... Y15: =SUM(Y12:Y14)
A17: COGS % | B17: =Assumptions!$F$20 | C17: =Assumptions!$F$20 | D17: =Assumptions!$F$20 | E17: =Assumptions!$F$20 | F17: =Assumptions!$F$20 | G17: =Assumptions!$F$20 | H17: =Assumptions!$F$20 | I17: =Assumptions!$F$20 | ... Y17: =Assumptions!$F$20
A18: COGS | B18: =B15*B17 | C18: =C15*C17 | D18: =D15*D17 | E18: =E15*E17 | F18: =F15*F17 | G18: =G15*G17 | H18: =H15*H17 | I18: =I15*I17 | ... Y18: =Y15*Y17
A19: Gross Profit | B19: =B15-B18 | C19: =C15-C18 | D19: =D15-D18 | E19: =E15-E18 | F19: =F15-F18 | G19: =G15-G18 | H19: =H15-H18 | I19: =I15-I18 | ... Y19: =Y15-Y18

Sheet Headcount
A1: Headcount & Payroll
A2: Editable hiring plan (blue/yellow) feeding monthly payroll expense.
A3: Department Schedules
B4: =Assumptions!$F$6 | C4: =DATE(YEAR(B4),MONTH(B4)+1,1) | D4: =DATE(YEAR(C4),MONTH(C4)+1,1) | E4: =DATE(YEAR(D4),MONTH(D4)+1,1) | F4: =DATE(YEAR(E4),MONTH(E4)+1,1) | G4: =DATE(YEAR(F4),MONTH(F4)+1,1) | H4: =DATE(YEAR(G4),MONTH(G4)+1,1) | I4: =DATE(YEAR(H4),MONTH(H4)+1,1) | J4: =DATE(YEAR(I4),MONTH(I4)+1,1) | ... Y4: =DATE(YEAR(X4),MONTH(X4)+1,1)
A6: Sales
A7: Opening HC | B7: =Assumptions!$F$28 | C7: =B10 | D7: =C10 | E7: =D10 | F7: =E10 | G7: =F10 | H7: =G10 | I7: =H10 | J7: =I10 | ... Y7: =X10
A8: Hires | B8: =Data_Entry!B52 | C8: =Data_Entry!C52 | D8: =Data_Entry!D52 | E8: =Data_Entry!E52 | F8: =Data_Entry!F52 | G8: =Data_Entry!G52 | H8: =Data_Entry!H52 | I8: =Data_Entry!I52 | ... Y8: =Data_Entry!Y52
A9: Terms | B9: =Data_Entry!B53 | C9: =Data_Entry!C53 | D9: =Data_Entry!D53 | E9: =Data_Entry!E53 | F9: =Data_Entry!F53 | G9: =Data_Entry!G53 | H9: =Data_Entry!H53 | I9: =Data_Entry!I53 | ... Y9: =Data_Entry!Y53
A10: Ending HC | B10: =B7+B8-B9 | C10: =C7+C8-C9 | D10: =D7+D8-D9 | E10: =E7+E8-E9 | F10: =F7+F8-F9 | G10: =G7+G8-G9 | H10: =H7+H8-H9 | I10: =I7+I8-I9 | ... Y10: =Y7+Y8-Y9
A11: Average HC | B11: =(B7+B10)/2 | C11: =(C7+C10)/2 | D11: =(D7+D10)/2 | E11: =(E7+E10)/2 | F11: =(F7+F10)/2 | G11: =(G7+G10)/2 | H11: =(H7+H10)/2 | I11: =(I7+I10)/2 | ... Y11: =(Y7+Y10)/2
A12: Salary Expense | B12: =B11*Assumptions!$F$33/12*(1+Assumptions!$F$21) | C12: =C11*Assumptions!$F$33/12*(1+Assumptions!$F$21) | D12: =D11*Assumptions!$F$33/12*(1+Assumptions!$F$21) | E12: =E11*Assumptions!$F$33/12*(1+Assumptions!$F$21) | F12: =F11*Assumptions!$F$33/12*(1+Assumptions!$F$21) | G12: =G11*Assumptions!$F$33/12*(1+Assumptions!$F$21) | H12: =H11*Assumptions!$F$33/12*(1+Assumptions!$F$21) | I12: =I11*Assumptions!$F$33/12*(1+Assumptions!$F$21) | ... Y12: =Y11*Assumptions!$F$33/12*(1+Assumptions!$F$21)
A15: Marketing
A16: Opening HC | B16: =Assumptions!$F$29 | C16: =B19 | D16: =C19 | E16: =D19 | F16: =E19 | G16: =F19 | H16: =G19 | I16: =H19 | J16: =I19 | ... Y16: =X19
A17: Hires | B17: =Data_Entry!B54 | C17: =Data_Entry!C54 | D17: =Data_Entry!D54 | E17: =Data_Entry!E54 | F17: =Data_Entry!F54 | G17: =Data_Entry!G54 | H17: =Data_Entry!H54 | I17: =Data_Entry!I54 | ... Y17: =Data_Entry!Y54
A18: Terms | B18: =Data_Entry!B55 | C18: =Data_Entry!C55 | D18: =Data_Entry!D55 | E18: =Data_Entry!E55 | F18: =Data_Entry!F55 | G18: =Data_Entry!G55 | H18: =Data_Entry!H55 | I18: =Data_Entry!I55 | ... Y18: =Data_Entry!Y55
A19: Ending HC | B19: =B16+B17-B18 | C19: =C16+C17-C18 | D19: =D16+D17-D18 | E19: =E16+E17-E18 | F19: =F16+F17-F18 | G19: =G16+G17-G18 | H19: =H16+H17-H18 | I19: =I16+I17-I18 | ... Y19: =Y16+Y17-Y18
A20: Average HC | B20: =(B16+B19)/2 | C20: =(C16+C19)/2 | D20: =(D16+D19)/2 | E20: =(E16+E19)/2 | F20: =(F16+F19)/2 | G20: =(G16+G19)/2 | H20: =(H16+H19)/2 | I20: =(I16+I19)/2 | ... Y20: =(Y16+Y19)/2
A21: Salary Expense | B21: =B20*Assumptions!$F$34/12*(1+Assumptions!$F$21) | C21: =C20*Assumptions!$F$34/12*(1+Assumptions!$F$21) | D21: =D20*Assumptions!$F$34/12*(1+Assumptions!$F$21) | E21: =E20*Assumptions!$F$34/12*(1+Assumptions!$F$21) | F21: =F20*Assumptions!$F$34/12*(1+Assumptions!$F$21) | G21: =G20*Assumptions!$F$34/12*(1+Assumptions!$F$21) | H21: =H20*Assumptions!$F$34/12*(1+Assumptions!$F$21) | I21: =I20*Assumptions!$F$34/12*(1+Assumptions!$F$21) | ... Y21: =Y20*Assumptions!$F$34/12*(1+Assumptions!$F$21)
A24: R&D
A25: Opening HC | B25: =Assumptions!$F$30 | C25: =B28 | D25: =C28 | E25: =D28 | F25: =E28 | G25: =F28 | H25: =G28 | I25: =H28 | J25: =I28 | ... Y25: =X28
A26: Hires | B26: =Data_Entry!B56 | C26: =Data_Entry!C56 | D26: =Data_Entry!D56 | E26: =Data_Entry!E56 | F26: =Data_Entry!F56 | G26: =Data_Entry!G56 | H26: =Data_Entry!H56 | I26: =Data_Entry!I56 | ... Y26: =Data_Entry!Y56
A27: Terms | B27: =Data_Entry!B57 | C27: =Data_Entry!C57 | D27: =Data_Entry!D57 | E27: =Data_Entry!E57 | F27: =Data_Entry!F57 | G27: =Data_Entry!G57 | H27: =Data_Entry!H57 | I27: =Data_Entry!I57 | ... Y27: =Data_Entry!Y57
A28: Ending HC | B28: =B25+B26-B27 | C28: =C25+C26-C27 | D28: =D25+D26-D27 | E28: =E25+E26-E27 | F28: =F25+F26-F27 | G28: =G25+G26-G27 | H28: =H25+H26-H27 | I28: =I25+I26-I27 | ... Y28: =Y25+Y26-Y27
A29: Average HC | B29: =(B25+B28)/2 | C29: =(C25+C28)/2 | D29: =(D25+D28)/2 | E29: =(E25+E28)/2 | F29: =(F25+F28)/2 | G29: =(G25+G28)/2 | H29: =(H25+H28)/2 | I29: =(I25+I28)/2 | ... Y29: =(Y25+Y28)/2
A30: Salary Expense | B30: =B29*Assumptions!$F$35/12*(1+Assumptions!$F$21) | C30: =C29*Assumptions!$F$35/12*(1+Assumptions!$F$21) | D30: =D29*Assumptions!$F$35/12*(1+Assumptions!$F$21) | E30: =E29*Assumptions!$F$35/12*(1+Assumptions!$F$21) | F30: =F29*Assumptions!$F$35/12*(1+Assumptions!$F$21) | G30: =G29*Assumptions!$F$35/12*(1+Assumptions!$F$21) | H30: =H29*Assumptions!$F$35/12*(1+Assumptions!$F$21) | I30: =I29*Assumptions!$F$35/12*(1+Assumptions!$F$21) | ... Y30: =Y29*Assumptions!$F$35/12*(1+Assumptions!$F$21)
A33: G&A
A34: Opening HC | B34: =Assumptions!$F$31 | C34: =B37 | D34: =C37 | E34: =D37 | F34: =E37 | G34: =F37 | H34: =G37 | I34: =H37 | J34: =I37 | ... Y34: =X37
A35: Hires | B35: =Data_Entry!B58 | C35: =Data_Entry!C58 | D35: =Data_Entry!D58 | E35: =Data_Entry!E58 | F35: =Data_Entry!F58 | G35: =Data_Entry!G58 | H35: =Data_Entry!H58 | I35: =Data_Entry!I58 | ... Y35: =Data_Entry!Y58
A36: Terms | B36: =Data_Entry!B59 | C36: =Data_Entry!C59 | D36: =Data_Entry!D59 | E36: =Data_Entry!E59 | F36: =Data_Entry!F59 | G36: =Data_Entry!G59 | H36: =Data_Entry!H59 | I36: =Data_Entry!I59 | ... Y36: =Data_Entry!Y59
A37: Ending HC | B37: =B34+B35-B36 | C37: =C34+C35-C36 | D37: =D34+D35-D36 | E37: =E34+E35-E36 | F37: =F34+F35-F36 | G37: =G34+G35-G36 | H37: =H34+H35-H36 | I37: =I34+I35-I36 | ... Y37: =Y34+Y35-Y36
A38: Average HC | B38: =(B34+B37)/2 | C38: =(C34+C37)/2 | D38: =(D34+D37)/2 | E38: =(E34+E37)/2 | F38: =(F34+F37)/2 | G38: =(G34+G37)/2 | H38: =(H34+H37)/2 | I38: =(I34+I37)/2 | ... Y38: =(Y34+Y37)/2
A39: Salary Expense | B39: =B38*Assumptions!$F$36/12*(1+Assumptions!$F$21) | C39: =C38*Assumptions!$F$36/12*(1+Assumptions!$F$21) | D39: =D38*Assumptions!$F$36/12*(1+Assumptions!$F$21) | E39: =E38*Assumptions!$F$36/12*(1+Assumptions!$F$21) | F39: =F38*Assumptions!$F$36/12*(1+Assumptions!$F$21) | G39: =G38*Assumptions!$F$36/12*(1+Assumptions!$F$21) | H39: =H38*Assumptions!$F$36/12*(1+Assumptions!$F$21) | I39: =I38*Assumptions!$F$36/12*(1+Assumptions!$F$21) | ... Y39: =Y38*Assumptions!$F$36/12*(1+Assumptions!$F$21)
A42: Customer Success
A43: Opening HC | B43: =Assumptions!$F$32 | C43: =B46 | D43: =C46 | E43: =D46 | F43: =E46 | G43: =F46 | H43: =G46 | I43: =H46 | J43: =I46 | ... Y43: =X46
A44: Hires | B44: =Data_Entry!B60 | C44: =Data_Entry!C60 | D44: =Data_Entry!D60 | E44: =Data_Entry!E60 | F44: =Data_Entry!F60 | G44: =Data_Entry!G60 | H44: =Data_Entry!H60 | I44: =Data_Entry!I60 | ... Y44: =Data_Entry!Y60
A45: Terms | B45: =Data_Entry!B61 | C45: =Data_Entry!C61 | D45: =Data_Entry!D61 | E45: =Data_Entry!E61 | F45: =Data_Entry!F61 | G45: =Data_Entry!G61 | H45: =Data_Entry!H61 | I45: =Data_Entry!I61 | ... Y45: =Data_Entry!Y61
A46: Ending HC | B46: =B43+B44-B45 | C46: =C43+C44-C45 | D46: =D43+D44-D45 | E46: =E43+E44-E45 | F46: =F43+F44-F45 | G46: =G43+G44-G45 | H46: =H43+H44-H45 | I46: =I43+I44-I45 | ... Y46: =Y43+Y44-Y45
A47: Average HC | B47: =(B43+B46)/2 | C47: =(C43+C46)/2 | D47: =(D43+D46)/2 | E47: =(E43+E46)/2 | F47: =(F43+F46)/2 | G47: =(G43+G46)/2 | H47: =(H43+H46)/2 | I47: =(I43+I46)/2 | ... Y47: =(Y43+Y46)/2
A48: Salary Expense | B48: =B47*Assumptions!$F$37/12*(1+Assumptions!$F$21) | C48: =C47*Assumptions!$F$37/12*(1+Assumptions!$F$21) | D48: =D47*Assumptions!$F$37/12*(1+Assumptions!$F$21) | E48: =E47*Assumptions!$F$37/12*(1+Assumptions!$F$21) | F48: =F47*Assumptions!$F$37/12*(1+Assumptions!$F$21) | G48: =G47*Assumptions!$F$37/12*(1+Assumptions!$F$21) | H48: =H47*Assumptions!$F$37/12*(1+Assumptions!$F$21) | I48: =I47*Assumptions!$F$37/12*(1+Assumptions!$F$21) | ... Y48: =Y47*Assumptions!$F$37/12*(1+Assumptions!$F$21)
A51: Headcount Summary
A52: Total Ending HC | B52: =B10+B19+B28+B37+B46 | C52: =C10+C19+C28+C37+C46 | D52: =D10+D19+D28+D37+D46 | E52: =E10+E19+E28+E37+E46 | F52: =F10+F19+F28+F37+F46 | G52: =G10+G19+G28+G37+G46 | H52: =H10+H19+H28+H37+H46 | I52: =I10+I19+I28+I37+I46 | ... Y52: =Y10+Y19+Y28+Y37+Y46
A53: Total Payroll Expense | B53: =B12+B21+B30+B39+B48 | C53: =C12+C21+C30+C39+C48 | D53: =D12+D21+D30+D39+D48 | E53: =E12+E21+E30+E39+E48 | F53: =F12+F21+F30+F39+F48 | G53: =G12+G21+G30+G39+G48 | H53: =H12+H21+H30+H39+H48 | I53: =I12+I21+I30+I39+I48 | ... Y53: =Y12+Y21+Y30+Y39+Y48

Sheet Opex
A1: Operating Expense Schedule
A2: Payroll linked from Headcount; other opex driven by assumptions and revenue.
A3: Monthly Opex
B4: =Assumptions!$F$6 | C4: =DATE(YEAR(B4),MONTH(B4)+1,1) | D4: =DATE(YEAR(C4),MONTH(C4)+1,1) | E4: =DATE(YEAR(D4),MONTH(D4)+1,1) | F4: =DATE(YEAR(E4),MONTH(E4)+1,1) | G4: =DATE(YEAR(F4),MONTH(F4)+1,1) | H4: =DATE(YEAR(G4),MONTH(G4)+1,1) | I4: =DATE(YEAR(H4),MONTH(H4)+1,1) | J4: =DATE(YEAR(I4),MONTH(I4)+1,1) | ... Y4: =DATE(YEAR(X4),MONTH(X4)+1,1)
A6: Payroll Expense | B6: =Headcount!B53 | C6: =Headcount!C53 | D6: =Headcount!D53 | E6: =Headcount!E53 | F6: =Headcount!F53 | G6: =Headcount!G53 | H6: =Headcount!H53 | I6: =Headcount!I53 | ... Y6: =Headcount!Y53
A7: Marketing Programs | B7: =Revenue!B15*Assumptions!$F$38 | C7: =Revenue!C15*Assumptions!$F$38 | D7: =Revenue!D15*Assumptions!$F$38 | E7: =Revenue!E15*Assumptions!$F$38 | F7: =Revenue!F15*Assumptions!$F$38 | G7: =Revenue!G15*Assumptions!$F$38 | H7: =Revenue!H15*Assumptions!$F$38 | I7: =Revenue!I15*Assumptions!$F$38 | ... Y7: =Revenue!Y15*Assumptions!$F$38
A8: Software | B8: =Assumptions!$F$39 | C8: =Assumptions!$F$39 | D8: =Assumptions!$F$39 | E8: =Assumptions!$F$39 | F8: =Assumptions!$F$39 | G8: =Assumptions!$F$39 | H8: =Assumptions!$F$39 | I8: =Assumptions!$F$39 | ... Y8: =Assumptions!$F$39
A9: Rent | B9: =Assumptions!$F$40 | C9: =Assumptions!$F$40 | D9: =Assumptions!$F$40 | E9: =Assumptions!$F$40 | F9: =Assumptions!$F$40 | G9: =Assumptions!$F$40 | H9: =Assumptions!$F$40 | I9: =Assumptions!$F$40 | ... Y9: =Assumptions!$F$40
A10: Travel & Entertainment | B10: =Revenue!B15*Assumptions!$F$41 | C10: =Revenue!C15*Assumptions!$F$41 | D10: =Revenue!D15*Assumptions!$F$41 | E10: =Revenue!E15*Assumptions!$F$41 | F10: =Revenue!F15*Assumptions!$F$41 | G10: =Revenue!G15*Assumptions!$F$41 | H10: =Revenue!H15*Assumptions!$F$41 | I10: =Revenue!I15*Assumptions!$F$41 | ... Y10: =Revenue!Y15*Assumptions!$F$41
A11: Other G&A | B11: =Assumptions!$F$42 | C11: =Assumptions!$F$42 | D11: =Assumptions!$F$42 | E11: =Assumptions!$F$42 | F11: =Assumptions!$F$42 | G11: =Assumptions!$F$42 | H11: =Assumptions!$F$42 | I11: =Assumptions!$F$42 | ... Y11: =Assumptions!$F$42
A12: Total Opex | B12: =SUM(B6:B11) | C12: =SUM(C6:C11) | D12: =SUM(D6:D11) | E12: =SUM(E6:E11) | F12: =SUM(F6:F11) | G12: =SUM(G6:G11) | H12: =SUM(H6:H11) | I12: =SUM(I6:I11) | ... Y12: =SUM(Y6:Y11)

Sheet Working_Capital
A1: Working Capital Schedule
A2: AR / AP balances based on DSO and DPO.
A3: Monthly Working Capital
B4: =Assumptions!$F$6 | C4: =DATE(YEAR(B4),MONTH(B4)+1,1) | D4: =DATE(YEAR(C4),MONTH(C4)+1,1) | E4: =DATE(YEAR(D4),MONTH(D4)+1,1) | F4: =DATE(YEAR(E4),MONTH(E4)+1,1) | G4: =DATE(YEAR(F4),MONTH(F4)+1,1) | H4: =DATE(YEAR(G4),MONTH(G4)+1,1) | I4: =DATE(YEAR(H4),MONTH(H4)+1,1) | J4: =DATE(YEAR(I4),MONTH(I4)+1,1) | ... Y4: =DATE(YEAR(X4),MONTH(X4)+1,1)
A6: Accounts Receivable | B6: =Revenue!B15/30*Assumptions!$F$23 | C6: =Revenue!C15/30*Assumptions!$F$23 | D6: =Revenue!D15/30*Assumptions!$F$23 | E6: =Revenue!E15/30*Assumptions!$F$23 | F6: =Revenue!F15/30*Assumptions!$F$23 | G6: =Revenue!G15/30*Assumptions!$F$23 | H6: =Revenue!H15/30*Assumptions!$F$23 | I6: =Revenue!I15/30*Assumptions!$F$23 | ... Y6: =Revenue!Y15/30*Assumptions!$F$23
A7: AP Base Costs | B7: =Revenue!B18+Opex!B7+Opex!B8+Opex!B9+Opex!B10+Opex!B11 | C7: =Revenue!C18+Opex!C7+Opex!C8+Opex!C9+Opex!C10+Opex!C11 | D7: =Revenue!D18+Opex!D7+Opex!D8+Opex!D9+Opex!D10+Opex!D11 | E7: =Revenue!E18+Opex!E7+Opex!E8+Opex!E9+Opex!E10+Opex!E11 | F7: =Revenue!F18+Opex!F7+Opex!F8+Opex!F9+Opex!F10+Opex!F11 | G7: =Revenue!G18+Opex!G7+Opex!G8+Opex!G9+Opex!G10+Opex!G11 | H7: =Revenue!H18+Opex!H7+Opex!H8+Opex!H9+Opex!H10+Opex!H11 | I7: =Revenue!I18+Opex!I7+Opex!I8+Opex!I9+Opex!I10+Opex!I11 | ... Y7: =Revenue!Y18+Opex!Y7+Opex!Y8+Opex!Y9+Opex!Y10+Opex!Y11
A8: Accounts Payable | B8: =B7/30*Assumptions!$F$24 | C8: =C7/30*Assumptions!$F$24 | D8: =D7/30*Assumptions!$F$24 | E8: =E7/30*Assumptions!$F$24 | F8: =F7/30*Assumptions!$F$24 | G8: =G7/30*Assumptions!$F$24 | H8: =H7/30*Assumptions!$F$24 | I8: =I7/30*Assumptions!$F$24 | ... Y8: =Y7/30*Assumptions!$F$24
A9: Change in AR | B9: =B6-Assumptions!$F$8 | C9: =C6-B6 | D9: =D6-C6 | E9: =E6-D6 | F9: =F6-E6 | G9: =G6-F6 | H9: =H6-G6 | I9: =I6-H6 | J9: =J6-I6 | ... Y9: =Y6-X6
A10: Change in AP | B10: =B8-Assumptions!$F$10 | C10: =C8-B8 | D10: =D8-C8 | E10: =E8-D8 | F10: =F8-E8 | G10: =G8-F8 | H10: =H8-G8 | I10: =I8-H8 | J10: =J8-I8 | ... Y10: =Y8-X8

Sheet Capex
A1: Capex & Depreciation
A2: Capex driven as % of revenue with straight-line depreciation.
A3: Monthly Capex
B4: =Assumptions!$F$6 | C4: =DATE(YEAR(B4),MONTH(B4)+1,1) | D4: =DATE(YEAR(C4),MONTH(C4)+1,1) | E4: =DATE(YEAR(D4),MONTH(D4)+1,1) | F4: =DATE(YEAR(E4),MONTH(E4)+1,1) | G4: =DATE(YEAR(F4),MONTH(F4)+1,1) | H4: =DATE(YEAR(G4),MONTH(G4)+1,1) | I4: =DATE(YEAR(H4),MONTH(H4)+1,1) | J4: =DATE(YEAR(I4),MONTH(I4)+1,1) | ... Y4: =DATE(YEAR(X4),MONTH(X4)+1,1)
A6: Opening Net PP&E | B6: =Assumptions!$F$9 | C6: =B9 | D6: =C9 | E6: =D9 | F6: =E9 | G6: =F9 | H6: =G9 | I6: =H9 | J6: =I9 | ... Y6: =X9
A7: Capex | B7: =Revenue!B15*Assumptions!$F$27 | C7: =Revenue!C15*Assumptions!$F$27 | D7: =Revenue!D15*Assumptions!$F$27 | E7: =Revenue!E15*Assumptions!$F$27 | F7: =Revenue!F15*Assumptions!$F$27 | G7: =Revenue!G15*Assumptions!$F$27 | H7: =Revenue!H15*Assumptions!$F$27 | I7: =Revenue!I15*Assumptions!$F$27 | ... Y7: =Revenue!Y15*Assumptions!$F$27
A8: Depreciation | B8: =SUM(B7:B7)/Assumptions!$F$26 | C8: =SUM(B7:C7)/Assumptions!$F$26 | D8: =SUM(B7:D7)/Assumptions!$F$26 | E8: =SUM(B7:E7)/Assumptions!$F$26 | F8: =SUM(B7:F7)/Assumptions!$F$26 | G8: =SUM(B7:G7)/Assumptions!$F$26 | H8: =SUM(B7:H7)/Assumptions!$F$26 | I8: =SUM(B7:I7)/Assumptions!$F$26 | J8: =SUM(B7:J7)/Assumptions!$F$26 | K8: =SUM(B7:K7)/Assumptions!$F$26 | L8: =SUM(B7:L7)/Assumptions!$F$26 | M8: =SUM(B7:M7)/Assumptions!$F$26 | N8: =SUM(B7:N7)/Assumptions!$F$26 | O8: =SUM(B7:O7)/Assumptions!$F$26 | P8: =SUM(B7:P7)/Assumptions!$F$26 | Q8: =SUM(B7:Q7)/Assumptions!$F$26 | R8: =SUM(B7:R7)/Assumptions!$F$26 | S8: =SUM(B7:S7)/Assumptions!$F$26 | T8: =SUM(B7:T7)/Assumptions!$F$26 | U8: =SUM(B7:U7)/Assumptions!$F$26 | V8: =SUM(B7:V7)/Assumptions!$F$26 | W8: =SUM(B7:W7)/Assumptions!$F$26 | X8: =SUM(B7:X7)/Assumptions!$F$26 | Y8: =SUM(B7:Y7)/Assumptions!$F$26
A9: Ending Net PP&E | B9: =B6+B7-B8 | C9: =C6+C7-C8 | D9: =D6+D7-D8 | E9: =E6+E7-E8 | F9: =F6+F7-F8 | G9: =G6+G7-G8 | H9: =H6+H7-H8 | I9: =I6+I7-I8 | ... Y9: =Y6+Y7-Y8

Sheet Checks
A1: Checks & QA
A2: Quality checks to prove the file is clean before client handoff.
B4: Core Checks
B5: Check | C5: Formula / Value | D5: Status | E5: Threshold
B6: Scenario selected | C6: =Control!C6
B7: First month BS balance | C7: =ABS(BS!B19) | D7: =IF(C7<1,"PASS","FAIL") | E7: < 1
B8: Last month BS balance | C8: =ABS(BS!Y19) | D8: =IF(C8<1,"PASS","FAIL") | E8: < 1
B9: Minimum ending cash | C9: =MIN(CF!B21:Y21) | D9: =IF(C9>0,"PASS","FAIL") | E9: > 0
B10: 2026 EBITDA margin | C10: =Dashboard!C16 | D10: =IF(C10>=0,"OK","REVIEW") | E10: review
B11: 2027 EBITDA margin | C11: =Dashboard!D16 | D11: =IF(C11>=0,"OK","REVIEW") | E11: review

Sheet Debt
A1: Debt Schedule
A2: Illustrative debt roll-forward with editable draws and repayments.
A3: Monthly Debt
B4: =Assumptions!$F$6 | C4: =DATE(YEAR(B4),MONTH(B4)+1,1) | D4: =DATE(YEAR(C4),MONTH(C4)+1,1) | E4: =DATE(YEAR(D4),MONTH(D4)+1,1) | F4: =DATE(YEAR(E4),MONTH(E4)+1,1) | G4: =DATE(YEAR(F4),MONTH(F4)+1,1) | H4: =DATE(YEAR(G4),MONTH(G4)+1,1) | I4: =DATE(YEAR(H4),MONTH(H4)+1,1) | J4: =DATE(YEAR(I4),MONTH(I4)+1,1) | ... Y4: =DATE(YEAR(X4),MONTH(X4)+1,1)
A6: Opening Debt | B6: =Assumptions!$F$11 | C6: =B9 | D6: =C9 | E6: =D9 | F6: =E9 | G6: =F9 | H6: =G9 | I6: =H9 | J6: =I9 | ... Y6: =X9
A7: Debt Draws | B7: =Data_Entry!B66 | C7: =Data_Entry!C66 | D7: =Data_Entry!D66 | E7: =Data_Entry!E66 | F7: =Data_Entry!F66 | G7: =Data_Entry!G66 | H7: =Data_Entry!H66 | I7: =Data_Entry!I66 | ... Y7: =Data_Entry!Y66
A8: Debt Repayments | B8: =Data_Entry!B67 | C8: =Data_Entry!C67 | D8: =Data_Entry!D67 | E8: =Data_Entry!E67 | F8: =Data_Entry!F67 | G8: =Data_Entry!G67 | H8: =Data_Entry!H67 | I8: =Data_Entry!I67 | ... Y8: =Data_Entry!Y67
A9: Ending Debt | B9: =B6+B7-B8 | C9: =C6+C7-C8 | D9: =D6+D7-D8 | E9: =E6+E7-E8 | F9: =F6+F7-F8 | G9: =G6+G7-G8 | H9: =H6+H7-H8 | I9: =I6+I7-I8 | ... Y9: =Y6+Y7-Y8
A10: Interest Expense | B10: =((B6+B9)/2)*Assumptions!$F$25/12 | C10: =((C6+C9)/2)*Assumptions!$F$25/12 | D10: =((D6+D9)/2)*Assumptions!$F$25/12 | E10: =((E6+E9)/2)*Assumptions!$F$25/12 | F10: =((F6+F9)/2)*Assumptions!$F$25/12 | G10: =((G6+G9)/2)*Assumptions!$F$25/12 | H10: =((H6+H9)/2)*Assumptions!$F$25/12 | I10: =((I6+I9)/2)*Assumptions!$F$25/12 | ... Y10: =((Y6+Y9)/2)*Assumptions!$F$25/12

Sheet IS
A1: Income Statement
A2: Integrated monthly P&L
A3: Monthly Income Statement
B4: =Assumptions!$F$6 | C4: =DATE(YEAR(B4),MONTH(B4)+1,1) | D4: =DATE(YEAR(C4),MONTH(C4)+1,1) | E4: =DATE(YEAR(D4),MONTH(D4)+1,1) | F4: =DATE(YEAR(E4),MONTH(E4)+1,1) | G4: =DATE(YEAR(F4),MONTH(F4)+1,1) | H4: =DATE(YEAR(G4),MONTH(G4)+1,1) | I4: =DATE(YEAR(H4),MONTH(H4)+1,1) | J4: =DATE(YEAR(I4),MONTH(I4)+1,1) | ... Y4: =DATE(YEAR(X4),MONTH(X4)+1,1)
A6: Total Revenue | B6: =Revenue!B15 | C6: =Revenue!C15 | D6: =Revenue!D15 | E6: =Revenue!E15 | F6: =Revenue!F15 | G6: =Revenue!G15 | H6: =Revenue!H15 | I6: =Revenue!I15 | ... Y6: =Revenue!Y15
A7: COGS | B7: =Revenue!B18 | C7: =Revenue!C18 | D7: =Revenue!D18 | E7: =Revenue!E18 | F7: =Revenue!F18 | G7: =Revenue!G18 | H7: =Revenue!H18 | I7: =Revenue!I18 | ... Y7: =Revenue!Y18
A8: Gross Profit | B8: =B6-B7 | C8: =C6-C7 | D8: =D6-D7 | E8: =E6-E7 | F8: =F6-F7 | G8: =G6-G7 | H8: =H6-H7 | I8: =I6-I7 | ... Y8: =Y6-Y7
A10: Payroll Expense | B10: =Opex!B6 | C10: =Opex!C6 | D10: =Opex!D6 | E10: =Opex!E6 | F10: =Opex!F6 | G10: =Opex!G6 | H10: =Opex!H6 | I10: =Opex!I6 | ... Y10: =Opex!Y6
A11: Non-Payroll Opex | B11: =Opex!B12-Opex!B6 | C11: =Opex!C12-Opex!C6 | D11: =Opex!D12-Opex!D6 | E11: =Opex!E12-Opex!E6 | F11: =Opex!F12-Opex!F6 | G11: =Opex!G12-Opex!G6 | H11: =Opex!H12-Opex!H6 | I11: =Opex!I12-Opex!I6 | ... Y11: =Opex!Y12-Opex!Y6
A12: EBITDA | B12: =B8-B10-B11 | C12: =C8-C10-C11 | D12: =D8-D10-D11 | E12: =E8-E10-E11 | F12: =F8-F10-F11 | G12: =G8-G10-G11 | H12: =H8-H10-H11 | I12: =I8-I10-I11 | ... Y12: =Y8-Y10-Y11
A13: Depreciation | B13: =Capex!B8 | C13: =Capex!C8 | D13: =Capex!D8 | E13: =Capex!E8 | F13: =Capex!F8 | G13: =Capex!G8 | H13: =Capex!H8 | I13: =Capex!I8 | ... Y13: =Capex!Y8
A14: EBIT | B14: =B12-B13 | C14: =C12-C13 | D14: =D12-D13 | E14: =E12-E13 | F14: =F12-F13 | G14: =G12-G13 | H14: =H12-H13 | I14: =I12-I13 | ... Y14: =Y12-Y13
A15: Interest | B15: =Debt!B10 | C15: =Debt!C10 | D15: =Debt!D10 | E15: =Debt!E10 | F15: =Debt!F10 | G15: =Debt!G10 | H15: =Debt!H10 | I15: =Debt!I10 | ... Y15: =Debt!Y10
A16: EBT | B16: =B14-B15 | C16: =C14-C15 | D16: =D14-D15 | E16: =E14-E15 | F16: =F14-F15 | G16: =G14-G15 | H16: =H14-H15 | I16: =I14-I15 | ... Y16: =Y14-Y15
A17: Taxes | B17: =MAX(0,B16*Assumptions!$F$22) | C17: =MAX(0,C16*Assumptions!$F$22) | D17: =MAX(0,D16*Assumptions!$F$22) | E17: =MAX(0,E16*Assumptions!$F$22) | F17: =MAX(0,F16*Assumptions!$F$22) | G17: =MAX(0,G16*Assumptions!$F$22) | H17: =MAX(0,H16*Assumptions!$F$22) | I17: =MAX(0,I16*Assumptions!$F$22) | ... Y17: =MAX(0,Y16*Assumptions!$F$22)
A18: Net Income | B18: =B16-B17 | C18: =C16-C17 | D18: =D16-D17 | E18: =E16-E17 | F18: =F16-F17 | G18: =G16-G17 | H18: =H16-H17 | I18: =I16-I17 | ... Y18: =Y16-Y17

Sheet Budget_vs_Actual
A1: Budget vs Actual – Monthly Variance Analysis
A2: HubSpot (HUBS) | FY2024 Forecast (Budget) vs Illustrative Actuals | USD
A3: Budget = Base Scenario from IS sheet. Actuals = illustrative ±variance for demo purposes.
A4: Legend: | C4: Budget | D4: Actual | E4: Variance $ | F4: Variance % | G4: Favourable | H4: Unfavourable
A6: Metric | B6: Jan-24 | F6: Feb-24 | J6: Mar-24 | N6: Apr-24 | R6: May-24 | V6: Jun-24 | Z6: Jul-24 | AD6: Aug-24 | AH6: Sep-24 | AL6: Oct-24 | AP6: Nov-24 | AT6: Dec-24 | AY6: FY2024 Budget | AZ6: FY2024 Actual | BA6: Total Var $ | BB6: Total Var %
B7: Budget | C7: Actual | D7: Var $ | E7: Var % | F7: Budget | G7: Actual | H7: Var $ | I7: Var % | J7: Budget | K7: Actual | L7: Var $ | M7: Var % | N7: Budget | O7: Actual | P7: Var $ | Q7: Var % | R7: Budget | S7: Actual | T7: Var $ | U7: Var % | V7: Budget | W7: Actual | X7: Var $ | Y7: Var % | Z7: Budget | AA7: Actual | AB7: Var $ | AC7: Var % | AD7: Budget | AE7: Actual | AF7: Var $ | AG7: Var % | AH7: Budget | AI7: Actual | AJ7: Var $ | AK7: Var % | AL7: Budget | AM7: Actual | AN7: Var $ | AO7: Var % | AP7: Budget | AQ7: Actual | AR7: Var $ | AS7: Var % | AT7: Budget | AU7: Actual | AV7: Var $ | AW7: Var %
A8: REVENUE
A9: Total Revenue | B9: =IS!B6 | C9: =B9*0.97 | D9: =C9-B9 | E9: =IF(B9=0,"-",D9/B9) | F9: =IS!C6 | G9: =F9*1.01 | H9: =G9-F9 | I9: =IF(F9=0,"-",H9/F9) | J9: =IS!D6 | K9: =J9*0.99 | L9: =K9-J9 | M9: =IF(J9=0,"-",L9/J9) | N9: =IS!E6 | O9: =N9*1.03 | P9: =O9-N9 | Q9: =IF(N9=0,"-",P9/N9) | R9: =IS!F6 | S9: =R9*1.02 | T9: =S9-R9 | U9: =IF(R9=0,"-",T9/R9) | V9: =IS!G6 | W9: =V9*0.98 | X9: =W9-V9 | Y9: =IF(V9=0,"-",X9/V9) | Z9: =IS!H6 | AA9: =Z9*1.04 | AB9: =AA9-Z9 | AC9: =IF(Z9=0,"-",AB9/Z9) | AD9: =IS!I6 | AE9: =AD9*1.01 | AF9: =AE9-AD9 | AG9: =IF(AD9=0,"-",AF9/AD9) | AH9: =IS!J6 | AI9: =AH9*0.99 | AJ9: =AI9-AH9 | AK9: =IF(AH9=0,"-",AJ9/AH9) | AL9: =IS!K6 | AM9: =AL9*1.05 | AN9: =AM9-AL9 | AO9: =IF(AL9=0,"-",AN9/AL9) | AP9: =IS!L6 | AQ9: =AP9*1.02 | AR9: =AQ9-AP9 | AS9: =IF(AP9=0,"-",AR9/AP9) | AT9: =IS!M6 | AU9: =AT9*1.03 | AV9: =AU9-AT9 | AW9: =IF(AT9=0,"-",AV9/AT9) | AY9: =SUM(B9:AT9) | AZ9: =SUM(C9:AU9) | BA9: =AZ9-AY9 | BB9: =IF(AY9=0,"-",BA9/AY9)
A11: GROSS PROFIT
A12: COGS | B12: =IS!B7 | C12: =B12*0.9409 | D12: =C12-B12 | E12: =IF(B12=0,"-",D12/B12) | F12: =IS!C7 | G12: =F12*0.9797 | H12: =G12-F12 | I12: =IF(F12=0,"-",H12/F12) | J12: =IS!D7 | K12: =J12*0.9603 | L12: =K12-J12 | M12: =IF(J12=0,"-",L12/J12) | N12: =IS!E7 | O12: =N12*0.9991 | P12: =O12-N12 | Q12: =IF(N12=0,"-",P12/N12) | R12: =IS!F7 | S12: =R12*0.9894 | T12: =S12-R12 | U12: =IF(R12=0,"-",T12/R12) | V12: =IS!G7 | W12: =V12*0.9506 | X12: =W12-V12 | Y12: =IF(V12=0,"-",X12/V12) | Z12: =IS!H7 | AA12: =Z12*1.0088 | AB12: =AA12-Z12 | AC12: =IF(Z12=0,"-",AB12/Z12) | AD12: =IS!I7 | AE12: =AD12*0.9797 | AF12: =AE12-AD12 | AG12: =IF(AD12=0,"-",AF12/AD12) | AH12: =IS!J7 | AI12: =AH12*0.9603 | AJ12: =AI12-AH12 | AK12: =IF(AH12=0,"-",AJ12/AH12) | AL12: =IS!K7 | AM12: =AL12*1.0185 | AN12: =AM12-AL12 | AO12: =IF(AL12=0,"-",AN12/AL12) | AP12: =IS!L7 | AQ12: =AP12*0.9894 | AR12: =AQ12-AP12 | AS12: =IF(AP12=0,"-",AR12/AP12) | AT12: =IS!M7 | AU12: =AT12*0.9991 | AV12: =AU12-AT12 | AW12: =IF(AT12=0,"-",AV12/AT12) | AY12: =SUM(B12:AT12) | AZ12: =SUM(C12:AU12) | BA12: =AZ12-AY12 | BB12: =IF(AY12=0,"-",BA12/AY12)
A13: Gross Profit | B13: =IS!B8 | C13: =B13*0.9894 | D13: =C13-B13 | E13: =IF(B13=0,"-",D13/B13) | F13: =IS!C8 | G13: =F13*1.0302 | H13: =G13-F13 | I13: =IF(F13=0,"-",H13/F13) | J13: =IS!D8 | K13: =J13*1.0098 | L13: =K13-J13 | M13: =IF(J13=0,"-",L13/J13) | N13: =IS!E8 | O13: =N13*1.0506 | P13: =O13-N13 | Q13: =IF(N13=0,"-",P13/N13) | R13: =IS!F8 | S13: =R13*1.0404 | T13: =S13-R13 | U13: =IF(R13=0,"-",T13/R13) | V13: =IS!G8 | W13: =V13*0.9996 | X13: =W13-V13 | Y13: =IF(V13=0,"-",X13/V13) | Z13: =IS!H8 | AA13: =Z13*1.0608 | AB13: =AA13-Z13 | AC13: =IF(Z13=0,"-",AB13/Z13) | AD13: =IS!I8 | AE13: =AD13*1.0302 | AF13: =AE13-AD13 | AG13: =IF(AD13=0,"-",AF13/AD13) | AH13: =IS!J8 | AI13: =AH13*1.0098 | AJ13: =AI13-AH13 | AK13: =IF(AH13=0,"-",AJ13/AH13) | AL13: =IS!K8 | AM13: =AL13*1.071 | AN13: =AM13-AL13 | AO13: =IF(AL13=0,"-",AN13/AL13) | AP13: =IS!L8 | AQ13: =AP13*1.0404 | AR13: =AQ13-AP13 | AS13: =IF(AP13=0,"-",AR13/AP13) | AT13: =IS!M8 | AU13: =AT13*1.0506 | AV13: =AU13-AT13 | AW13: =IF(AT13=0,"-",AV13/AT13) | AY13: =SUM(B13:AT13) | AZ13: =SUM(C13:AU13) | BA13: =AZ13-AY13 | BB13: =IF(AY13=0,"-",BA13/AY13)
A15: OPERATING EXPENSES
A16: Payroll Expense | B16: =IS!B10 | C16: =B16*1.0088 | D16: =C16-B16 | E16: =IF(B16=0,"-",D16/B16) | F16: =IS!C10 | G16: =F16*1.0504 | H16: =G16-F16 | I16: =IF(F16=0,"-",H16/F16) | J16: =IS!D10 | K16: =J16*1.0296 | L16: =K16-J16 | M16: =IF(J16=0,"-",L16/J16) | N16: =IS!E10 | O16: =N16*1.0712 | P16: =O16-N16 | Q16: =IF(N16=0,"-",P16/N16) | R16: =IS!F10 | S16: =R16*1.0608 | T16: =S16-R16 | U16: =IF(R16=0,"-",T16/R16) | V16: =IS!G10 | W16: =V16*1.0192 | X16: =W16-V16 | Y16: =IF(V16=0,"-",X16/V16) | Z16: =IS!H10 | AA16: =Z16*1.0816 | AB16: =AA16-Z16 | AC16: =IF(Z16=0,"-",AB16/Z16) | AD16: =IS!I10 | AE16: =AD16*1.0504 | AF16: =AE16-AD16 | AG16: =IF(AD16=0,"-",AF16/AD16) | AH16: =IS!J10 | AI16: =AH16*1.0296 | AJ16: =AI16-AH16 | AK16: =IF(AH16=0,"-",AJ16/AH16) | AL16: =IS!K10 | AM16: =AL16*1.092 | AN16: =AM16-AL16 | AO16: =IF(AL16=0,"-",AN16/AL16) | AP16: =IS!L10 | AQ16: =AP16*1.0608 | AR16: =AQ16-AP16 | AS16: =IF(AP16=0,"-",AR16/AP16) | AT16: =IS!M10 | AU16: =AT16*1.0712 | AV16: =AU16-AT16 | AW16: =IF(AT16=0,"-",AV16/AT16) | AY16: =SUM(B16:AT16) | AZ16: =SUM(C16:AU16) | BA16: =AZ16-AY16 | BB16: =IF(AY16=0,"-",BA16/AY16)
A17: Non-Payroll Opex | B17: =IS!B11 | C17: =B17*0.9506 | D17: =C17-B17 | E17: =IF(B17=0,"-",D17/B17) | F17: =IS!C11 | G17: =F17*0.9898 | H17: =G17-F17 | I17: =IF(F17=0,"-",H17/F17) | J17: =IS!D11 | K17: =J17*0.9702 | L17: =K17-J17 | M17: =IF(J17=0,"-",L17/J17) | N17: =IS!E11 | O17: =N17*1.0094 | P17: =O17-N17 | Q17: =IF(N17=0,"-",P17/N17) | R17: =IS!F11 | S17: =R17*0.9996 | T17: =S17-R17 | U17: =IF(R17=0,"-",T17/R17) | V17: =IS!G11 | W17: =V17*0.9604 | X17: =W17-V17 | Y17: =IF(V17=0,"-",X17/V17) | Z17: =IS!H11 | AA17: =Z17*1.0192 | AB17: =AA17-Z17 | AC17: =IF(Z17=0,"-",AB17/Z17) | AD17: =IS!I11 | AE17: =AD17*0.9898 | AF17: =AE17-AD17 | AG17: =IF(AD17=0,"-",AF17/AD17) | AH17: =IS!J11 | AI17: =AH17*0.9702 | AJ17: =AI17-AH17 | AK17: =IF(AH17=0,"-",AJ17/AH17) | AL17: =IS!K11 | AM17: =AL17*1.029 | AN17: =AM17-AL17 | AO17: =IF(AL17=0,"-",AN17/AL17) | AP17: =IS!L11 | AQ17: =AP17*0.9996 | AR17: =AQ17-AP17 | AS17: =IF(AP17=0,"-",AR17/AP17) | AT17: =IS!M11 | AU17: =AT17*1.0094 | AV17: =AU17-AT17 | AW17: =IF(AT17=0,"-",AV17/AT17) | AY17: =SUM(B17:AT17) | AZ17: =SUM(C17:AU17) | BA17: =AZ17-AY17 | BB17: =IF(AY17=0,"-",BA17/AY17)
A18: EBITDA | B18: =IS!B12 | C18: =B18*0.9991 | D18: =C18-B18 | E18: =IF(B18=0,"-",D18/B18) | F18: =IS!C12 | G18: =F18*1.0403 | H18: =G18-F18 | I18: =IF(F18=0,"-",H18/F18) | J18: =IS!D12 | K18: =J18*1.0197 | L18: =K18-J18 | M18: =IF(J18=0,"-",L18/J18) | N18: =IS!E12 | O18: =N18*1.0609 | P18: =O18-N18 | Q18: =IF(N18=0,"-",P18/N18) | R18: =IS!F12 | S18: =R18*1.0506 | T18: =S18-R18 | U18: =IF(R18=0,"-",T18/R18) | V18: =IS!G12 | W18: =V18*1.0094 | X18: =W18-V18 | Y18: =IF(V18=0,"-",X18/V18) | Z18: =IS!H12 | AA18: =Z18*1.0712 | AB18: =AA18-Z18 | AC18: =IF(Z18=0,"-",AB18/Z18) | AD18: =IS!I12 | AE18: =AD18*1.0403 | AF18: =AE18-AD18 | AG18: =IF(AD18=0,"-",AF18/AD18) | AH18: =IS!J12 | AI18: =AH18*1.0197 | AJ18: =AI18-AH18 | AK18: =IF(AH18=0,"-",AJ18/AH18) | AL18: =IS!K12 | AM18: =AL18*1.0815 | AN18: =AM18-AL18 | AO18: =IF(AL18=0,"-",AN18/AL18) | AP18: =IS!L12 | AQ18: =AP18*1.0506 | AR18: =AQ18-AP18 | AS18: =IF(AP18=0,"-",AR18/AP18) | AT18: =IS!M12 | AU18: =AT18*1.0609 | AV18: =AU18-AT18 | AW18: =IF(AT18=0,"-",AV18/AT18) | AY18: =SUM(B18:AT18) | AZ18: =SUM(C18:AU18) | BA18: =AZ18-AY18 | BB18: =IF(AY18=0,"-",BA18/AY18)
A20: BELOW THE LINE
A21: Depreciation | B21: =IS!B13 | C21: =B21*0.97 | D21: =C21-B21 | E21: =IF(B21=0,"-",D21/B21) | F21: =IS!C13 | G21: =F21*1.01 | H21: =G21-F21 | I21: =IF(F21=0,"-",H21/F21) | J21: =IS!D13 | K21: =J21*0.99 | L21: =K21-J21 | M21: =IF(J21=0,"-",L21/J21) | N21: =IS!E13 | O21: =N21*1.03 | P21: =O21-N21 | Q21: =IF(N21=0,"-",P21/N21) | R21: =IS!F13 | S21: =R21*1.02 | T21: =S21-R21 | U21: =IF(R21=0,"-",T21/R21) | V21: =IS!G13 | W21: =V21*0.98 | X21: =W21-V21 | Y21: =IF(V21=0,"-",X21/V21) | Z21: =IS!H13 | AA21: =Z21*1.04 | AB21: =AA21-Z21 | AC21: =IF(Z21=0,"-",AB21/Z21) | AD21: =IS!I13 | AE21: =AD21*1.01 | AF21: =AE21-AD21 | AG21: =IF(AD21=0,"-",AF21/AD21) | AH21: =IS!J13 | AI21: =AH21*0.99 | AJ21: =AI21-AH21 | AK21: =IF(AH21=0,"-",AJ21/AH21) | AL21: =IS!K13 | AM21: =AL21*1.05 | AN21: =AM21-AL21 | AO21: =IF(AL21=0,"-",AN21/AL21) | AP21: =IS!L13 | AQ21: =AP21*1.02 | AR21: =AQ21-AP21 | AS21: =IF(AP21=0,"-",AR21/AP21) | AT21: =IS!M13 | AU21: =AT21*1.03 | AV21: =AU21-AT21 | AW21: =IF(AT21=0,"-",AV21/AT21) | AY21: =SUM(B21:AT21) | AZ21: =SUM(C21:AU21) | BA21: =AZ21-AY21 | BB21: =IF(AY21=0,"-",BA21/AY21)
A22: EBIT | B22: =IS!B14 | C22: =B22*1.0185 | D22: =C22-B22 | E22: =IF(B22=0,"-",D22/B22) | F22: =IS!C14 | G22: =F22*1.0605 | H22: =G22-F22 | I22: =IF(F22=0,"-",H22/F22) | J22: =IS!D14 | K22: =J22*1.0395 | L22: =K22-J22 | M22: =IF(J22=0,"-",L22/J22) | N22: =IS!E14 | O22: =N22*1.0815 | P22: =O22-N22 | Q22: =IF(N22=0,"-",P22/N22) | R22: =IS!F14 | S22: =R22*1.071 | T22: =S22-R22 | U22: =IF(R22=0,"-",T22/R22) | V22: =IS!G14 | W22: =V22*1.029 | X22: =W22-V22 | Y22: =IF(V22=0,"-",X22/V22) | Z22: =IS!H14 | AA22: =Z22*1.092 | AB22: =AA22-Z22 | AC22: =IF(Z22=0,"-",AB22/Z22) | AD22: =IS!I14 | AE22: =AD22*1.0605 | AF22: =AE22-AD22 | AG22: =IF(AD22=0,"-",AF22/AD22) | AH22: =IS!J14 | AI22: =AH22*1.0395 | AJ22: =AI22-AH22 | AK22: =IF(AH22=0,"-",AJ22/AH22) | AL22: =IS!K14 | AM22: =AL22*1.1025 | AN22: =AM22-AL22 | AO22: =IF(AL22=0,"-",AN22/AL22) | AP22: =IS!L14 | AQ22: =AP22*1.071 | AR22: =AQ22-AP22 | AS22: =IF(AP22=0,"-",AR22/AP22) | AT22: =IS!M14 | AU22: =AT22*1.0815 | AV22: =AU22-AT22 | AW22: =IF(AT22=0,"-",AV22/AT22) | AY22: =SUM(B22:AT22) | AZ22: =SUM(C22:AU22) | BA22: =AZ22-AY22 | BB22: =IF(AY22=0,"-",BA22/AY22)
A23: Taxes | B23: =IS!B17 | C23: =B23*0.9215 | D23: =C23-B23 | E23: =IF(B23=0,"-",D23/B23) | F23: =IS!C17 | G23: =F23*0.9595 | H23: =G23-F23 | I23: =IF(F23=0,"-",H23/F23) | J23: =IS!D17 | K23: =J23*0.9405 | L23: =K23-J23 | M23: =IF(J23=0,"-",L23/J23) | N23: =IS!E17 | O23: =N23*0.9785 | P23: =O23-N23 | Q23: =IF(N23=0,"-",P23/N23) | R23: =IS!F17 | S23: =R23*0.969 | T23: =S23-R23 | U23: =IF(R23=0,"-",T23/R23) | V23: =IS!G17 | W23: =V23*0.931 | X23: =W23-V23 | Y23: =IF(V23=0,"-",X23/V23) | Z23: =IS!H17 | AA23: =Z23*0.988 | AB23: =AA23-Z23 | AC23: =IF(Z23=0,"-",AB23/Z23) | AD23: =IS!I17 | AE23: =AD23*0.9595 | AF23: =AE23-AD23 | AG23: =IF(AD23=0,"-",AF23/AD23) | AH23: =IS!J17 | AI23: =AH23*0.9405 | AJ23: =AI23-AH23 | AK23: =IF(AH23=0,"-",AJ23/AH23) | AL23: =IS!K17 | AM23: =AL23*0.9975 | AN23: =AM23-AL23 | AO23: =IF(AL23=0,"-",AN23/AL23) | AP23: =IS!L17 | AQ23: =AP23*0.969 | AR23: =AQ23-AP23 | AS23: =IF(AP23=0,"-",AR23/AP23) | AT23: =IS!M17 | AU23: =AT23*0.9785 | AV23: =AU23-AT23 | AW23: =IF(AT23=0,"-",AV23/AT23) | AY23: =SUM(B23:AT23) | AZ23: =SUM(C23:AU23) | BA23: =AZ23-AY23 | BB23: =IF(AY23=0,"-",BA23/AY23)
A24: Net Income | B24: =IS!B18 | C24: =B24*1.0476 | D24: =C24-B24 | E24: =IF(B24=0,"-",D24/B24) | F24: =IS!C18 | G24: =F24*1.0908 | H24: =G24-F24 | I24: =IF(F24=0,"-",H24/F24) | J24: =IS!D18 | K24: =J24*1.0692 | L24: =K24-J24 | M24: =IF(J24=0,"-",L24/J24) | N24: =IS!E18 | O24: =N24*1.1124 | P24: =O24-N24 | Q24: =IF(N24=0,"-",P24/N24) | R24: =IS!F18 | S24: =R24*1.1016 | T24: =S24-R24 | U24: =IF(R24=0,"-",T24/R24) | V24: =IS!G18 | W24: =V24*1.0584 | X24: =W24-V24 | Y24: =IF(V24=0,"-",X24/V24) | Z24: =IS!H18 | AA24: =Z24*1.1232 | AB24: =AA24-Z24 | AC24: =IF(Z24=0,"-",AB24/Z24) | AD24: =IS!I18 | AE24: =AD24*1.0908 | AF24: =AE24-AD24 | AG24: =IF(AD24=0,"-",AF24/AD24) | AH24: =IS!J18 | AI24: =AH24*1.0692 | AJ24: =AI24-AH24 | AK24: =IF(AH24=0,"-",AJ24/AH24) | AL24: =IS!K18 | AM24: =AL24*1.134 | AN24: =AM24-AL24 | AO24: =IF(AL24=0,"-",AN24/AL24) | AP24: =IS!L18 | AQ24: =AP24*1.1016 | AR24: =AQ24-AP24 | AS24: =IF(AP24=0,"-",AR24/AP24) | AT24: =IS!M18 | AU24: =AT24*1.1124 | AV24: =AU24-AT24 | AW24: =IF(AT24=0,"-",AV24/AT24) | AY24: =SUM(B24:AT24) | AZ24: =SUM(C24:AU24) | BA24: =AZ24-AY24 | BB24: =IF(AY24=0,"-",BA24/AY24)

Sheet DCF_Valuation
A1: DCF Valuation – HubSpot (HUBS) | Illustrative Enterprise Value Analysis
A2: Based on 24-month FP&A model. Terminal value via Gordon Growth Model. USD millions.
A3: Source: HubSpot 10-K 2023 (SEC EDGAR). For illustrative/portfolio purposes only.
A5: SECTION 1 — WACC (Weighted Average Cost of Capital)
A6: Risk-Free Rate (10-yr UST) | B6: 0.044 | C6: US Treasury, Dec 2023
A7: Equity Risk Premium | B7: 0.055 | C7: Damodaran, Jan 2024
A8: Beta (levered, 5-yr monthly vs S&P) | B8: 1.35 | C8: Bloomberg
A9: Cost of Equity [Rf + β × ERP] | B9: =B6+B8*B7 | C9: CAPM formula
A10: Pre-tax Cost of Debt | B10: =Assumptions!$F$30 | C10: Data_Entry rate
A11: Tax Rate | B11: =Assumptions!$F$22 | C11: Data_Entry
A12: After-tax Cost of Debt [Kd×(1-t)] | B12: =B10*(1-B11)
A13: Market Cap (USD mm) | B13: 19500 | C13: Bloomberg, Dec 2023 approx
A14: Total Debt (USD mm) | B14: =Assumptions!$F$11/1000000 | C14: Model opening
A15: Total Capital [E+D] | B15: =B13+B14
A16: Weight of Equity [E/V] | B16: =B13/B15
A17: Weight of Debt [D/V] | B17: =B14/B15
A19: WACC [Ke×E/V + Kd(1-t)×D/V] | B19: =B9*B16+B12*B17 | C19: KEY OUTPUT
A22: SECTION 2 — Free Cash Flow Projection (USD mm)
A23: Metric | B23: FY 2024 (Yr 1) | C23: FY 2025 (Yr 2)
A24: Total Revenue | B24: =SUM(IS!B6:IS6)/1000000 | C24: =SUM(IS!N6:IS6)/1000000
A25: EBITDA | B25: =SUM(IS!B12:IS12)/1000000 | C25: =SUM(IS!N12:IS12)/1000000
A26: EBITDA Margin | B26: =B25/B24 | C26: =C25/C24
A27: Less: Depreciation | B27: =-SUM(Capex!B8:M8)/1000000 | C27: =-SUM(Capex!N8:Y8)/1000000
A28: Less: Cash Taxes | B28: =-SUM(IS!B17:IS17)/1000000 | C28: =-SUM(IS!N17:IS17)/1000000
A29: Less: Capex | B29: =-SUM(Capex!B7:M7)/1000000 | C29: =-SUM(Capex!N7:Y7)/1000000
A30: Less: Δ Working Capital | B30: =-( SUM(Working_Capital!B6:M6) - SUM(Working_Capital!B9:M9) )/1000000 | C30: =-( SUM(Working_Capital!N6:Y6) - SUM(Working_Capital!N9:Y9) )/1000000
A31: Unlevered FCF | B31: =B25+B27+B28+B29+B30 | C31: =C25+C27+C28+C29+C30
A34: Terminal Growth Rate (g) | B34: 0.03 | C34: Conservative — long-run GDP proxy
A35: Terminal Year FCF | B35: =C31 | C35: FY2025 normalised FCF
A36: Terminal Value [FCF×(1+g)/(WACC-g)] | B36: =B35*(1+B34)/(B19-B34) | C36: Gordon Growth
A37: PV of Terminal Value | B37: =B36/(1+B19)^2 | C37: Discounted 2 yrs
A38: PV of FCF Year 1 | B38: =B31/(1+B19)^1
A39: PV of FCF Year 2 | B39: =C31/(1+B19)^2
A40: Sum of PV FCFs | B40: =B38+B39
A42: Enterprise Value (EV) | B42: =B37+B40 | C42: PV TV + PV FCFs
A43: Less: Net Debt (Debt − Cash) | B43: =(Assumptions!$F$11-Assumptions!$F$7)/1000000 | C43: From model
A44: Equity Value | B44: =B42-B43
A45: Shares Outstanding (mm) | B45: 303 | C45: HubSpot 10-K 2023
A46: Implied Share Price | B46: =B44*1000000/B45
A47: Current Market Price (Dec 2023) | B47: 635 | C47: Bloomberg approx
A48: Upside / (Downside) | B48: =(B46-B47)/B47 | C48: vs market
A52: SECTION 4 — Sensitivity: Implied Share Price (WACC vs Terminal Growth Rate)
A53: TGR \ WACC → | B53: 0.08 | C53: 0.09 | D53: 0.1 | E53: 0.11 | F53: 0.12
A54: 0.02 | B54: =(C31*(1+0.02)/(0.08-0.02)/(1+0.08)^2+B31/(1+0.08)+C31/(1+0.08)^2-B43)*1000000/B45 | C54: =(C31*(1+0.02)/(0.09-0.02)/(1+0.09)^2+B31/(1+0.09)+C31/(1+0.09)^2-B43)*1000000/B45 | D54: =(C31*(1+0.02)/(0.1-0.02)/(1+0.1)^2+B31/(1+0.1)+C31/(1+0.1)^2-B43)*1000000/B45 | E54: =(C31*(1+0.02)/(0.11-0.02)/(1+0.11)^2+B31/(1+0.11)+C31/(1+0.11)^2-B43)*1000000/B45 | F54: =(C31*(1+0.02)/(0.12-0.02)/(1+0.12)^2+B31/(1+0.12)+C31/(1+0.12)^2-B43)*1000000/B45
A55: 0.025 | B55: =(C31*(1+0.025)/(0.08-0.025)/(1+0.08)^2+B31/(1+0.08)+C31/(1+0.08)^2-B43)*1000000/B45 | C55: =(C31*(1+0.025)/(0.09-0.025)/(1+0.09)^2+B31/(1+0.09)+C31/(1+0.09)^2-B43)*1000000/B45 | D55: =(C31*(1+0.025)/(0.1-0.025)/(1+0.1)^2+B31/(1+0.1)+C31/(1+0.1)^2-B43)*1000000/B45 | E55: =(C31*(1+0.025)/(0.11-0.025)/(1+0.11)^2+B31/(1+0.11)+C31/(1+0.11)^2-B43)*1000000/B45 | F55: =(C31*(1+0.025)/(0.12-0.025)/(1+0.12)^2+B31/(1+0.12)+C31/(1+0.12)^2-B43)*1000000/B45
A56: 0.03 | B56: =(C31*(1+0.03)/(0.08-0.03)/(1+0.08)^2+B31/(1+0.08)+C31/(1+0.08)^2-B43)*1000000/B45 | C56: =(C31*(1+0.03)/(0.09-0.03)/(1+0.09)^2+B31/(1+0.09)+C31/(1+0.09)^2-B43)*1000000/B45 | D56: =(C31*(1+0.03)/(0.1-0.03)/(1+0.1)^2+B31/(1+0.1)+C31/(1+0.1)^2-B43)*1000000/B45 | E56: =(C31*(1+0.03)/(0.11-0.03)/(1+0.11)^2+B31/(1+0.11)+C31/(1+0.11)^2-B43)*1000000/B45 | F56: =(C31*(1+0.03)/(0.12-0.03)/(1+0.12)^2+B31/(1+0.12)+C31/(1+0.12)^2-B43)*1000000/B45
A57: 0.035 | B57: =(C31*(1+0.035)/(0.08-0.035)/(1+0.08)^2+B31/(1+0.08)+C31/(1+0.08)^2-B43)*1000000/B45 | C57: =(C31*(1+0.035)/(0.09-0.035)/(1+0.09)^2+B31/(1+0.09)+C31/(1+0.09)^2-B43)*1000000/B45 | D57: =(C31*(1+0.035)/(0.1-0.035)/(1+0.1)^2+B31/(1+0.1)+C31/(1+0.1)^2-B43)*1000000/B45 | E57: =(C31*(1+0.035)/(0.11-0.035)/(1+0.11)^2+B31/(1+0.11)+C31/(1+0.11)^2-B43)*1000000/B45 | F57: =(C31*(1+0.035)/(0.12-0.035)/(1+0.12)^2+B31/(1+0.12)+C31/(1+0.12)^2-B43)*1000000/B45
A58: 0.04 | B58: =(C31*(1+0.04)/(0.08-0.04)/(1+0.08)^2+B31/(1+0.08)+C31/(1+0.08)^2-B43)*1000000/B45 | C58: =(C31*(1+0.04)/(0.09-0.04)/(1+0.09)^2+B31/(1+0.09)+C31/(1+0.09)^2-B43)*1000000/B45 | D58: =(C31*(1+0.04)/(0.1-0.04)/(1+0.1)^2+B31/(1+0.1)+C31/(1+0.1)^2-B43)*1000000/B45 | E58: =(C31*(1+0.04)/(0.11-0.04)/(1+0.11)^2+B31/(1+0.11)+C31/(1+0.11)^2-B43)*1000000/B45 | F58: =(C31*(1+0.04)/(0.12-0.04)/(1+0.12)^2+B31/(1+0.12)+C31/(1+0.12)^2-B43)*1000000/B45
A60: Orange = base case (WACC 10.0%, TGR 3.0%). Each cell shows implied share price under that combination.

Sheet CF
A1: Cash Flow Statement
A2: Indirect method with debt flows and capex.
A3: Monthly Cash Flow
B4: =Assumptions!$F$6 | C4: =DATE(YEAR(B4),MONTH(B4)+1,1) | D4: =DATE(YEAR(C4),MONTH(C4)+1,1) | E4: =DATE(YEAR(D4),MONTH(D4)+1,1) | F4: =DATE(YEAR(E4),MONTH(E4)+1,1) | G4: =DATE(YEAR(F4),MONTH(F4)+1,1) | H4: =DATE(YEAR(G4),MONTH(G4)+1,1) | I4: =DATE(YEAR(H4),MONTH(H4)+1,1) | J4: =DATE(YEAR(I4),MONTH(I4)+1,1) | ... Y4: =DATE(YEAR(X4),MONTH(X4)+1,1)
A6: Opening Cash | B6: =Assumptions!$F$7 | C6: =B21 | D6: =C21 | E6: =D21 | F6: =E21 | G6: =F21 | H6: =G21 | I6: =H21 | J6: =I21 | ... Y6: =X21
A7: Net Income | B7: =IS!B18 | C7: =IS!C18 | D7: =IS!D18 | E7: =IS!E18 | F7: =IS!F18 | G7: =IS!G18 | H7: =IS!H18 | I7: =IS!I18 | ... Y7: =IS!Y18
A8: Depreciation | B8: =Capex!B8 | C8: =Capex!C8 | D8: =Capex!D8 | E8: =Capex!E8 | F8: =Capex!F8 | G8: =Capex!G8 | H8: =Capex!H8 | I8: =Capex!I8 | ... Y8: =Capex!Y8
A9: Change in AR | B9: =-Working_Capital!B9 | C9: =-Working_Capital!C9 | D9: =-Working_Capital!D9 | E9: =-Working_Capital!E9 | F9: =-Working_Capital!F9 | G9: =-Working_Capital!G9 | H9: =-Working_Capital!H9 | I9: =-Working_Capital!I9 | ... Y9: =-Working_Capital!Y9
A10: Change in AP | B10: =Working_Capital!B10 | C10: =Working_Capital!C10 | D10: =Working_Capital!D10 | E10: =Working_Capital!E10 | F10: =Working_Capital!F10 | G10: =Working_Capital!G10 | H10: =Working_Capital!H10 | I10: =Working_Capital!I10 | ... Y10: =Working_Capital!Y10
A11: Operating Cash Flow | B11: =SUM(B7:B10) | C11: =SUM(C7:C10) | D11: =SUM(D7:D10) | E11: =SUM(E7:E10) | F11: =SUM(F7:F10) | G11: =SUM(G7:G10) | H11: =SUM(H7:H10) | I11: =SUM(I7:I10) | ... Y11: =SUM(Y7:Y10)
A13: Investing Cash Flow
A14: Investing Cash Flow subtotal | B14: =B15 | C14: =C15 | D14: =D15 | E14: =E15 | F14: =F15 | G14: =G15 | H14: =H15 | I14: =I15 | ... Y14: =Y15
A15: Capex | B15: =-Capex!B7 | C15: =-Capex!C7 | D15: =-Capex!D7 | E15: =-Capex!E7 | F15: =-Capex!F7 | G15: =-Capex!G7 | H15: =-Capex!H7 | I15: =-Capex!I7 | ... Y15: =-Capex!Y7
A16: Debt Draws | B16: =Debt!B7 | C16: =Debt!C7 | D16: =Debt!D7 | E16: =Debt!E7 | F16: =Debt!F7 | G16: =Debt!G7 | H16: =Debt!H7 | I16: =Debt!I7 | ... Y16: =Debt!Y7
A17: Debt Repayments | B17: =-Debt!B8 | C17: =-Debt!C8 | D17: =-Debt!D8 | E17: =-Debt!E8 | F17: =-Debt!F8 | G17: =-Debt!G8 | H17: =-Debt!H8 | I17: =-Debt!I8 | ... Y17: =-Debt!Y8
A18: Financing Cash Flow | B18: =SUM(B16:B17) | C18: =SUM(C16:C17) | D18: =SUM(D16:D17) | E18: =SUM(E16:E17) | F18: =SUM(F16:F17) | G18: =SUM(G16:G17) | H18: =SUM(H16:H17) | I18: =SUM(I16:I17) | ... Y18: =SUM(Y16:Y17)
A20: Net Change in Cash | B20: =B11+B14+B18 | C20: =C11+C14+C18 | D20: =D11+D14+D18 | E20: =E11+E14+E18 | F20: =F11+F14+F18 | G20: =G11+G14+G18 | H20: =H11+H14+H18 | I20: =I11+I14+I18 | ... Y20: =Y11+Y14+Y18
A21: Ending Cash | B21: =B6+B20 | C21: =C6+C20 | D21: =D6+D20 | E21: =E6+E20 | F21: =F6+F20 | G21: =G6+G20 | H21: =H6+H20 | I21: =I6+I20 | ... Y21: =Y6+Y20

Sheet Dashboard
A1: Dashboard
A2: Snapshot of key KPIs for the selected scenario.
A3: Monthly KPI Trend
B4: =Assumptions!$F$6 | C4: =DATE(YEAR(B4),MONTH(B4)+1,1) | D4: =DATE(YEAR(C4),MONTH(C4)+1,1) | E4: =DATE(YEAR(D4),MONTH(D4)+1,1) | F4: =DATE(YEAR(E4),MONTH(E4)+1,1) | G4: =DATE(YEAR(F4),MONTH(F4)+1,1) | H4: =DATE(YEAR(G4),MONTH(G4)+1,1) | I4: =DATE(YEAR(H4),MONTH(H4)+1,1) | J4: =DATE(YEAR(I4),MONTH(I4)+1,1) | ... Y4: =DATE(YEAR(X4),MONTH(X4)+1,1)
A6: Revenue | B6: =Revenue!B15 | C6: =Revenue!C15 | D6: =Revenue!D15 | E6: =Revenue!E15 | F6: =Revenue!F15 | G6: =Revenue!G15 | H6: =Revenue!H15 | I6: =Revenue!I15 | ... Y6: =Revenue!Y15
A7: EBITDA | B7: =IS!B12 | C7: =IS!C12 | D7: =IS!D12 | E7: =IS!E12 | F7: =IS!F12 | G7: =IS!G12 | H7: =IS!H12 | I7: =IS!I12 | ... Y7: =IS!Y12
A8: Ending Cash | B8: =CF!B21 | C8: =CF!C21 | D8: =CF!D21 | E8: =CF!E21 | F8: =CF!F21 | G8: =CF!G21 | H8: =CF!H21 | I8: =CF!I21 | ... Y8: =CF!Y21
A9: Ending Customers | B9: =Revenue!B10 | C9: =Revenue!C10 | D9: =Revenue!D10 | E9: =Revenue!E10 | F9: =Revenue!F10 | G9: =Revenue!G10 | H9: =Revenue!H10 | I9: =Revenue!I10 | ... Y9: =Revenue!Y10
A10: Ending HC | B10: =Headcount!B52 | C10: =Headcount!C52 | D10: =Headcount!D52 | E10: =Headcount!E52 | F10: =Headcount!F52 | G10: =Headcount!G52 | H10: =Headcount!H52 | I10: =Headcount!I52 | ... Y10: =Headcount!Y52
A12: Annual Summary
B13: Metric | C13: =YEAR(B4) | D13: =YEAR(N4)
B14: Revenue | C14: =SUM(B6:M6) | D14: =SUM(N6:Y6)
B15: EBITDA | C15: =SUM(B7:M7) | D15: =SUM(N7:Y7)
B16: EBITDA Margin | C16: =C15/C14 | D16: =D15/D14
B17: Ending Cash | C17: =M8 | D17: =Y8
B18: Ending Customers | C18: =M9 | D18: =Y9
B19: Ending HC | C19: =M10 | D19: =Y10

Sheet Scenario_Analysis
A1: HubSpot (HUBS) — Scenario Analysis | Base / Upside / Downside | Illustrative
A2: Scenarios driven by Assumptions sheet (rows 13–40). Change assumptions there to update all linked schedules.
A4: SECTION 1 — KEY ASSUMPTION COMPARISON
A5: Assumption | B5: Unit | C5: Base Case | D5: Upside Case | E5: Downside Case | F5: Base vs Upside | G5: Base vs Downside
A6: Monthly New Customers | C6: 3800 | D6: 4200 | E6: 3200 | F6: 0.10526316 | G6: -0.15789474
A7: Monthly Churn % | B7: % | C7: 0.015 | D7: 0.012 | E7: 0.02 | F7: -0.2 | G7: 0.33333333
A8: Starting ARPU | B8: USD | C8: 947 | D8: 960 | E8: 920 | F8: 0.013727561 | G8: -0.028511088
A9: Annual Price Uplift % | B9: % | C9: 0.02 | D9: 0.04 | E9: 0 | F9: 1 | G9: -1
A10: Implementation Fee / Cust | B10: USD | C10: 3000 | D10: 3500 | E10: 2500 | F10: 0.16666667 | G10: -0.16666667
A11: COGS % Revenue | B11: % | C11: 0.139 | D11: 0.13 | E11: 0.155 | F11: -0.064748201 | G11: 0.11510791
A12: Capex % Revenue | B12: % | C12: 0.042 | D12: 0.038 | E12: 0.048 | F12: -0.095238095 | G12: 0.14285714
A13: Marketing Programs % Rev | B13: % | C13: 0.09 | D13: 0.1 | E13: 0.08 | F13: 0.11111111 | G13: -0.11111111
A14: Travel % Revenue | B14: % | C14: 0.01 | D14: 0.012 | E14: 0.008 | F14: 0.2 | G14: -0.2
A16: SECTION 2 — FINANCIAL OUTPUT SUMMARY BY SCENARIO
A17: Metric | B17: Unit | C17: Base Case | D17: Upside Case | E17: Downside Case | F17: Up vs Base Δ | G17: Dn vs Base Δ
A18: FY2024 Revenue | B18: $M | C18: 2540.1742 | D18: 2710.5606 | E18: 2300.0068 | F18: 0.067076648 | G18: -0.094547609
A19: FY2025 Revenue | B19: $M | C19: 2673.6384 | D19: 3034.5357 | E19: 2205.7974 | F19: 0.13498357 | G19: -0.17498291
A20: FY2025 YoY Growth | B20: % | C20: 0.052541357 | D20: 0.11952328 | E20: -0.040960499 | F20: 1.2748418 | G20: -1.7795859
A21: FY2024 ARR | B21: $M | C21: 2466.3549 | D21: 2684.2701 | E21: 2157.0356 | F21: 0.088355199 | G21: -0.12541554
A22: FY2025 ARR | B22: $M | C22: 2594.9484 | D22: 3003.9001 | E22: 2072.9383 | F22: 0.15759529 | G22: -0.20116396
A23: FY2024 Gross Margin | B23: % | C23: 0.861 | D23: 0.87 | E23: 0.845 | F23: 0.010452962 | G23: -0.018583043
A24: FY2025 Gross Margin | B24: % | C24: 0.861 | D24: 0.87 | E24: 0.845 | F24: 0.010452962 | G24: -0.018583043
A25: FY2024 EBITDA | B25: $M | C25: 1568.6659 | D25: 1699.3054 | E25: 1368.3855 | F25: 0.083280628 | G25: -0.12767565
A26: FY2025 EBITDA | B26: $M | C26: 1595.4956 | D26: 1864.0843 | E26: 1232.6483 | F26: 0.16834188 | G26: -0.22741979
A27: FY2024 EBITDA Margin | B27: % | C27: 0.61754265 | D27: 0.62692028 | E27: 0.59494844 | F27: 0.015185395 | G27: -0.036587281
A28: FY2025 EBITDA Margin | B28: % | C28: 0.59675069 | D28: 0.6142898 | E28: 0.55882209 | F28: 0.029391012 | G28: -0.063558537
A29: FY2024 End Customers | C29: 213092.86 | D29: 224634.31 | E29: 195383.66 | F29: 0.054161596 | G29: -0.083105548
A30: FY2025 End Customers | C30: 219767.47 | D30: 241541.89 | E30: 187766.15 | F30: 0.099079367 | G30: -0.14561444
A32: COLOUR LEGEND
A33: Blue text | B33: Hardcoded input assumption (change in Assumptions sheet)
A34: Green | B34: Favourable vs Base / Upside scenario
A35: Red | B35: Unfavourable vs Base / Downside scenario
A36: Navy | B36: Base Case

Sheet BS
A1: Balance Sheet
A2: Integrated monthly balance sheet with balance check.
A3: Monthly Balance Sheet
B4: =Assumptions!$F$6 | C4: =DATE(YEAR(B4),MONTH(B4)+1,1) | D4: =DATE(YEAR(C4),MONTH(C4)+1,1) | E4: =DATE(YEAR(D4),MONTH(D4)+1,1) | F4: =DATE(YEAR(E4),MONTH(E4)+1,1) | G4: =DATE(YEAR(F4),MONTH(F4)+1,1) | H4: =DATE(YEAR(G4),MONTH(G4)+1,1) | I4: =DATE(YEAR(H4),MONTH(H4)+1,1) | J4: =DATE(YEAR(I4),MONTH(I4)+1,1) | ... Y4: =DATE(YEAR(X4),MONTH(X4)+1,1)
A6: Cash | B6: =CF!B21 | C6: =CF!C21 | D6: =CF!D21 | E6: =CF!E21 | F6: =CF!F21 | G6: =CF!G21 | H6: =CF!H21 | I6: =CF!I21 | ... Y6: =CF!Y21
A7: Accounts Receivable | B7: =Working_Capital!B6 | C7: =Working_Capital!C6 | D7: =Working_Capital!D6 | E7: =Working_Capital!E6 | F7: =Working_Capital!F6 | G7: =Working_Capital!G6 | H7: =Working_Capital!H6 | I7: =Working_Capital!I6 | ... Y7: =Working_Capital!Y6
A8: Net PP&E | B8: =Capex!B9 | C8: =Capex!C9 | D8: =Capex!D9 | E8: =Capex!E9 | F8: =Capex!F9 | G8: =Capex!G9 | H8: =Capex!H9 | I8: =Capex!I9 | ... Y8: =Capex!Y9
A9: Total Assets | B9: =SUM(B6:B8) | C9: =SUM(C6:C8) | D9: =SUM(D6:D8) | E9: =SUM(E6:E8) | F9: =SUM(F6:F8) | G9: =SUM(G6:G8) | H9: =SUM(H6:H8) | I9: =SUM(I6:I8) | ... Y9: =SUM(Y6:Y8)
A11: Accounts Payable | B11: =Working_Capital!B8 | C11: =Working_Capital!C8 | D11: =Working_Capital!D8 | E11: =Working_Capital!E8 | F11: =Working_Capital!F8 | G11: =Working_Capital!G8 | H11: =Working_Capital!H8 | I11: =Working_Capital!I8 | ... Y11: =Working_Capital!Y8
A12: Debt | B12: =Debt!B9 | C12: =Debt!C9 | D12: =Debt!D9 | E12: =Debt!E9 | F12: =Debt!F9 | G12: =Debt!G9 | H12: =Debt!H9 | I12: =Debt!I9 | ... Y12: =Debt!Y9
A13: Total Liabilities | B13: =SUM(B11:B12) | C13: =SUM(C11:C12) | D13: =SUM(D11:D12) | E13: =SUM(E11:E12) | F13: =SUM(F11:F12) | G13: =SUM(G11:G12) | H13: =SUM(H11:H12) | I13: =SUM(I11:I12) | ... Y13: =SUM(Y11:Y12)
A15: Share Capital | B15: =Assumptions!$F$12 | C15: =Assumptions!$F$12 | D15: =Assumptions!$F$12 | E15: =Assumptions!$F$12 | F15: =Assumptions!$F$12 | G15: =Assumptions!$F$12 | H15: =Assumptions!$F$12 | I15: =Assumptions!$F$12 | ... Y15: =Assumptions!$F$12
A16: Retained Earnings | B16: =Assumptions!$F$13+IS!B18 | C16: =B16+IS!C18 | D16: =C16+IS!D18 | E16: =D16+IS!E18 | F16: =E16+IS!F18 | G16: =F16+IS!G18 | H16: =G16+IS!H18 | I16: =H16+IS!I18 | J16: =I16+IS!J18 | ... Y16: =X16+IS!Y18
A17: Total Equity | B17: =B15+B16 | C17: =C15+C16 | D17: =D15+D16 | E17: =E15+E16 | F17: =F15+F16 | G17: =G15+G16 | H17: =H15+H16 | I17: =I15+I16 | ... Y17: =Y15+Y16
A18: Total Liabilities + Equity | B18: =B13+B17 | C18: =C13+C17 | D18: =D13+D17 | E18: =E13+E17 | F18: =F13+F17 | G18: =G13+G17 | H18: =H13+H17 | I18: =I13+I17 | ... Y18: =Y13+Y17
A19: Balance Check | B19: =B9-B18 | C19: =C9-C18 | D19: =D9-D18 | E19: =E9-E18 | F19: =F9-F18 | G19: =G9-G18 | H19: =H9-H18 | I19: =I9-I18 | ... Y19: =Y9-Y18

Sheet Rolling_Forecast
A1: HubSpot (HUBS) — Rolling Forecast | FY2024–FY2025 | Lock Date: Jun-24 | Amounts in $M USD
A2: Rolling Forecast: each month, Actuals replace prior forecasts and the horizon extends 18 months forward. Blue = Actuals (locked) | Green = Original Forecast (IS Base) | Amber = Revised Forecast (mid-year reforecast) | ± = Variance
A3: Metric | B3: Unit | C3: Jan-24 | F3: Feb-24 | I3: Mar-24 | L3: Apr-24 | O3: May-24 | R3: Jun-24 | U3: Jul-24 | X3: Aug-24 | AA3: Sep-24 | AD3: Oct-24 | AG3: Nov-24 | AJ3: Dec-24 | AM3: Jan-25 | AP3: Feb-25 | AS3: Mar-25 | AV3: Apr-25 | AY3: May-25 | BB3: Jun-25 | BE3: Jul-25 | BH3: Aug-25 | BK3: Sep-25 | BN3: Oct-25 | BQ3: Nov-25 | BT3: Dec-25
C4: Actual | D4: — | E4: — | F4: Actual | G4: — | H4: — | I4: Actual | J4: — | K4: — | L4: Actual | M4: — | N4: — | O4: Actual | P4: — | Q4: — | R4: Actual | S4: — | T4: — | U4: Orig FC | V4: Rev FC | W4: Δ | X4: Orig FC | Y4: Rev FC | Z4: Δ | AA4: Orig FC | AB4: Rev FC | AC4: Δ | AD4: Orig FC | AE4: Rev FC | AF4: Δ | AG4: Orig FC | AH4: Rev FC | AI4: Δ | AJ4: Orig FC | AK4: Rev FC | AL4: Δ | AM4: Orig FC | AN4: Rev FC | AO4: Δ | AP4: Orig FC | AQ4: Rev FC | AR4: Δ | AS4: Orig FC | AT4: Rev FC | AU4: Δ | AV4: Orig FC | AW4: Rev FC | AX4: Δ | AY4: Orig FC | AZ4: Rev FC | BA4: Δ | BB4: Orig FC | BC4: Rev FC | BD4: Δ | BE4: Orig FC | BF4: Rev FC | BG4: Δ | BH4: Orig FC | BI4: Rev FC | BJ4: Δ | BK4: Orig FC | BL4: Rev FC | BM4: Δ | BN4: Orig FC | BO4: Rev FC | BP4: Δ | BQ4: Orig FC | BR4: Rev FC | BS4: Δ | BT4: Orig FC | BU4: Rev FC | BV4: Δ
A5: REVENUE & GROSS PROFIT
A6: Total Revenue | B6: $M | C6: 0 | F6: 0 | I6: 0 | L6: 0 | O6: 0 | R6: 0 | U6: 211.8909 | V6: 216.12872 | W6: 4.2378181 | X6: 212.85351 | Y6: 217.11058 | Z6: 4.2570703 | AA6: 213.80933 | AB6: 218.08552 | AC6: 4.2761867 | AD6: 214.75846 | AE6: 219.05363 | AF6: 4.2951692 | AG6: 215.701 | AH6: 220.01502 | AI6: 4.31402 | AJ6: 216.63705 | AK6: 220.96979 | AL6: 4.3327409 | AM6: 217.5667 | AN6: 219.74236 | AO6: 2.175667 | AP6: 218.49005 | AQ6: 220.67495 | AR6: 2.1849005 | AS6: 219.40719 | AT6: 221.60127 | AU6: 2.1940719 | AV6: 220.31823 | AW6: 222.52141 | AX6: 2.2031823 | AY6: 221.22324 | AZ6: 223.43547 | BA6: 2.2122324 | BB6: 222.12232 | BC6: 224.34354 | BD6: 2.2212232 | BE6: 223.01556 | BF6: 225.24572 | BG6: 2.2301556 | BH6: 223.90305 | BI6: 226.14208 | BJ6: 2.2390305 | BK6: 224.78488 | BL6: 227.03273 | BM6: 2.2478488 | BN6: 225.66112 | BO6: 227.91774 | BP6: 2.2566112 | BQ6: 226.53188 | BR6: 228.7972 | BS6: 2.2653188 | BT6: 227.39722 | BU6: 229.67119 | BV6: 2.2739722
A7: YoY MoM Growth | B7: % | C7: 0 | F7: 0.0048820938 | I7: 0.0048225014 | L7: 0.0047641803 | O7: 0.0047070968 | R7: 0.0046512182 | U7: 0.004596513 | V7: 0.024688443 | X7: 0.0045429506 | Y7: 0.0045429506 | AA7: 0.0044905016 | AB7: 0.0044905016 | AD7: 0.0044391373 | AE7: 0.0044391373 | AG7: 0.0043888303 | AH7: 0.0043888303 | AJ7: 0.0043395537 | AK7: 0.0043395537 | AM7: 0.0042912818 | AN7: -0.0055547112 | AP7: 0.0042439894 | AQ7: 0.0042439894 | AS7: 0.0041976523 | AT7: 0.0041976523 | AV7: 0.004152247 | AW7: 0.004152247 | AY7: 0.0041077507 | AZ7: 0.0041077507 | BB7: 0.0040641413 | BC7: 0.0040641413 | BE7: 0.0040213975 | BF7: 0.0040213975 | BH7: 0.0039794985 | BI7: 0.0039794985 | BK7: 0.0039384241 | BL7: 0.0039384241 | BN7: 0.0038981548 | BO7: 0.0038981548 | BQ7: 0.0038586716 | BR7: 0.0038586716 | BT7: 0.0038199562 | BU7: 0.0038199562
A8: COGS | B8: $M | C8: 28.629388 | F8: 28.769159 | I8: 28.907898 | L8: 29.045621 | O8: 29.182341 | R8: 29.318075 | U8: 29.452836 | V8: 28.863779 | W8: -0.58905671 | X8: 29.586639 | Y8: 28.994906 | Z8: -0.59173277 | AA8: 29.719497 | AB8: 29.125107 | AC8: -0.59438995 | AD8: 29.851426 | AE8: 29.254398 | AF8: -0.59702853 | AG8: 29.982439 | AH8: 29.38279 | AI8: -0.59964878 | AJ8: 30.11255 | AK8: 29.510299 | AL8: -0.60225099 | AM8: 30.241771 | AN8: 29.636936 | AO8: -0.60483542 | AP8: 30.370117 | AQ8: 29.762714 | AR8: -0.60740233 | AS8: 30.4976 | AT8: 29.887648 | AU8: -0.609952 | AV8: 30.624233 | AW8: 30.011749 | AX8: -0.61248467 | AY8: 30.75003 | AZ8: 30.13503 | BA8: -0.6150006 | BB8: 30.875003 | BC8: 30.257503 | BD8: -0.61750005 | BE8: 30.999163 | BF8: 30.37918 | BG8: -0.61998327 | BH8: 31.122524 | BI8: 30.500074 | BJ8: -0.62245049 | BK8: 31.245098 | BL8: 30.620196 | BM8: -0.62490196 | BN8: 31.366896 | BO8: 30.739558 | BP8: -0.62733793 | BQ8: 31.487931 | BR8: 30.858172 | BS8: -0.62975862 | BT8: 31.608213 | BU8: 30.976049 | BV8: -0.63216427
A9: Gross Profit | B9: $M | C9: 0 | F9: 0 | I9: 0 | L9: 0 | O9: 0 | R9: 0 | U9: 182.43807 | V9: 182.43807 | W9: 0 | X9: 183.26688 | Y9: 183.26688 | Z9: 0 | AA9: 184.08984 | AB9: 184.08984 | AC9: 0 | AD9: 184.90704 | AE9: 184.90704 | AF9: 0 | AG9: 185.71856 | AH9: 185.71856 | AI9: 0 | AJ9: 186.5245 | AK9: 186.5245 | AL9: 0 | AM9: 187.32493 | AN9: 187.32493 | AO9: 0 | AP9: 188.11993 | AQ9: 188.11993 | AR9: 0 | AS9: 188.90959 | AT9: 188.90959 | AU9: 0 | AV9: 189.69399 | AW9: 189.69399 | AX9: 0 | AY9: 190.47321 | AZ9: 190.47321 | BA9: 0 | BB9: 191.24732 | BC9: 191.24732 | BD9: 0 | BE9: 192.0164 | BF9: 192.0164 | BG9: 0 | BH9: 192.78053 | BI9: 192.78053 | BJ9: 0 | BK9: 193.53978 | BL9: 193.53978 | BM9: 0 | BN9: 194.29423 | BO9: 194.29423 | BP9: 0 | BQ9: 195.04395 | BR9: 195.04395 | BS9: 0 | BT9: 195.78901 | BU9: 195.78901 | BV9: 0
A10: Gross Margin % | B10: % | C10: 0.861 | F10: 0.861 | I10: 0.861 | L10: 0.861 | O10: 0.861 | R10: 0.861 | U10: 0.861 | V10: 0.83567647 | X10: 0.861 | Y10: 0.83567647 | AA10: 0.861 | AB10: 0.83567647 | AD10: 0.861 | AE10: 0.83567647 | AG10: 0.861 | AH10: 0.83567647 | AJ10: 0.861 | AK10: 0.83567647 | AM10: 0.861 | AN10: 0.8439505 | AP10: 0.861 | AQ10: 0.8439505 | AS10: 0.861 | AT10: 0.8439505 | AV10: 0.861 | AW10: 0.8439505 | AY10: 0.861 | AZ10: 0.8439505 | BB10: 0.861 | BC10: 0.8439505 | BE10: 0.861 | BF10: 0.8439505 | BH10: 0.861 | BI10: 0.8439505 | BK10: 0.861 | BL10: 0.8439505 | BN10: 0.861 | BO10: 0.8439505 | BQ10: 0.861 | BR10: 0.8439505 | BT10: 0.861 | BU10: 0.8439505
A11: OPERATING EXPENSES
A12: Payroll Expense | B12: $M | C12: -128.103 | F12: -407.7675 | I12: -408.031 | L12: -408.301 | O12: -408.582 | R12: -408.85275 | U12: -409.12075 | V12: -396.84713 | W12: 12.273622 | X12: -409.399 | Y12: -397.11703 | Z12: 12.28197 | AA12: -409.6845 | AB12: -397.39396 | AC12: 12.290535 | AD12: -409.95425 | AE12: -397.65562 | AF12: 12.298628 | AG12: -410.22225 | AH12: -397.91558 | AI12: 12.306667 | AJ12: -410.5015 | AK12: -398.18646 | AL12: 12.315045 | AM12: -410.7825 | AN12: -398.45902 | AO12: 12.323475 | AP12: -411.05775 | AQ12: -398.72602 | AR12: 12.331732 | AS12: -411.31675 | AT12: -398.97725 | AU12: 12.339503 | AV12: -411.586 | AW12: -399.23842 | AX12: 12.34758 | AY12: -411.867 | AZ12: -399.51099 | BA12: 12.35601 | BB12: -412.1415 | BC12: -399.77726 | BD12: 12.364245 | BE12: -412.4095 | BF12: -400.03722 | BG12: 12.372285 | BH12: -412.684 | BI12: -400.30348 | BJ12: 12.38052 | BK12: -412.9695 | BL12: -400.58042 | BM12: 12.389085 | BN12: -413.2355 | BO12: -400.83844 | BP12: 12.397065 | BQ12: -413.5035 | BR12: -401.09839 | BS12: 12.405105 | BT12: -413.7865 | BU12: -401.37291 | BV12: 12.413595
A13: Non-Payroll Opex | B13: $M | C13: 28.596682 | F13: 28.697237 | I13: 28.797049 | L13: 28.89613 | O13: 28.99449 | R13: 29.09214 | U13: 29.18909 | V13: 29.18909 | W13: 0 | X13: 29.285351 | Y13: 29.285351 | Z13: 0 | AA13: 29.380933 | AB13: 29.380933 | AC13: 0 | AD13: 29.475846 | AE13: 29.475846 | AF13: 0 | AG13: 29.5701 | AH13: 29.5701 | AI13: 0 | AJ13: 29.663705 | AK13: 29.663705 | AL13: 0 | AM13: 29.75667 | AN13: 29.75667 | AO13: 0 | AP13: 29.849005 | AQ13: 29.849005 | AR13: 0 | AS13: 29.940719 | AT13: 29.940719 | AU13: 0 | AV13: 30.031823 | AW13: 30.031823 | AX13: 0 | AY13: 30.122324 | AZ13: 30.122324 | BA13: 0 | BB13: 30.212232 | BC13: 30.212232 | BD13: 0 | BE13: 30.301556 | BF13: 30.301556 | BG13: 0 | BH13: 30.390305 | BI13: 30.390305 | BJ13: 0 | BK13: 30.478488 | BL13: 30.478488 | BM13: 0 | BN13: 30.566112 | BO13: 30.566112 | BP13: 0 | BQ13: 30.653188 | BR13: 30.653188 | BS13: 0 | BT13: 30.739722 | BU13: 30.739722 | BV13: 0
A14: EBITDA | B14: $M | C14: 0 | F14: 0 | I14: 0 | L14: 0 | O14: 0 | R14: 0 | U14: 409.85854 | V14: 409.85854 | W14: 0 | X14: 410.13155 | Y14: 410.13155 | Z14: 0 | AA14: 410.41188 | AB14: 410.41188 | AC14: 0 | AD14: 410.67654 | AE14: 410.67654 | AF14: 0 | AG14: 410.93952 | AH14: 410.93952 | AI14: 0 | AJ14: 411.21383 | AK14: 411.21383 | AL14: 0 | AM14: 411.48996 | AN14: 411.48996 | AO14: 0 | AP14: 411.76042 | AQ14: 411.76042 | AR14: 0 | AS14: 412.0147 | AT14: 412.0147 | AU14: 0 | AV14: 412.2793 | AW14: 412.2793 | AX14: 0 | AY14: 412.55571 | AZ14: 412.55571 | BA14: 0 | BB14: 412.8257 | BC14: 412.8257 | BD14: 0 | BE14: 413.08926 | BF14: 413.08926 | BG14: 0 | BH14: 413.35938 | BI14: 413.35938 | BJ14: 0 | BK14: 413.64057 | BL14: 413.64057 | BM14: 0 | BN14: 413.90232 | BO14: 413.90232 | BP14: 0 | BQ14: 414.16614 | BR14: 414.16614 | BS14: 0 | BT14: 414.44503 | BU14: 414.44503 | BV14: 0
A15: EBITDA Margin % | B15: % | C15: 1.3441182 | F15: 1.9738515 | I15: 1.9656181 | L15: 1.9575635 | O15: 1.9497045 | R15: 1.941936 | U15: 1.9342904 | V15: 1.9536333 | X15: 1.9268253 | Y15: 1.9460936 | AA15: 1.9195227 | AB15: 1.938718 | AD15: 1.9122717 | AE15: 1.9313945 | AG15: 1.905135 | AH15: 1.9241863 | AJ15: 1.8981695 | AK15: 1.9171512 | AM15: 1.8913279 | AN15: 1.9102412 | AP15: 1.8845729 | AQ15: 1.9034186 | AS15: 1.8778541 | AT15: 1.8966326 | AV15: 1.87129 | AW15: 1.8900029 | AY15: 1.8648842 | AZ15: 1.883533 | BB15: 1.8585512 | BC15: 1.8771367 | BE15: 1.8522889 | BF15: 1.8708118 | BH15: 1.8461534 | BI15: 1.8646149 | BK15: 1.8401619 | BL15: 1.8585635 | BN15: 1.8341765 | BO15: 1.8525182 | BQ15: 1.8282908 | BR15: 1.8465737 | BT15: 1.8225598 | BU15: 1.8407854
A16: NET INCOME
A17: Net Income | B17: $M | C17: 0 | F17: 0 | I17: 0 | L17: 0 | O17: 0 | R17: 0 | U17: 323.59296 | V17: 323.59296 | W17: 0 | X17: 323.80774 | Y17: 323.80774 | Z17: 0 | AA17: 324.02832 | AB17: 324.02832 | AC17: 0 | AD17: 324.23653 | AE17: 324.23653 | AF17: 0 | AG17: 324.44342 | AH17: 324.44342 | AI17: 0 | AJ17: 324.65926 | AK17: 324.65926 | AL17: 0 | AM17: 324.87655 | AN17: 324.87655 | AO17: 0 | AP17: 325.08936 | AQ17: 325.08936 | AR17: 0 | AS17: 325.28939 | AT17: 325.28939 | AU17: 0 | AV17: 325.49758 | AW17: 325.49758 | AX17: 0 | AY17: 325.71512 | AZ17: 325.71512 | BA17: 0 | BB17: 325.92758 | BC17: 325.92758 | BD17: 0 | BE17: 326.13497 | BF17: 326.13497 | BG17: 0 | BH17: 326.34755 | BI17: 326.34755 | BJ17: 0 | BK17: 326.56887 | BL17: 326.56887 | BM17: 0 | BN17: 326.77485 | BO17: 326.77485 | BP17: 0 | BQ17: 326.98247 | BR17: 326.98247 | BS17: 0 | BT17: 327.20199 | BU17: 327.20199 | BV17: 0
A18: Net Margin % | B18: % | C18: 1.0536408 | F18: 1.558421 | I18: 1.5519167 | L18: 1.5455535 | O18: 1.5393449 | R18: 1.5332078 | U18: 1.5271677 | V18: 1.5424394 | X18: 1.5212704 | Y18: 1.5364831 | AA18: 1.5155013 | AB18: 1.5306563 | AD18: 1.509773 | AE18: 1.5248707 | AG18: 1.504135 | AH18: 1.5191763 | AJ18: 1.4986322 | AK18: 1.5136185 | AM18: 1.4932274 | AN18: 1.5081596 | AP18: 1.4878909 | AQ18: 1.5027698 | AS18: 1.4825831 | AT18: 1.4974089 | AV18: 1.4773974 | AW18: 1.4921714 | AY18: 1.4723368 | AZ18: 1.4870602 | BB18: 1.4673338 | BC18: 1.4820071 | BE18: 1.4623866 | BF18: 1.4770104 | BH18: 1.4575395 | BI18: 1.4721149 | BK18: 1.4528062 | BL18: 1.4673343 | BN18: 1.4480777 | BO18: 1.4625585 | BQ18: 1.443428 | BR18: 1.4578623 | BT18: 1.4389006 | BU18: 1.4532896
A20: FULL-YEAR SUMMARY
A21: Metric | B21: Unit | C21: FY24 Orig FC | D21: FY24 Rev FC | E21: FY24 Δ | F21: FY25 Orig FC | G21: FY25 Rev FC | H21: FY25 Δ
A22: Total Revenue | B22: $M | C22: 2536.3875 | D22: 2562.1006 | E22: 25.713005 | F22: 2670.4214 | G22: 2697.1257 | H22: 26.704214
A23: Gross Profit | B23: $M | C23: 2183.8297 | D23: 2183.8297 | E23: 0 | F23: 2299.2329 | G23: 2299.2329 | H23: 0
A24: Gross Margin % | B24: % | C24: 0.861 | D24: 0.84383549 | F24: 0.861 | G24: 0.8439505
A25: EBITDA | B25: $M | C25: 4785.3803 | D25: 4785.3803 | E25: 0 | F25: 4955.5285 | G25: 4955.5285 | H25: 0
A26: EBITDA Margin % | B26: % | C26: 1.8866913 | D26: 1.9055582 | F26: 1.8557103 | G26: 1.8742674
A27: Net Income | B27: $M | C27: 3776.611 | D27: 3776.611 | E27: 0 | F27: 3912.4063 | G27: 3912.4063 | H27: 0
A29: HOW ROLLING FORECAST WORKS IN PRACTICE:
A30: 1. LOCK DATE: Each month-end, advance the lock by 1. Columns left of lock = Actuals (immutable).
A31: 2. ORIGINAL FC: Base Case from IS sheet — the original annual plan submitted at start of FY.
A32: 3. REVISED FC: Mid-year reforecast — Revenue +2% H2-24 (pipeline beat), Payroll -3% (hiring freeze). Adjust REV_ADJ dict to change.
A33: 4. HORIZON: Always maintains 18-month forward view. As Dec-25 closes, Jan-26 gets added.
A34: 5. WHY CLIENTS PAY FOR THIS: Static budgets go stale by month 3. Rolling Forecast keeps decisions data-current.

Sheet SaaS_KPI_Tracker
A1: HubSpot (HUBS) — SaaS KPI Tracker | FY2024–FY2025 | Illustrative
A2: Note: KPIs derived from Revenue, IS, and Headcount schedules. CAC/LTV are illustrative proxies for demo purposes.
A3: KPI Metric | B3: Unit | C3: Jan-24 | D3: Feb-24 | E3: Mar-24 | F3: Apr-24 | G3: May-24 | H3: Jun-24 | I3: Jul-24 | J3: Aug-24 | K3: Sep-24 | L3: Oct-24 | M3: Nov-24 | N3: Dec-24 | O3: Jan-25 | P3: Feb-25 | Q3: Mar-25 | R3: Apr-25 | S3: May-25 | T3: Jun-25 | U3: Jul-25 | V3: Aug-25 | W3: Sep-25 | X3: Oct-25 | Y3: Nov-25 | Z3: Dec-25
A4: GROWTH METRICS
A5: ARR (Annualised Run Rate) | B5: USD $M | C5: 2334.7658 | D5: 2346.8324 | E5: 2358.8099 | F5: 2370.6996 | G5: 2382.5028 | H5: 2394.2208 | I5: 2405.8549 | J5: 2417.4062 | K5: 2428.876 | L5: 2440.2655 | M5: 2451.576 | N5: 2462.8086 | O5: 2473.9644 | P5: 2485.0446 | Q5: 2496.0503 | R5: 2506.9827 | S5: 2517.8429 | T5: 2528.6319 | U5: 2539.3508 | V5: 2550.0006 | W5: 2560.5825 | X5: 2571.0975 | Y5: 2581.5465 | Z5: 2591.9306
A6: MRR (Monthly Recurring Rev) | B6: USD $M | C6: 194.56382 | D6: 195.56937 | E6: 196.56749 | F6: 197.5583 | G6: 198.5419 | H6: 199.5184 | I6: 200.4879 | J6: 201.45051 | K6: 202.40633 | L6: 203.35546 | M6: 204.298 | N6: 205.23405 | O6: 206.1637 | P6: 207.08705 | Q6: 208.00419 | R6: 208.91523 | S6: 209.82024 | T6: 210.71932 | U6: 211.61256 | V6: 212.50005 | W6: 213.38188 | X6: 214.25812 | Y6: 215.12888 | Z6: 215.99422
A7: Total Revenue | B7: USD $M | C7: 205.96682 | D7: 206.97237 | E7: 207.97049 | F7: 208.9613 | G7: 209.9449 | H7: 210.9214 | I7: 211.8909 | J7: 212.85351 | K7: 213.80933 | L7: 214.75846 | M7: 215.701 | N7: 216.63705 | O7: 217.5667 | P7: 218.49005 | Q7: 219.40719 | R7: 220.31823 | S7: 221.22324 | T7: 222.12232 | U7: 223.01556 | V7: 223.90305 | W7: 224.78488 | X7: 225.66112 | Y7: 226.53188 | Z7: 227.39722
A8: MoM Revenue Growth | B8: % | C8: - | D8: 0.0048820938 | E8: 0.0048225014 | F8: 0.0047641803 | G8: 0.0047070968 | H8: 0.0046512182 | I8: 0.004596513 | J8: 0.0045429506 | K8: 0.0044905016 | L8: 0.0044391373 | M8: 0.0043888303 | N8: 0.0043395537 | O8: 0.0042912818 | P8: 0.0042439894 | Q8: 0.0041976523 | R8: 0.004152247 | S8: 0.0041077507 | T8: 0.0040641413 | U8: 0.0040213975 | V8: 0.0039794985 | W8: 0.0039384241 | X8: 0.0038981548 | Y8: 0.0038586716 | Z8: 0.0038199562
A9: CUSTOMER METRICS
A10: Ending Customers | C10: 205814.64 | D10: 206527.42 | E10: 207229.5 | F10: 207921.06 | G10: 208602.25 | H10: 209273.21 | I10: 209934.11 | J10: 210585.1 | K10: 211226.33 | L10: 211857.93 | M10: 212480.06 | N10: 213092.86 | O10: 213696.47 | P10: 214291.02 | Q10: 214876.66 | R10: 215453.51 | S10: 216021.7 | T10: 216581.38 | U10: 217132.66 | V10: 217675.67 | W10: 218210.53 | X10: 218737.37 | Y10: 219256.31 | Z10: 219767.47
A11: New Customers Added | C11: 3800 | D11: 3800 | E11: 3800 | F11: 3800 | G11: 3800 | H11: 3800 | I11: 3800 | J11: 3800 | K11: 3800 | L11: 3800 | M11: 3800 | N11: 3800 | O11: 3800 | P11: 3800 | Q11: 3800 | R11: 3800 | S11: 3800 | T11: 3800 | U11: 3800 | V11: 3800 | W11: 3800 | X11: 3800 | Y11: 3800 | Z11: 3800
A12: Churned Customers | C12: 3076.365 | D12: 3087.2195 | E12: 3097.9112 | F12: 3108.4426 | G12: 3118.8159 | H12: 3129.0337 | I12: 3139.0982 | J12: 3149.0117 | K12: 3158.7765 | L12: 3168.3949 | M12: 3177.869 | N12: 3187.2009 | O12: 3196.3929 | P12: 3205.447 | Q12: 3214.3653 | R12: 3223.1498 | S12: 3231.8026 | T12: 3240.3255 | U12: 3248.7207 | V12: 3256.9899 | W12: 3265.135 | X12: 3273.158 | Y12: 3281.0606 | Z12: 3288.8447
A13: Monthly Churn Rate | B13: % | C13: 0.015 | D13: 0.015 | E13: 0.015 | F13: 0.015 | G13: 0.015 | H13: 0.015 | I13: 0.015 | J13: 0.015 | K13: 0.015 | L13: 0.015 | M13: 0.015 | N13: 0.015 | O13: 0.015 | P13: 0.015 | Q13: 0.015 | R13: 0.015 | S13: 0.015 | T13: 0.015 | U13: 0.015 | V13: 0.015 | W13: 0.015 | X13: 0.015 | Y13: 0.015 | Z13: 0.015
A14: Net Revenue Retention (NRR) | B14: % | C14: 0.985 | D14: 0.98664167 | E14: 0.98664167 | F14: 0.98664167 | G14: 0.98664167 | H14: 0.98664167 | I14: 0.98664167 | J14: 0.98664167 | K14: 0.98664167 | L14: 0.98664167 | M14: 0.98664167 | N14: 0.98664167 | O14: 0.98664167 | P14: 0.98664167 | Q14: 0.98664167 | R14: 0.98664167 | S14: 0.98664167 | T14: 0.98664167 | U14: 0.98664167 | V14: 0.98664167 | W14: 0.98664167 | X14: 0.98664167 | Y14: 0.98664167 | Z14: 0.98664167
A15: ARPU (Avg Revenue / Customer) | B15: USD | C15: 947 | D15: 948.57833 | E15: 950.1593 | F15: 951.7429 | G15: 953.32913 | H15: 954.91802 | I15: 956.50955 | J15: 958.10373 | K15: 959.70057 | L15: 961.30007 | M15: 962.90224 | N15: 964.50707 | O15: 966.11458 | P15: 967.72478 | Q15: 969.33765 | R15: 970.95321 | S15: 972.57147 | T15: 974.19242 | U15: 975.81608 | V15: 977.44244 | W15: 979.07151 | X15: 980.70329 | Y15: 982.3378 | Z15: 983.97503
A16: PROFITABILITY METRICS
A17: Gross Profit | B17: USD $M | C17: 177.33743 | D17: 178.20321 | E17: 179.06259 | F17: 179.91568 | G17: 180.76256 | H17: 181.60333 | I17: 182.43807 | J17: 183.26688 | K17: 184.08984 | L17: 184.90704 | M17: 185.71856 | N17: 186.5245 | O17: 187.32493 | P17: 188.11993 | Q17: 188.90959 | R17: 189.69399 | S17: 190.47321 | T17: 191.24732 | U17: 192.0164 | V17: 192.78053 | W17: 193.53978 | X17: 194.29423 | Y17: 195.04395 | Z17: 195.78901
A18: Gross Margin % | B18: % | C18: 0.861 | D18: 0.861 | E18: 0.861 | F18: 0.861 | G18: 0.861 | H18: 0.861 | I18: 0.861 | J18: 0.861 | K18: 0.861 | L18: 0.861 | M18: 0.861 | N18: 0.861 | O18: 0.861 | P18: 0.861 | Q18: 0.861 | R18: 0.861 | S18: 0.861 | T18: 0.861 | U18: 0.861 | V18: 0.861 | W18: 0.861 | X18: 0.861 | Y18: 0.861 | Z18: 0.861
A19: EBITDA (Monthly) | B19: USD $M | C19: 276.84375 | D19: 408.53272 | E19: 408.79057 | F19: 409.05501 | G19: 409.33052 | H19: 409.59587 | I19: 409.85854 | J19: 410.13155 | K19: 410.41188 | L19: 410.67654 | M19: 410.93952 | N19: 411.21383 | O19: 411.48996 | P19: 411.76042 | Q19: 412.0147 | R19: 412.2793 | S19: 412.55571 | T19: 412.8257 | U19: 413.08926 | V19: 413.35938 | W19: 413.64057 | X19: 413.90232 | Y19: 414.16614 | Z19: 414.44503
A20: EBITDA Margin % | B20: % | C20: 1.3441182 | D20: 1.9738515 | E20: 1.9656181 | F20: 1.9575635 | G20: 1.9497045 | H20: 1.941936 | I20: 1.9342904 | J20: 1.9268253 | K20: 1.9195227 | L20: 1.9122717 | M20: 1.905135 | N20: 1.8981695 | O20: 1.8913279 | P20: 1.8845729 | Q20: 1.8778541 | R20: 1.87129 | S20: 1.8648842 | T20: 1.8585512 | U20: 1.8522889 | V20: 1.8461534 | W20: 1.8401619 | X20: 1.8341765 | Y20: 1.8282908 | Z20: 1.8225598
A21: UNIT ECONOMICS
A22: CAC (Customer Acq. Cost) | B22: USD | C22: 13484.526 | D22: 42922.895 | E22: 42950.632 | F22: 42979.053 | G22: 43008.632 | H22: 43037.132 | I22: 43065.342 | J22: 43094.632 | K22: 43124.684 | L22: 43153.079 | M22: 43181.289 | N22: 43210.684 | O22: 43240.263 | P22: 43269.237 | Q22: 43296.5 | R22: 43324.842 | S22: 43354.421 | T22: 43383.316 | U22: 43411.526 | V22: 43440.421 | W22: 43470.474 | X22: 43498.474 | Y22: 43526.684 | Z22: 43556.474
A23: LTV (Lifetime Value) | B23: USD | C23: 54357.8 | D23: 54448.396 | E23: 54539.144 | F23: 54630.042 | G23: 54721.092 | H23: 54812.294 | I23: 54903.648 | J23: 54995.154 | K23: 55086.813 | L23: 55178.624 | M23: 55270.588 | N23: 55362.706 | O23: 55454.977 | P23: 55547.402 | Q23: 55639.981 | R23: 55732.714 | S23: 55825.602 | T23: 55918.645 | U23: 56011.843 | V23: 56105.196 | W23: 56198.704 | X23: 56292.369 | Y23: 56386.19 | Z23: 56480.167
A24: LTV / CAC Ratio | B24: x | C24: 4.0311242 | D24: 1.2685164 | E24: 1.2698101 | F24: 1.2710853 | G24: 1.2723281 | H24: 1.2736047 | I24: 1.2748917 | J24: 1.2761486 | K24: 1.2773847 | L24: 1.2786718 | M24: 1.2799661 | N24: 1.2812272 | O24: 1.2824847 | P24: 1.283762 | Q24: 1.2850919 | R24: 1.2863916 | S24: 1.2876565 | T24: 1.2889435 | U24: 1.2902528 | V24: 1.2915436 | W24: 1.2928017 | X24: 1.2941229 | Y24: 1.2954396 | Z24: 1.2967112
A25: CAC Payback Period | B25: months | C25: 16.537984 | D25: 52.554832 | E25: 52.501291 | F25: 52.448617 | G25: 52.397384 | H25: 52.344864 | I25: 52.292023 | J25: 52.24052 | K25: 52.189967 | L25: 52.137435 | M25: 52.084711 | N25: 52.033444 | O25: 51.982425 | P25: 51.930706 | Q25: 51.876965 | R25: 51.824549 | S25: 51.773642 | T25: 51.721945 | U25: 51.669462 | V25: 51.617823 | W25: 51.567587 | X25: 51.514944 | Y25: 51.462583 | Z25: 51.412117
